Workbook

Sheet Fábricas
B2: Fábrica | C2: Ordem de vendas | D2: Razão Social | E2: Cnpj | F2: Inscrição Estadual St | G2: Endereço | H2: N | I2: Bairro | J2: CEP | K2: Cidade | L2: Estado
B3: Itu | C3: 5000 | D3: HNK BR INDUSTRIA DE BEBIDAS LTDA. | E3: 50.221.019/0001-36 | F3: 387000650117 | G3: Av Primo Schincariol | H3: 2222 | I3: Chácara Flórida | J3: 13312250 | K3: Itu | L3: SP
B4: Jacarei | C4: 5238 | D4: HNK BR INDUSTRIA DE BEBIDAS LTDA. | E4: 50.221.019/0104-41 | F4: 392558326113 | G4: Av Presidente Humberto de Alencar Castelo Branco | H4: 2911 | I4: Conjunto Habitacional Marinho | J4: 12321150 | K4: Jacareí | L4: SP
B5: Araraquara | C5: 5239 | D5: HNK BR INDUSTRIA DE BEBIDAS LTDA. | E5: 50.221.019/0105-22 | F5: 181661963118 | G5: Av Marginal 01 | H5: 701 | I5: Chácara Catani | J5: 14808080 | K5: Araraquara | L5: SP
B6: Ponta Grossa | C6: 5231 | D6: HNK BR INDUSTRIA DE BEBIDAS LTDA. | E6: 50.221.019/0097-88 | F6: 911.300.50.81 | G6: Av Tocantins | H6: 199 | I6: Cara-Cara | J6: 84043610 | K6: Ponta Grossa | L6: PR

Sheet Proposta Assaí Outubro'25
AH2: =SUBTOTAL(9,AH5:AH57) -> 1067795.8 | AK2: =SUBTOTAL(9,AK5:AK57) -> 174579.83 | AN2: =SUBTOTAL(9,AN5:AN57) -> 1512745.7
B3: =SUBTOTAL(9,B5:B57) -> #N/A | V3: SUGESTÃO DE PREÇO OUT'25 | Y3: =SUBTOTAL(9,Y5:Y57) -> 2606749.2 | AA3: =SUBTOTAL(9,AA5:AA57) -> 30361.505 | AC3: Total de Investimento Gerado | AD3: TT Investimento Liberado | AE3: Diferença | AH3: Verba Calendario TPR | AK3: Back Margem | AN3: Verba Adicional | AP3: =SUBTOTAL(9,AP5:AP57) -> 2755121.3 | AV3: Margem entregue no promo
A4: Coeficiente | B4: HL Act Restrito | C4: Em caixas | D4: Categoria | E4: Marcas | F4: CÓDIGO SAP HNK | G4: CÓDIGO | H4: PRODUTO | I4: CX | J4: PALETE | K4: CARGA | L4: QTDE COMPRA | M4: QTDE PALETE | N4: QTDE CARRO | O4: CUSTO CX NF | P4: Custo Unitário | Q4: VERBA SELL IN CX | R4: * VERBA SELL IN UND | S4: VERBA ADIC CX | T4: * VERBA ADIC UND | U4: Total Investimento Liberado | V4: PREÇO REGULAR | W4: PREÇO PROMO | X4: PREÇO LIBERADO TELE | Y4: VERBA TOTAL SELL IN | Z4: TOTAL PEDIDO NF | AA4: HL | AG4: R$/HL | AH4: Verba Gerado | AI4: Verba unidade | AJ4: R$/HL | AK4: Verba Gerado | AL4: Verba unidade | AM4: R$/HL | AN4: Verba Gerado | AO4: Verba unidade | AP4: Gerado total | AQ4: Unidade total | AR4: VERBA TOTAL SELL IN | AS4: Saving | AT4: CUSTO UNI. NF | AU4: NOVO CUSTO | AX4: 50% Volume preço Promo | AY4: 50% Volume preço Televendas | AZ4: Preço Médio | BA4: Margem entregue | BC4: Cidade | BD4: Razão social | BE4: CNPJ | BF4: Inscrição estadual | BG4: Endereço | BH4: Número | BI4: Bairro | BJ4: Cidade | BK4: Estado | BL4: Cep
A5: 0.03228 | B5: =VLOOKUP(F5,Planilha3!D:F,3,0) -> 1663.6933 | C5: =B5/A5 -> 51539.444 | D5: Mainstream | E5: Amstel | F5: 904113 | G5: 1052772 | H5: CERVEJA AMSTEL 269ML | I5: 12 | J5: 336 | K5: =J5*24 -> 8064 | L5: 161280 | M5: =L5/J5 -> 480 | N5: =L5/K5 -> 20 | O5: 33.16 | P5: =O5/I5 -> 2.7633333 | Q5: =R5*I5 -> 0.6 | R5: 0.05 | S5: =T5*I5 -> 3.6 | T5: 0.3 | U5: =SUM(R5,T5) -> 0.35 | V5: =VLOOKUP(F5,'[1]Proposta HNK para Tenda'!$F:$T,15,0) -> 3.29 | W5: =VLOOKUP(F5,'[1]Proposta HNK para Tenda'!$F:$U,16,0) -> 3.09 | X5: 2.79 | Y5: =L5*(Q5+S5) -> 677376 | Z5: =L5*O5 -> 5348044.8 | AA5: =L5*12*0.269/100 -> 5206.1184 | AC5: =SUM(AI5,AL5,AO5) -> 0.3681265 | AD5: =SUM(R5,T5) -> 0.35 | AE5: =AC5-AD5 -> 0.0181265 | AG5: 19.98 | AH5: =AG5*AA5 -> 104018.25 | AI5: =AH5/L5/I5 -> 0.0537462 | AJ5: 23.87 | AK5: =AJ5*AA5 -> 124270.05 | AL5: =AK5/L5/I5 -> 0.0642103 | AM5: 93 | AN5: =AM5*AA5 -> 484169.01 | AO5: =AN5/L5/I5 -> 0.25017 | AP5: =SUM(AH5,AK5,AN5) -> 712457.3 | AQ5: =SUM(AI5,AL5,AO5) -> 0.3681265 | AR5: =Y5 -> 677376 | AS5: =AP5-AR5 -> 35081.303 | AT5: =O5/I5 -> 2.7633333 | AU5: =AT5-R5-T5 -> 2.4133333 | AV5: =(W5-AU5)/W5 -> 0.21898598 | AX5: =W5*50% -> 1.545 | AY5: =X5*50% -> 1.395 | AZ5: =AX5+AY5 -> 2.94 | BA5: =(W5-X5)/W5 -> 0.097087379 | BC5: Itu | BD5: HNK BR INDUSTRIA DE BEBIDAS LTDA. | BE5: 50.221.019/0001-36 | BF5: 387000650117 | BG5: Av Primo Schincariol | BH5: 2222 | BI5: Chácara Flórida | BJ5: 13312250 | BK5: Itu | BL5: SP
A6: 0.042 | B6: =VLOOKUP(F6,Planilha3!D:F,3,0) -> 1031.9338 | C6: =B6/A6 -> 24569.852 | D6: Mainstream | E6: Amstel | F6: 904952 | G6: 1193288 | H6: CERVEJA AMSTEL 350ML SLEEK | I6: 12 | J6: 280 | K6: =J6*24 -> 6720 | L6: =K6*8 -> 53760 | M6: =L6/J6 -> 192 | N6: =L6/K6 -> 8 | O6: 39.21 | P6: =O6/I6 -> 3.2675 | Q6: =R6*I6 -> 1.2 | R6: 0.1 | S6: =T6*I6 -> 3.24 | T6: 0.27 | U6: =SUM(R6,T6) -> 0.37 | V6: =VLOOKUP(F6,'[1]Proposta HNK para Tenda'!$F:$T,15,0) -> 3.89 | W6: =VLOOKUP(F6,'[1]Proposta HNK para Tenda'!$F:$U,16,0) -> 3.69 | X6: 3.29 | Y6: =L6*(Q6+S6) -> 238694.4 | Z6: =L6*O6 -> 2107929.6 | AA6: =L6*12*0.35/100 -> 2257.92 | AC6: =SUM(AI6,AL6,AO6) -> 0.378 | AD6: =SUM(R6,T6) -> 0.37 | AE6: =AC6-AD6 -> 0.008 | AG6: 21.4 | AH6: =AG6*AA6 -> 48319.488 | AI6: =AH6/L6/I6 -> 0.0749 | AJ6: 21.6 | AK6: =AJ6*AA6 -> 48771.072 | AL6: =AK6/L6/I6 -> 0.0756 | AM6: 65 | AN6: =AM6*AA6 -> 146764.8 | AO6: =AN6/L6/I6 -> 0.2275 | AP6: =SUM(AH6,AK6,AN6) -> 243855.36 | AQ6: =SUM(AI6,AL6,AO6) -> 0.378 | AR6: =Y6 -> 238694.4 | AS6: =AP6-AR6 -> 5160.96 | AT6: =O6/I6 -> 3.2675 | AU6: =AT6-R6-T6 -> 2.8975 | AV6: =(W6-AU6)/W6 -> 0.21476965 | AX6: =W6*50% -> 1.845 | AY6: =X6*50% -> 1.645 | AZ6: =AX6+AY6 -> 3.49 | BA6: =(W6-X6)/W6 -> 0.10840108 | BC6: Jacarei | BD6: HNK BR INDUSTRIA DE BEBIDAS LTDA. | BE6: 50.221.019/0104-41 | BF6: 392558326113 | BG6: Av Presidente Humberto de Alencar Castelo Branco | BH6: 2911 | BI6: Conjunto Habitacional Marinho | BJ6: 12321150 | BK6: Jacareí | BL6: SP
A7: 0.072 | B7: =VLOOKUP(F7,Planilha3!D:F,3,0) -> 40.23064 | C7: =B7/A7 -> 558.75888 | D7: Mainstream | E7: Amstel | F7: 905052 | G7: 1207152 | H7: CERVEJA AMSTEL LN 355ML | I7: 12 | J7: 175 | K7: =J7*24 -> 4200 | L7: 1400 | M7: =L7/J7 -> 8 | N7: =L7/K7 -> 0.33333333 | O7: 47.28 | P7: =O7/I7 -> 3.94 | Q7: =R7*I7 -> 0.6 | R7: 0.05 | S7: =T7*I7 -> 2.4 | T7: 0.2 | U7: =SUM(R7,T7) -> 0.25 | V7: =VLOOKUP(F7,'[1]Proposta HNK para Tenda'!$F:$T,15,0) -> 4.69 | W7: =VLOOKUP(F7,'[1]Proposta HNK para Tenda'!$F:$U,16,0) -> 4.49 | Y7: =L7*(Q7+S7) -> 4200 | Z7: =L7*O7 -> 66192 | AA7: =L7*12*0.355/100 -> 59.64 | AC7: =SUM(AI7,AL7,AO7) -> 0.1662465 | AD7: =SUM(R7,T7) -> 0.25 | AE7: =AC7-AD7 -> -0.0837535 | AG7: 21.03 | AH7: =AG7*AA7 -> 1254.2292 | AI7: =AH7/L7/I7 -> 0.0746565 | AJ7: 25.8 | AK7: =AJ7*AA7 -> 1538.712 | AL7: =AK7/L7/I7 -> 0.09159 | AM7: 0 | AN7: =AM7*AA7 -> 0 | AO7: =AN7/L7/I7 -> 0 | AP7: =SUM(AH7,AK7,AN7) -> 2792.9412 | AQ7: =SUM(AI7,AL7,AO7) -> 0.1662465 | AR7: =Y7 -> 4200 | AS7: =AP7-AR7 -> -1407.0588 | AT7: =O7/I7 -> 3.94 | AU7: =AT7-R7-T7 -> 3.69 | AV7: =(W7-AU7)/W7 -> 0.17817372 | AX7: =W7*100% -> 4.49 | AY7: =X7*50% -> 0 | AZ7: =AX7+AY7 -> 4.49 | BC7: Itu | BD7: HNK BR INDUSTRIA DE BEBIDAS LTDA. | BE7: 50.221.019/0001-36 | BF7: 387000650117 | BG7: Av Primo Schincariol | BH7: 2222 | BI7: Chácara Flórida | BJ7: 13312250 | BK7: Itu | BL7: SP
A8: =0.275*12/100 -> 0.033 | B8: =VLOOKUP(F8,Planilha3!D:F,3,0) -> #N/A | C8: =B8/A8 -> #N/A | D8: Mainstream | E8: Amstel | F8: 904632 | G8: 1155684 | H8: CERVEJA AMSTEL ULTRA 269 ML | I8: 12 | J8: 364 | K8: =J8*24 -> 8736 | L8: =J8*2 -> 728 | M8: =L8/J8 -> 2 | N8: =L8/K8 -> 0.083333333 | O8: 39.26 | P8: =O8/I8 -> 3.2716667 | Q8: =R8*I8 -> 1.2 | R8: 0.1 | S8: =T8*I8 -> 1.56 | T8: 0.13 | U8: =SUM(R8,T8) -> 0.23 | V8: 3.99 | W8: 3.49 | Y8: =L8*(Q8+S8) -> 2009.28 | Z8: =L8*O8 -> 28581.28 | AA8: =L8*12*0.275/100 -> 24.024 | AC8: =SUM(AI8,AL8,AO8) -> 0.2377375 | AD8: =SUM(R8,T8) -> 0.23 | AE8: =AC8-AD8 -> 0.0077375 | AG8: 86.45 | AH8: =AG8*AA8 -> 2076.8748 | AI8: =AH8/L8/I8 -> 0.2377375 | AJ8: 0 | AK8: =AJ8*AA8 -> 0 | AL8: =AK8/L8/I8 -> 0 | AM8: 0 | AN8: =AM8*AA8 -> 0 | AO8: =AN8/L8/I8 -> 0 | AP8: =SUM(AH8,AK8,AN8) -> 2076.8748 | AQ8: =SUM(AI8,AL8,AO8) -> 0.2377375 | AR8: =Y8 -> 2009.28 | AS8: =AP8-AR8 -> 67.5948 | AT8: =O8/I8 -> 3.2716667 | AU8: =AT8-R8-T8 -> 3.0416667 | AV8: =(W8-AU8)/W8 -> 0.12846227 | AX8: =W8*100% -> 3.49 | AY8: =X8*50% -> 0 | AZ8: =AX8+AY8 -> 3.49 | BC8: Itu | BD8: HNK BR INDUSTRIA DE BEBIDAS LTDA. | BE8: 50.221.019/0001-36 | BF8: 387000650117 | BG8: Av Primo Schincariol | BH8: 2222 | BI8: Chácara Flórida | BJ8: 13312250 | BK8: Itu | BL8: SP
A9: =0.275*12/100 -> 0.033 | B9: =VLOOKUP(F9,Planilha3!D:F,3,0) -> 7.6058015 | C9: =B9/A9 -> 230.47883 | D9: Mainstream | E9: Amstel | F9: 904631 | G9: 1160860 | H9: CERVEJA AMSTEL ULTRA LN 275 ML | I9: 12 | J9: 196 | K9: =J9*24 -> 4704 | L9: =J9*5 -> 980 | M9: =L9/J9 -> 5 | N9: =L9/K9 -> 0.20833333 | O9: 47.13 | P9: =O9/I9 -> 3.9275 | Q9: =R9*I9 -> 0 | R9: 0 | S9: =T9*I9 -> 0 | T9: 0 | U9: =SUM(R9,T9) -> 0 | V9: =VLOOKUP(F9,'[1]Proposta HNK para Tenda'!$F:$T,15,0) -> 4.79 | W9: =VLOOKUP(F9,'[1]Proposta HNK para Tenda'!$F:$U,16,0) -> 4.79 | Y9: =L9*(Q9+S9) -> 0 | Z9: =L9*O9 -> 46187.4 | AA9: =L9*12*0.275/100 -> 32.34 | AC9: =SUM(AI9,AL9,AO9) -> 0 | AD9: =SUM(R9,T9) -> 0 | AE9: =AC9-AD9 -> 0 | AG9: 0 | AH9: =AG9*AA9 -> 0 | AI9: =AH9/L9/I9 -> 0 | AK9: =AJ9*AA9 -> 0 | AL9: =AK9/L9/I9 -> 0 | AM9: 0 | AN9: =AM9*AA9 -> 0 | AO9: =AN9/L9/I9 -> 0 | AP9: =SUM(AH9,AK9,AN9) -> 0 | AQ9: =SUM(AI9,AL9,AO9) -> 0 | AR9: =Y9 -> 0 | AS9: =AP9-AR9 -> 0 | AT9: =O9/I9 -> 3.9275 | AU9: =AT9-R9-T9 -> 3.9275 | AV9: =(W9-AU9)/W9 -> 0.18006263 | AX9: =W9*100% -> 4.79 | AY9: =X9*50% -> 0 | AZ9: =AX9+AY9 -> 4.79 | BC9: Itu | BD9: HNK BR INDUSTRIA DE BEBIDAS LTDA. | BE9: 50.221.019/0001-36 | BF9: 387000650117 | BG9: Av Primo Schincariol | BH9: 2222 | BI9: Chácara Flórida | BJ9: 13312250 | BK9: Itu | BL9: SP
A10: 0.03228 | B10: =VLOOKUP(F10,Planilha3!D:F,3,0) -> 113.71405 | C10: =B10/A10 -> 3522.7399 | D10: Premium | E10: Eisenbahn | F10: 904194 | G10: 1153719 | H10: CERVEJA EISENBAHN PILSEN 269ML | I10: 12 | J10: 364 | K10: =J10*24 -> 8736 | L10: 17472 | M10: =L10/J10 -> 48 | N10: =L10/K10 -> 2 | O10: 31.52 | P10: =O10/I10 -> 2.6266667 | Q10: =R10*I10 -> 0 | R10: 0 | S10: =T10*I10 -> 0 | T10: 0 | U10: =SUM(R10,T10) -> 0 | V10: 3.09 | W10: 3.09 | Y10: =L10*(Q10+S10) -> 0 | Z10: =L10*O10 -> 550717.44 | AA10: =L10*12*0.269/100 -> 563.99616 | AC10: =SUM(AI10,AL10,AO10) -> 0 | AD10: =SUM(R10,T10) -> 0 | AE10: =AC10-AD10 -> 0 | AG10: 0 | AH10: =AG10*AA10 -> 0 | AI10: =AH10/L10/I10 -> 0 | AK10: =AJ10*AA10 -> 0 | AL10: =AK10/L10/I10 -> 0 | AM10: 0 | AN10: =AM10*AA10 -> 0 | AO10: =AN10/L10/I10 -> 0 | AP10: =SUM(AH10,AK10,AN10) -> 0 | AQ10: =SUM(AI10,AL10,AO10) -> 0 | AR10: =Y10 -> 0 | AS10: =AP10-AR10 -> 0 | AT10: =O10/I10 -> 2.6266667 | AU10: =AT10-R10-T10 -> 2.6266667 | AV10: =(W10-AU10)/W10 -> 0.14994606 | AX10: =W10*100% -> 3.09 | AY10: =X10*50% -> 0 | AZ10: =AX10+AY10 -> 3.09 | BC10: Itu | BD10: HNK BR INDUSTRIA DE BEBIDAS LTDA. | BE10: 50.221.019/0001-36 | BF10: 387000650117 | BG10: Av Primo Schincariol | BH10: 2222 | BI10: Chácara Flórida | BJ10: 13312250 | BK10: Itu | BL10: SP
A11: 0.042 | B11: =VLOOKUP(F11,Planilha3!D:F,3,0) -> 719.15382 | C11: =B11/A11 -> 17122.71 | D11: Premium | E11: Eisenbahn | F11: 903750 | G11: 1055249 | H11: CERVEJA EISENBAHN PILSEN 350ML | I11: 12 | J11: 280 | K11: =J11*24 -> 6720 | L11: 20160 | M11: =L11/J11 -> 72 | N11: =L11/K11 -> 3 | O11: 40.7 | P11: =O11/I11 -> 3.3916667 | Q11: =R11*I11 -> 0 | R11: 0 | S11: =T11*I11 -> 0 | T11: 0 | U11: =SUM(R11,T11) -> 0 | V11: 3.99 | W11: 3.99 | Y11: =L11*(Q11+S11) -> 0 | Z11: =L11*O11 -> 820512 | AA11: =L11*12*0.35/100 -> 846.72 | AC11: =SUM(AI11,AL11,AO11) -> 0 | AD11: =SUM(R11,T11) -> 0 | AE11: =AC11-AD11 -> 0 | AG11: 0 | AH11: =AG11*AA11 -> 0 | AI11: =AH11/L11/I11 -> 0 | AK11: =AJ11*AA11 -> 0 | AL11: =AK11/L11/I11 -> 0 | AM11: 0 | AN11: =AM11*AA11 -> 0 | AO11: =AN11/L11/I11 -> 0 | AP11: =SUM(AH11,AK11,AN11) -> 0 | AQ11: =SUM(AI11,AL11,AO11) -> 0 | AR11: =Y11 -> 0 | AS11: =AP11-AR11 -> 0 | AT11: =O11/I11 -> 3.3916667 | AU11: =AT11-R11-T11 -> 3.3916667 | AV11: =(W11-AU11)/W11 -> 0.14995823 | AX11: =W11*100% -> 3.99 | AY11: =X11*50% -> 0 | AZ11: =AX11+AY11 -> 3.99 | BC11: Itu | BD11: HNK BR INDUSTRIA DE BEBIDAS LTDA. | BE11: 50.221.019/0001-36 | BF11: 387000650117 | BG11: Av Primo Schincariol | BH11: 2222 | BI11: Chácara Flórida | BJ11: 13312250 | BK11: Itu | BL11: SP
A12: 0.0426 | B12: =VLOOKUP(F12,Planilha3!D:F,3,0) -> 44.325777 | C12: =B12/A12 -> 1040.5112 | D12: Premium | E12: Eisenbahn | F12: 901781 | G12: 1016972 | H12: CERVEJA EISENBAHN PILSEN LN 355ML | I12: 12 | J12: 175 | K12: =J12*24 -> 4200 | L12: =J12*10 -> 1750 | M12: =L12/J12 -> 10 | N12: =L12/K12 -> 0.41666667 | O12: 51.92 | P12: =O12/I12 -> 4.3266667 | Q12: =R12*I12 -> 3 | R12: 0.25 | S12: =T12*I12 -> 0.36 | T12: 0.03 | U12: =SUM(R12,T12) -> 0.28 | V12: 5.09 | W12: 4.19 | Y12: =L12*(Q12+S12) -> 5880 | Z12: =L12*O12 -> 90860 | AA12: =L12*12*0.355/100 -> 74.55 | AC12: =SUM(AI12,AL12,AO12) -> 0.28826 | AD12: =SUM(R12,T12) -> 0.28 | AE12: =AC12-AD12 -> 0.00826 | AG12: 81.2 | AH12: =AG12*AA12 -> 6053.46 | AI12: =AH12/L12/I12 -> 0.28826 | AK12: =AJ12*AA12 -> 0 | AL12: =AK12/L12/I12 -> 0 | AM12: 0 | AN12: =AM12*AA12 -> 0 | AO12: =AN12/L12/I12 -> 0 | AP12: =SUM(AH12,AK12,AN12) -> 6053.46 | AQ12: =SUM(AI12,AL12,AO12) -> 0.28826 | AR12: =Y12 -> 5880 | AS12: =AP12-AR12 -> 173.46 | AT12: =O12/I12 -> 4.3266667 | AU12: =AT12-R12-T12 -> 4.0466667 | AV12: =(W12-AU12)/W12 -> 0.034208433 | AX12: =W12*100% -> 4.19 | AY12: =X12*50% -> 0 | AZ12: =AX12+AY12 -> 4.19 | BC12: Itu | BD12: HNK BR INDUSTRIA DE BEBIDAS LTDA. | BE12: 50.221.019/0001-36 | BF12: 387000650117 | BG12: Av Primo Schincariol | BH12: 2222 | BI12: Chácara Flórida | BJ12: 13312250 | BK12: Itu | BL12: SP
A13: 0.042 | B13: =VLOOKUP(F13,Planilha3!D:F,3,0) -> 32.20274 | C13: =B13/A13 -> 766.73189 | D13: Premium | E13: Eisenbahn | F13: 904772 | G13: 1170146 | H13: CERVEJA EISENBAHN UNFILTERED LA 350ML | I13: 12 | J13: 280 | K13: =J13*24 -> 6720 | L13: =K13*1 -> 6720 | M13: =L13/J13 -> 24 | N13: =L13/K13 -> 1 | O13: 40.7 | P13: =O13/I13 -> 3.3916667 | Q13: =R13*I13 -> 0 | R13: 0 | S13: =T13*I13 -> 0 | T13: 0 | U13: =SUM(R13,T13) -> 0 | V13: 3.99 | W13: 3.99 | Y13: =L13*(Q13+S13) -> 0 | Z13: =L13*O13 -> 273504 | AA13: =L13*12*0.35/100 -> 282.24 | AC13: =SUM(AI13,AL13,AO13) -> 0 | AD13: =SUM(R13,T13) -> 0 | AE13: =AC13-AD13 -> 0 | AG13: 0 | AH13: =AG13*AA13 -> 0 | AI13: =AH13/L13/I13 -> 0 | AK13: =AJ13*AA13 -> 0 | AL13: =AK13/L13/I13 -> 0 | AM13: 0 | AN13: =AM13*AA13 -> 0 | AO13: =AN13/L13/I13 -> 0 | AP13: =SUM(AH13,AK13,AN13) -> 0 | AQ13: =SUM(AI13,AL13,AO13) -> 0 | AR13: =Y13 -> 0 | AS13: =AP13-AR13 -> 0 | AT13: =O13/I13 -> 3.3916667 | AU13: =AT13-R13-T13 -> 3.3916667 | AV13: =(W13-AU13)/W13 -> 0.14995823 | AX13: =W13*100% -> 3.99 | AY13: =X13*50% -> 0 | AZ13: =AX13+AY13 -> 3.99 | BC13: Itu | BD13: HNK BR INDUSTRIA DE BEBIDAS LTDA. | BE13: 50.221.019/0001-36 | BF13: 387000650117 | BG13: Av Primo Schincariol | BH13: 2222 | BI13: Chácara Flórida | BJ13: 13312250 | BK13: Itu | BL13: SP
A14: 0.0426 | B14: =VLOOKUP(F14,Planilha3!D:F,3,0) -> 1.8908876 | C14: =B14/A14 -> 44.387033 | D14: Premium | E14: Eisenbahn | F14: 904771 | G14: 1170180 | H14: CERVEJA EISENBAHN UNFILTERED LN 355ML | I14: 12 | J14: 175 | K14: =J14*24 -> 4200 | L14: =K14*1 -> 4200 | M14: =L14/J14 -> 24 | N14: =L14/K14 -> 1 | O14: 51.92 | P14: =O14/I14 -> 4.3266667 | Q14: =R14*I14 -> 3 | R14: 0.25 | S14: =T14*I14 -> 0.36 | T14: 0.03 | U14: =SUM(R14,T14) -> 0.28 | V14: 5.09 | W14: 4.19 | Y14: =L14*(Q14+S14) -> 14112 | Z14: =L14*O14 -> 218064 | AA14: =L14*12*0.355/100 -> 178.92 | AC14: =SUM(AI14,AL14,AO14) -> 0.28826 | AD14: =SUM(R14,T14) -> 0.28 | AE14: =AC14-AD14 -> 0.00826 | AG14: 81.2 | AH14: =AG14*AA14 -> 14528.304 | AI14: =AH14/L14/I14 -> 0.28826 | AK14: =AJ14*AA14 -> 0 | AL14: =AK14/L14/I14 -> 0 | AM14: 0 | AN14: =AM14*AA14 -> 0 | AO14: =AN14/L14/I14 -> 0 | AP14: =SUM(AH14,AK14,AN14) -> 14528.304 | AQ14: =SUM(AI14,AL14,AO14) -> 0.28826 | AR14: =Y14 -> 14112 | AS14: =AP14-AR14 -> 416.304 | AT14: =O14/I14 -> 4.3266667 | AU14: =AT14-R14-T14 -> 4.0466667 | AV14: =(W14-AU14)/W14 -> 0.034208433 | AX14: =W14*100% -> 4.19 | AY14: =X14*50% -> 0 | AZ14: =AX14+AY14 -> 4.19 | BC14: Itu | BD14: HNK BR INDUSTRIA DE BEBIDAS LTDA. | BE14: 50.221.019/0001-36 | BF14: 387000650117 | BG14: Av Primo Schincariol | BH14: 2222 | BI14: Chácara Flórida | BJ14: 13312250 | BK14: Itu | BL14: SP
A15: =0.269*8/100 -> 0.02152 | B15: =VLOOKUP(F15,Planilha3!D:F,3,0) -> 105.66937 | C15: =B15/A15 -> 4910.2865 | D15: Premium | E15: Heineken | F15: 904895 | G15: 1208101 | H15: CERVEJA HEINEKEN 0% ALCOOL LA 269ML | I15: 8 | J15: 520 | K15: =J15*26 -> 13520 | L15: 40560 | M15: =L15/J15 -> 78 | N15: =L15/K15 -> 3 | O15: 31.21 | P15: =O15/I15 -> 3.90125 | Q15: =R15*I15 -> 0.8 | R15: 0.1 | S15: =T15*I15 -> 0.64 | T15: 0.08 | U15: =SUM(R15,T15) -> 0.18 | V15: =VLOOKUP(F15,'[1]Proposta HNK para Tenda'!$F:$T,15,0) -> 4.59 | W15: =VLOOKUP(F15,'[1]Proposta HNK para Tenda'!$F:$U,16,0) -> 3.99 | Y15: =L15*(Q15+S15) -> 58406.4 | Z15: =L15*O15 -> 1265877.6 | AA15: =L15*8*0.269/100 -> 872.8512 | AC15: =SUM(AI15,AL15,AO15) -> 0.1905596 | AD15: =SUM(R15,T15) -> 0.18 | AE15: =AC15-AD15 -> 0.0105596 | AG15: 70.84 | AH15: =AG15*AA15 -> 61832.779 | AI15: =AH15/L15/I15 -> 0.1905596 | AK15: =AJ15*AA15 -> 0 | AL15: =AK15/L15/I15 -> 0 | AM15: 0 | AN15: =AM15*AA15 -> 0 | AO15: =AN15/L15/I15 -> 0 | AP15: =SUM(AH15,AK15,AN15) -> 61832.779 | AQ15: =SUM(AI15,AL15,AO15) -> 0.1905596 | AR15: =Y15 -> 58406.4 | AS15: =AP15-AR15 -> 3426.379 | AT15: =O15/I15 -> 3.90125 | AU15: =AT15-R15-T15 -> 3.72125 | AV15: =(W15-AU15)/W15 -> 0.06735589 | AX15: =W15*100% -> 3.99 | AY15: =X15*50% -> 0 | AZ15: =AX15+AY15 -> 3.99 | BC15: Ponta Grossa | BD15: HNK BR INDUSTRIA DE BEBIDAS LTDA. | BE15: 50.221.019/0097-88 | BF15: 911.300.50.81 | BG15: Av Tocantins | BH15: 199 | BI15: Cara-Cara | BJ15: 84043610 | BK15: Ponta Grossa | BL15: PR
A16: 0.042 | B16: =VLOOKUP(F16,Planilha3!D:F,3,0) -> 151.60164 | C16: =B16/A16 -> 3609.5629 | D16: Premium | E16: Heineken | F16: 904961 | G16: 1193325 | H16: CERVEJA HEINEKEN 0% ALCOOL LA 350ML SLEEK | I16: 12 | J16: 280 | K16: =J16*26 -> 7280 | L16: 21840 | M16: =L16/J16 -> 78 | N16: =L16/K16 -> 3 | O16: 58.04 | P16: =O16/I16 -> 4.8366667 | Q16: =R16*I16 -> 1.2 | R16: 0.1 | S16: =T16*I16 -> 4.2 | T16: 0.35 | U16: =SUM(R16,T16) -> 0.45 | V16: =VLOOKUP(F16,'[1]Proposta HNK para Tenda'!$F:$T,15,0) -> 5.69 | W16: =VLOOKUP(F16,'[1]Proposta HNK para Tenda'!$F:$U,16,0) -> 5.29 | Y16: =L16*(Q16+S16) -> 117936 | Z16: =L16*O16 -> 1267593.6 | AA16: =L16*12*0.35/100 -> 917.28 | AC16: =SUM(AI16,AL16,AO16) -> 0.47901 | AD16: =SUM(R16,T16) -> 0.45 | AE16: =AC16-AD16 -> 0.02901 | AG16: 33.86 | AH16: =AG16*AA16 -> 31059.101 | AI16: =AH16/L16/I16 -> 0.11851 | AK16: =AJ16*AA16 -> 0 | AL16: =AK16/L16/I16 -> 0 | AM16: 103 | AN16: =AM16*AA16 -> 94479.84 | AO16: =AN16/L16/I16 -> 0.3605 | AP16: =SUM(AH16,AK16,AN16) -> 125538.94 | AQ16: =SUM(AI16,AL16,AO16) -> 0.47901 | AR16: =Y16 -> 117936 | AS16: =AP16-AR16 -> 7602.9408 | AT16: =O16/I16 -> 4.8366667 | AU16: =AT16-R16-T16 -> 4.3866667 | AV16: =(W16-AU16)/W16 -> 0.17076244 | AX16: =W16*100% -> 5.29 | AY16: =X16*50% -> 0 | AZ16: =AX16+AY16 -> 5.29 | BC16: Ponta Grossa | BD16: HNK BR INDUSTRIA DE BEBIDAS LTDA. | BE16: 50.221.019/0097-88 | BF16: 911.300.50.81 | BG16: Av Tocantins | BH16: 199 | BI16: Cara-Cara | BJ16: 84043610 | BK16: Ponta Grossa | BL16: PR
A17: 0.0792 | B17: =VLOOKUP(F17,Planilha3!D:F,3,0) -> 143.24875 | C17: =B17/A17 -> 1808.6964 | D17: Premium | E17: Heineken | F17: 903996 | G17: 1140139 | H17: CERVEJA HEINEKEN 0% ALCOOL LN 330ML | I17: 24 | J17: 91 | K17: =J17*26 -> 2366 | L17: =J17*20 -> 1820 | M17: =L17/J17 -> 20 | N17: =L17/K17 -> 0.76923077 | O17: 142.6 | P17: =O17/I17 -> 5.9416667 | Q17: =R17*I17 -> 1.2 | R17: 0.05 | S17: =T17*I17 -> 0.24 | T17: 0.01 | U17: =SUM(R17,T17) -> 0.06 | V17: =VLOOKUP(F17,'[1]Proposta HNK para Tenda'!$F:$T,15,0) -> 6.99 | W17: =VLOOKUP(F17,'[1]Proposta HNK para Tenda'!$F:$U,16,0) -> 6.59 | Y17: =L17*(Q17+S17) -> 2620.8 | Z17: =L17*O17 -> 259532 | AA17: =L17*24*0.33/100 -> 144.144 | AC17: =SUM(AI17,AL17,AO17) -> 0.068508 | AD17: =SUM(R17,T17) -> 0.06 | AE17: =AC17-AD17 -> 0.008508 | AG17: 20.76 | AH17: =AG17*AA17 -> 2992.4294 | AI17: =AH17/L17/I17 -> 0.068508 | AK17: =AJ17*AA17 -> 0 | AL17: =AK17/L17/I17 -> 0 | AM17: 0 | AN17: =AM17*AA17 -> 0 | AO17: =AN17/L17/I17 -> 0 | AP17: =SUM(AH17,AK17,AN17) -> 2992.4294 | AQ17: =SUM(AI17,AL17,AO17) -> 0.068508 | AR17: =Y17 -> 2620.8 | AS17: =AP17-AR17 -> 371.62944 | AT17: =O17/I17 -> 5.9416667 | AU17: =AT17-R17-T17 -> 5.8816667 | AV17: =(W17-AU17)/W17 -> 0.10748609 | AX17: =W17*100% -> 6.59 | AY17: =X17*50% -> 0 | AZ17: =AX17+AY17 -> 6.59 | BC17: Ponta Grossa | BD17: HNK BR INDUSTRIA DE BEBIDAS LTDA. | BE17: 50.221.019/0097-88 | BF17: 911.300.50.81 | BG17: Av Tocantins | BH17: 199 | BI17: Cara-Cara | BJ17: 84043610 | BK17: Ponta Grossa | BL17: PR
A18: =0.269*8/100 -> 0.02152 | B18: =VLOOKUP(F18,Planilha3!D:F,3,0) -> 1756.2216 | C18: =B18/A18 -> 81608.811 | D18: Premium | E18: Heineken | F18: 904721 | G18: 1169727 | H18: CERVEJA HEINEKEN 269ML | I18: 8 | J18: 520 | K18: =J18*26 -> 13520 | L18: 270400 | M18: =L18/J18 -> 520 | N18: =L18/K18 -> 20 | O18: 31.21 | P18: =O18/I18 -> 3.90125 | Q18: =R18*I18 -> 0.8 | R18: 0.1 | S18: =T18*I18 -> 0.64 | T18: 0.08 | U18: =SUM(R18,T18) -> 0.18 | V18: =VLOOKUP(F18,'[1]Proposta HNK para Tenda'!$F:$T,15,0) -> 4.59 | W18: =VLOOKUP(F18,'[1]Proposta HNK para Tenda'!$F:$U,16,0) -> 3.99 | Y18: =L18*(Q18+S18) -> 389376 | Z18: =L18*O18 -> 8439184 | AA18: =L18*8*0.269/100 -> 5819.008 | AC18: =SUM(AI18,AL18,AO18) -> 0.1905596 | AD18: =SUM(R18,T18) -> 0.18 | AE18: =AC18-AD18 -> 0.0105596 | AG18: 70.84 | AH18: =AG18*AA18 -> 412218.53 | AI18: =AH18/L18/I18 -> 0.1905596 | AK18: =AJ18*AA18 -> 0 | AL18: =AK18/L18/I18 -> 0 | AM18: 0 | AN18: =AM18*AA18 -> 0 | AO18: =AN18/L18/I18 -> 0 | AP18: =SUM(AH18,AK18,AN18) -> 412218.53 | AQ18: =SUM(AI18,AL18,AO18) -> 0.1905596 | AR18: =Y18 -> 389376 | AS18: =AP18-AR18 -> 22842.527 | AT18: =O18/I18 -> 3.90125 | AU18: =AT18-R18-T18 -> 3.72125 | AV18: =(W18-AU18)/W18 -> 0.06735589 | AX18: =W18*100% -> 3.99 | AY18: =X18*50% -> 0 | AZ18: =AX18+AY18 -> 3.99 | BC18: Ponta Grossa | BD18: HNK BR INDUSTRIA DE BEBIDAS LTDA. | BE18: 50.221.019/0097-88 | BF18: 911.300.50.81 | BG18: Av Tocantins | BH18: 199 | BI18: Cara-Cara | BJ18: 84043610 | BK18: Ponta Grossa | BL18: PR
A19: 0.042 | B19: =VLOOKUP(F19,Planilha3!D:F,3,0) -> 2524.72 | C19: =B19/A19 -> 60112.38 | D19: Premium | E19: Heineken | F19: 904932 | G19: 1193319 | H19: CERVEJA HEINEKEN 350ML SLEEK | I19: 12 | J19: 280 | K19: =J19*26 -> 7280 | L19: =K19*25 -> 182000 | M19: =L19/J19 -> 650 | N19: =L19/K19 -> 25 | O19: 58.04 | P19: =O19/I19 -> 4.8366667 | Q19: =R19*I19 -> 1.2 | R19: 0.1 | S19: =T19*I19 -> 4.2 | T19: 0.35 | U19: =SUM(R19,T19) -> 0.45 | V19: =VLOOKUP(F19,'[1]Proposta HNK para Tenda'!$F:$T,15,0) -> 5.69 | W19: =VLOOKUP(F19,'[1]Proposta HNK para Tenda'!$F:$U,16,0) -> 5.29 | X19: 4.99 | Y19: =L19*(Q19+S19) -> 982800 | Z19: =L19*O19 -> 10563280 | AA19: =L19*12*0.35/100 -> 7644 | AC19: =SUM(AI19,AL19,AO19) -> 0.47901 | AD19: =SUM(R19,T19) -> 0.45 | AE19: =AC19-AD19 -> 0.02901 | AG19: 33.86 | AH19: =AG19*AA19 -> 258825.84 | AI19: =AH19/L19/I19 -> 0.11851 | AK19: =AJ19*AA19 -> 0 | AL19: =AK19/L19/I19 -> 0 | AM19: 103 | AN19: =AM19*AA19 -> 787332 | AO19: =AN19/L19/I19 -> 0.3605 | AP19: =SUM(AH19,AK19,AN19) -> 1046157.8 | AQ19: =SUM(AI19,AL19,AO19) -> 0.47901 | AR19: =Y19 -> 982800 | AS19: =AP19-AR19 -> 63357.84 | AT19: =O19/I19 -> 4.8366667 | AU19: =AT19-R19-T19 -> 4.3866667 | AV19: =(W19-AU19)/W19 -> 0.17076244 | AX19: =W19*50% -> 2.645 | AY19: =X19*50% -> 2.495 | AZ19: =AX19+AY19 -> 5.14 | BA19: =(W19-X19)/W19 -> 0.056710775 | BC19: Jacarei | BD19: HNK BR INDUSTRIA DE BEBIDAS LTDA. | BE19: 50.221.019/0104-41 | BF19: 392558326113 | BG19: Av Presidente Humberto de Alencar Castelo Branco | BH19: 2911 | BI19: Conjunto Habitacional Marinho | BJ19: 12321150 | BK19: Jacareí | BL19: SP
A20: =0.25*24/100 -> 0.06 | B20: =VLOOKUP(F20,Planilha3!D:F,3,0) -> 501.62261 | C20: =B20/A20 -> 8360.3768 | D20: Premium | E20: Heineken | F20: 905291 | G20: 1016561 | H20: CERVEJA HEINEKEN LN 250ML | I20: 24 | J20: 104 | K20: =J20*26 -> 2704 | L20: 10816 | M20: =L20/J20 -> 104 | N20: =L20/K20 -> 4 | O20: 107.92 | P20: =O20/I20 -> 4.4966667 | Q20: =R20*I20 -> 1.2 | R20: 0.05 | S20: =T20*I20 -> 0.72 | T20: 0.03 | U20: =SUM(R20,T20) -> 0.08 | V20: 5.29 | W20: 4.99 | Y20: =L20*(Q20+S20) -> 20766.72 | Z20: =L20*O20 -> 1167262.7 | AA20: =L20*24*0.25/100 -> 648.96 | AC20: =SUM(AI20,AL20,AO20) -> 0.0895 | AD20: =SUM(R20,T20) -> 0.08 | AE20: =AC20-AD20 -> 0.0095 | AG20: 35.8 | AH20: =AG20*AA20 -> 23232.768 | AI20: =AH20/L20/I20 -> 0.0895 | AK20: =AJ20*AA20 -> 0 | AL20: =AK20/L20/I20 -> 0 | AM20: 0 | AN20: =AM20*AA20 -> 0 | AO20: =AN20/L20/I20 -> 0 | AP20: =SUM(AH20,AK20,AN20) -> 23232.768 | AQ20: =SUM(AI20,AL20,AO20) -> 0.0895 | AR20: =Y20 -> 20766.72 | AS20: =AP20-AR20 -> 2466.048 | AT20: =O20/I20 -> 4.4966667 | AU20: =AT20-R20-T20 -> 4.4166667 | AV20: =(W20-AU20)/W20 -> 0.11489646 | AX20: =W20*100% -> 4.99 | AY20: =X20*50% -> 0 | AZ20: =AX20+AY20 -> 4.99 | BC20: Jacarei | BD20: HNK BR INDUSTRIA DE BEBIDAS LTDA. | BE20: 50.221.019/0104-41 | BF20: 392558326113 | BG20: Av Presidente Humberto de Alencar Castelo Branco | BH20: 2911 | BI20: Conjunto Habitacional Marinho | BJ20: 12321150 | BK20: Jacareí | BL20: SP
A21: 0.0792 | B21: =VLOOKUP(F21,Planilha3!D:F,3,0) -> 1279.3007 | C21: =B21/A21 -> 16152.787 | D21: Premium | E21: Heineken | F21: 903478 | G21: 1045807 | H21: CERVEJA HEINEKEN LN 330 ML | I21: 24 | J21: 91 | K21: =J21*26 -> 2366 | L21: 23660 | M21: =L21/J21 -> 260 | N21: =L21/K21 -> 10 | O21: 142.6 | P21: =O21/I21 -> 5.9416667 | Q21: =R21*I21 -> 1.2 | R21: 0.05 | S21: =T21*I21 -> 0.24 | T21: 0.01 | U21: =SUM(R21,T21) -> 0.06 | V21: =VLOOKUP(F21,'[1]Proposta HNK para Tenda'!$F:$T,15,0) -> 6.99 | W21: =VLOOKUP(F21,'[1]Proposta HNK para Tenda'!$F:$U,16,0) -> 6.59 | Y21: =L21*(Q21+S21) -> 34070.4 | Z21: =L21*O21 -> 3373916 | AA21: =L21*24*0.33/100 -> 1873.872 | AC21: =SUM(AI21,AL21,AO21) -> 0.068508 | AD21: =SUM(R21,T21) -> 0.06 | AE21: =AC21-AD21 -> 0.008508 | AG21: 20.76 | AH21: =AG21*AA21 -> 38901.583 | AI21: =AH21/L21/I21 -> 0.068508 | AK21: =AJ21*AA21 -> 0 | AL21: =AK21/L21/I21 -> 0 | AM21: 0 | AN21: =AM21*AA21 -> 0 | AO21: =AN21/L21/I21 -> 0 | AP21: =SUM(AH21,AK21,AN21) -> 38901.583 | AQ21: =SUM(AI21,AL21,AO21) -> 0.068508 | AR21: =Y21 -> 34070.4 | AS21: =AP21-AR21 -> 4831.1827 | AT21: =O21/I21 -> 5.9416667 | AU21: =AT21-R21-T21 -> 5.8816667 | AV21: =(W21-AU21)/W21 -> 0.10748609 | AX21: =W21*100% -> 6.59 | AY21: =X21*50% -> 0 | AZ21: =AX21+AY21 -> 6.59 | BC21: Araraquara | BD21: HNK BR INDUSTRIA DE BEBIDAS LTDA. | BE21: 50.221.019/0105-22 | BF21: 181661963118 | BG21: Av Marginal 01 | BH21: 701 | BI21: Chácara Catani | BJ21: 14808080 | BK21: Araraquara | BL21: SP
A22: 0.072 | B22: =VLOOKUP(F22,Planilha3!D:F,3,0) -> 156.38563 | C22: =B22/A22 -> 2172.0226 | D22: Premium | E22: Heineken | F22: 903480 | G22: 99187 | H22: CERVEJA HEINEKEN ONE WAY 600ML | I22: 12 | J22: 96 | K22: =J22*26 -> 2496 | L22: =J22*10 -> 960 | M22: =L22/J22 -> 10 | N22: =L22/K22 -> 0.38461538 | O22: 137.6 | P22: =O22/I22 -> 11.466667 | Q22: =R22*I22 -> 0 | R22: 0 | S22: =T22*I22 -> 0 | T22: 0 | U22: =SUM(R22,T22) -> 0 | V22: =VLOOKUP(F22,'[1]Proposta HNK para Tenda'!$F:$T,15,0) -> 13.49 | W22: =VLOOKUP(F22,'[1]Proposta HNK para Tenda'!$F:$U,16,0) -> 13.49 | Y22: =L22*(Q22+S22) -> 0 | Z22: =L22*O22 -> 132096 | AA22: =L22*12*0.6/100 -> 69.12 | AC22: =SUM(AI22,AL22,AO22) -> 0 | AD22: =SUM(R22,T22) -> 0 | AE22: =AC22-AD22 -> 0 | AG22: 0 | AH22: =AG22*AA22 -> 0 | AI22: =AH22/L22/I22 -> 0 | AK22: =AJ22*AA22 -> 0 | AL22: =AK22/L22/I22 -> 0 | AM22: 0 | AN22: =AM22*AA22 -> 0 | AO22: =AN22/L22/I22 -> 0 | AP22: =SUM(AH22,AK22,AN22) -> 0 | AQ22: =SUM(AI22,AL22,AO22) -> 0 | AR22: =Y22 -> 0 | AS22: =AP22-AR22 -> 0 | AT22: =O22/I22 -> 11.466667 | AU22: =AT22-R22-T22 -> 11.466667 | AV22: =(W22-AU22)/W22 -> 0.14998765 | AX22: =W22*100% -> 13.49 | AY22: =X22*50% -> 0 | AZ22: =AX22+AY22 -> 13.49 | BC22: Jacarei | BD22: HNK BR INDUSTRIA DE BEBIDAS LTDA. | BE22: 50.221.019/0104-41 | BF22: 392558326113 | BG22: Av Presidente Humberto de Alencar Castelo Branco | BH22: 2911 | BI22: Conjunto Habitacional Marinho | BJ22: 12321150 | BK22: Jacareí | BL22: SP
A23: 0.0792 | B23: 26 | C23: =B23/A23 -> 328.28283 | D23: Premium | E23: Sol | F23: 904701 | G23: 1022426 | H23: CERVEJA SOL PREMIUM LN 330ML | I23: 24 | J23: 91 | K23: 2366 | L23: 1274 | M23: =L23/J23 -> 14 | N23: =L23/K23 -> 0.53846154 | O23: 122.2 | P23: =O23/I23 -> 5.0916667 | Q23: =R23*I23 -> 1.44 | R23: 0.06 | S23: =T23*I23 -> 1.2 | T23: 0.05 | U23: =SUM(R23,T23) -> 0.11 | V23: 5.49 | W23: 5.09 | Y23: =L23*(Q23+S23) -> 3363.36 | Z23: =L23*O23 -> 155682.8 | AA23: =L23*24*0.33/100 -> 100.9008 | AC23: =SUM(AI23,AL23,AO23) -> 0.119493 | AD23: =SUM(R23,T23) -> 0.11 | AE23: =AC23-AD23 -> 0.009493 | AG23: 36.21 | AH23: =AG23*AA23 -> 3653.618 | AI23: =AH23/L23/I23 -> 0.119493 | AK23: =AJ23*AA23 -> 0 | AL23: =AK23/L23/I23 -> 0 | AM23: 0 | AN23: =AM23*AA23 -> 0 | AO23: =AN23/L23/I23 -> 0 | AP23: =SUM(AH23,AK23,AN23) -> 3653.618 | AQ23: =SUM(AI23,AL23,AO23) -> 0.119493 | AR23: =Y23 -> 3363.36 | AS23: =AP23-AR23 -> 290.25797 | AT23: =O23/I23 -> 5.0916667 | AU23: =AT23-R23-T23 -> 4.9816667 | AV23: =(W23-AU23)/W23 -> 0.021283563 | AX23: =W23*100% -> 5.09 | AY23: =X23*50% -> 0 | AZ23: =AX23+AY23 -> 5.09 | BC23: Jacarei | BD23: HNK BR INDUSTRIA DE BEBIDAS LTDA. | BE23: 50.221.019/0104-41 | BF23: 392558326113 | BG23: Av Presidente Humberto de Alencar Castelo Branco | BH23: 2911 | BI23: Conjunto Habitacional Marinho | BJ23: 12321150 | BK23: Jacareí | BL23: SP
A24: 0.0792 | B24: 26 | C24: =B24/A24 -> 328.28283 | D24: Premium | E24: Sol | F24: 905271 | G24: 1228753 | H24: CERVEJA SOL 0% PREMIUM LN 330ML | I24: 24 | J24: 91 | K24: 2366 | L24: =J24*7 -> 637 | M24: =L24/J24 -> 7 | N24: =L24/K24 -> 0.26923077 | O24: 122.2 | P24: =O24/I24 -> 5.0916667 | Q24: =R24*I24 -> 1.44 | R24: 0.06 | S24: =T24*I24 -> 1.2 | T24: 0.05 | U24: =SUM(R24,T24) -> 0.11 | V24: 5.99 | W24: 5.79 | Y24: =L24*(Q24+S24) -> 1681.68 | Z24: =L24*O24 -> 77841.4 | AA24: =L24*24*0.33/100 -> 50.4504 | AC24: =SUM(AI24,AL24,AO24) -> 0.119493 | AD24: =SUM(R24,T24) -> 0.11 | AE24: =AC24-AD24 -> 0.009493 | AG24: 36.21 | AH24: =AG24*AA24 -> 1826.809 | AI24: =AH24/L24/I24 -> 0.119493 | AK24: =AJ24*AA24 -> 0 | AL24: =AK24/L24/I24 -> 0 | AM24: 0 | AN24: =AM24*AA24 -> 0 | AO24: =AN24/L24/I24 -> 0 | AP24: =SUM(AH24,AK24,AN24) -> 1826.809 | AQ24: =SUM(AI24,AL24,AO24) -> 0.119493 | AR24: =Y24 -> 1681.68 | AS24: =AP24-AR24 -> 145.12898 | AT24: =O24/I24 -> 5.0916667 | AU24: =AT24-R24-T24 -> 4.9816667 | AV24: =(W24-AU24)/W24 -> 0.13960852 | AX24: =W24*100% -> 5.79 | AY24: =X24*50% -> 0 | AZ24: =AX24+AY24 -> 5.79 | BC24: Jacarei | BD24: HNK BR INDUSTRIA DE BEBIDAS LTDA. | BE24: 50.221.019/0104-41 | BF24: 392558326113 | BG24: Av Presidente Humberto de Alencar Castelo Branco | BH24: 2911 | BI24: Conjunto Habitacional Marinho | BJ24: 12321150 | BK24: Jacareí | BL24: SP
A25: =5*2/100 -> 0.1 | B25: =VLOOKUP(F25,Planilha3!D:F,3,0) -> 282.36335 | C25: =B25/A25 -> 2823.6335 | D25: Premium | E25: Heineken | F25: 903483 | G25: 75013 | H25: CHOPP HEINEKEN 5LT | I25: 2 | J25: 90 | K25: =J25*26 -> 2340 | L25: 2340 | M25: =L25/J25 -> 26 | N25: =L25/K25 -> 1 | O25: 177.63 | P25: =O25/I25 -> 88.815 | Q25: =R25*I25 -> 0 | R25: 0 | S25: =T25*I25 -> 0 | T25: 0 | U25: =SUM(R25,T25) -> 0 | V25: =VLOOKUP(F25,'[1]Proposta HNK para Tenda'!$F:$T,15,0) -> 113.99 | W25: =VLOOKUP(F25,'[1]Proposta HNK para Tenda'!$F:$U,16,0) -> 113.99 | Y25: =L25*(Q25+S25) -> 0 | Z25: =L25*O25 -> 415654.2 | AA25: =L25*2*5/100 -> 234 | AC25: =SUM(AI25,AL25,AO25) -> 0 | AD25: =SUM(R25,T25) -> 0 | AE25: =AC25-AD25 -> 0 | AG25: 0 | AH25: =AG25*AA25 -> 0 | AI25: =AH25/L25/I25 -> 0 | AK25: =AJ25*AA25 -> 0 | AL25: =AK25/L25/I25 -> 0 | AM25: 0 | AN25: =AM25*AA25 -> 0 | AO25: =AN25/L25/I25 -> 0 | AP25: =SUM(AH25,AK25,AN25) -> 0 | AQ25: =SUM(AI25,AL25,AO25) -> 0 | AR25: =Y25 -> 0 | AS25: =AP25-AR25 -> 0 | AT25: =O25/I25 -> 88.815 | AU25: =AT25-R25-T25 -> 88.815 | AV25: =(W25-AU25)/W25 -> 0.22085271 | AX25: =W25*100% -> 113.99 | AY25: =X25*50% -> 0 | AZ25: =AX25+AY25 -> 113.99 | BC25: Ponta Grossa | BD25: HNK BR INDUSTRIA DE BEBIDAS LTDA. | BE25: 50.221.019/0097-88 | BF25: 911.300.50.81 | BG25: Av Tocantins | BH25: 199 | BI25: Cara-Cara | BJ25: 84043610 | BK25: Ponta Grossa | BL25: PR
A26: =0.355*6/100 -> 0.0213 | C26: =B26/A26 -> 0 | D26: Premium | E26: Praya | F26: 631974 | G26: 1228751 | H26: CERVEJA PRAYA LAGER 355ML | I26: 6 | J26: 350 | K26: =J26*26 -> 9100 | L26: =J26*5 -> 1750 | M26: =L26/J26 -> 5 | N26: =L26/K26 -> 0.19230769 | O26: 33.07 | P26: =O26/I26 -> 5.5116667 | Q26: =R26*I26 -> 0 | R26: 0 | S26: =T26*I26 -> 0 | T26: 0 | U26: =SUM(R26,T26) -> 0 | V26: 6.99 | W26: 6.49 | Y26: =L26*(Q26+S26) -> 0 | Z26: =L26*O26 -> 57872.5 | AA26: =L26*I26*0.35/100 -> 36.75 | AC26: =SUM(AI26,AL26,AO26) -> 0 | AD26: =SUM(R26,T26) -> 0 | AE26: =AC26-AD26 -> 0 | AG26: 0 | AH26: =AG26*AA26 -> 0 | AI26: =AH26/L26/I26 -> 0 | AK26: =AJ26*AA26 -> 0 | AL26: =AK26/L26/I26 -> 0 | AM26: 0 | AN26: =AM26*AA26 -> 0 | AO26: =AN26/L26/I26 -> 0 | AP26: =SUM(AH26,AK26,AN26) -> 0 | AQ26: =SUM(AI26,AL26,AO26) -> 0 | AR26: =Y26 -> 0 | AS26: =AP26-AR26 -> 0 | AT26: =O26/I26 -> 5.5116667 | AU26: =AT26-R26-T26 -> 5.5116667 | AV26: =(W26-AU26)/W26 -> 0.15074474 | AX26: =W26*100% -> 6.49 | AY26: =X26*50% -> 0 | AZ26: =AX26+AY26 -> 6.49 | BC26: Itu | BD26: HNK BR INDUSTRIA DE BEBIDAS LTDA. | BE26: 50.221.019/0001-36 | BF26: 387000650117 | BG26: Av Primo Schincariol | BH26: 2222 | BI26: Chácara Flórida | BJ26: 13312250 | BK26: Itu | BL26: SP
A27: =0.355*24/100 -> 0.0852 | C27: =B27/A27 -> 0 | D27: Premium | E27: Praya | F27: 634958 | G27: 1149563 | H27: CERVEJA PRAYA RECEITA CLÁSSICA LN 355ML | I27: 24 | J27: 84 | K27: =J27*26 -> 2184 | L27: =J27*4 -> 336 | M27: =L27/J27 -> 4 | N27: =L27/K27 -> 0.15384615 | O27: 170.82 | P27: =O27/I27 -> 7.1175 | Q27: =R27*I27 -> 0 | R27: 0 | S27: =T27*I27 -> 0 | T27: 0 | U27: =SUM(R27,T27) -> 0 | V27: 9.49 | W27: 8.49 | Y27: =L27*(Q27+S27) -> 0 | Z27: =L27*O27 -> 57395.52 | AA27: =L27*I27*0.35/100 -> 28.224 | AC27: =SUM(AI27,AL27,AO27) -> 0 | AD27: =SUM(R27,T27) -> 0 | AE27: =AC27-AD27 -> 0 | AG27: 0 | AH27: =AG27*AA27 -> 0 | AI27: =AH27/L27/I27 -> 0 | AK27: =AJ27*AA27 -> 0 | AL27: =AK27/L27/I27 -> 0 | AM27: 0 | AN27: =AM27*AA27 -> 0 | AO27: =AN27/L27/I27 -> 0 | AP27: =SUM(AH27,AK27,AN27) -> 0 | AQ27: =SUM(AI27,AL27,AO27) -> 0 | AR27: =Y27 -> 0 | AS27: =AP27-AR27 -> 0 | AT27: =O27/I27 -> 7.1175 | AU27: =AT27-R27-T27 -> 7.1175 | AV27: =(W27-AU27)/W27 -> 0.16166078 | AX27: =W27*100% -> 8.49 | AY27: =X27*50% -> 0 | AZ27: =AX27+AY27 -> 8.49 | BC27: Itu | BD27: HNK BR INDUSTRIA DE BEBIDAS LTDA. | BE27: 50.221.019/0001-36 | BF27: 387000650117 | BG27: Av Primo Schincariol | BH27: 2222 | BI27: Chácara Flórida | BJ27: 13312250 | BK27: Itu | BL27: SP
A28: =0.6*12/100 -> 0.072 | C28: =B28/A28 -> 0 | D28: Premium | E28: Praya | F28: 634957 | G28: 1149565 | H28: CERVEJA PRAYA RECEITA CLÁSSICA 600ML | I28: 12 | J28: 60 | K28: =J28*26 -> 1560 | L28: =J28*14 -> 840 | M28: =L28/J28 -> 14 | N28: =L28/K28 -> 0.53846154 | O28: 136.71 | P28: =O28/I28 -> 11.3925 | Q28: =R28*I28 -> 0 | R28: 0 | S28: =T28*I28 -> 0 | T28: 0 | U28: =SUM(R28,T28) -> 0 | V28: 15.19 | W28: 13.29 | Y28: =L28*(Q28+S28) -> 0 | Z28: =L28*O28 -> 114836.4 | AA28: =L28*I28*0.6/100 -> 60.48 | AC28: =SUM(AI28,AL28,AO28) -> 0 | AD28: =SUM(R28,T28) -> 0 | AE28: =AC28-AD28 -> 0 | AG28: 0 | AH28: =AG28*AA28 -> 0 | AI28: =AH28/L28/I28 -> 0 | AK28: =AJ28*AA28 -> 0 | AL28: =AK28/L28/I28 -> 0 | AM28: 0 | AN28: =AM28*AA28 -> 0 | AO28: =AN28/L28/I28 -> 0 | AP28: =SUM(AH28,AK28,AN28) -> 0 | AQ28: =SUM(AI28,AL28,AO28) -> 0 | AR28: =Y28 -> 0 | AS28: =AP28-AR28 -> 0 | AT28: =O28/I28 -> 11.3925 | AU28: =AT28-R28-T28 -> 11.3925 | AV28: =(W28-AU28)/W28 -> 0.14277652 | AX28: =W28*100% -> 13.29 | AY28: =X28*50% -> 0 | AZ28: =AX28+AY28 -> 13.29 | BC28: Itu | BD28: HNK BR INDUSTRIA DE BEBIDAS LTDA. | BE28: 50.221.019/0001-36 | BF28: 387000650117 | BG28: Av Primo Schincariol | BH28: 2222 | BI28: Chácara Flórida | BJ28: 13312250 | BK28: Itu | BL28: SP
A29: 0.072 | B29: =VLOOKUP(F29,Planilha3!D:F,3,0) -> 7.4611665 | C29: =B29/A29 -> 103.62731 | D29: Craft | E29: Baden | F29: 902832 | G29: 1046669 | H29: CERVEJA BADEN IPA 600ML | I29: 12 | J29: 60 | K29: =J29*24 -> 1440 | L29: 600 | M29: =L29/J29 -> 10 | N29: =L29/K29 -> 0.41666667 | O29: 134.52 | P29: =O29/I29 -> 11.21 | Q29: =R29*I29 -> 0 | R29: 0 | S29: =T29*I29 -> 0 | T29: 0 | U29: =SUM(R29,T29) -> 0 | V29: =VLOOKUP(F29,'[1]Proposta HNK para Tenda'!$F:$T,15,0) -> 14.19 | W29: =VLOOKUP(F29,'[1]Proposta HNK para Tenda'!$F:$U,16,0) -> 14.19 | Y29: =L29*(Q29+S29) -> 0 | Z29: =L29*O29 -> 80712 | AA29: =L29*12*0.6/100 -> 43.2 | AC29: =SUM(AI29,AL29,AO29) -> 0 | AD29: =SUM(R29,T29) -> 0 | AE29: =AC29-AD29 -> 0 | AG29: 0 | AH29: =AG29*AA29 -> 0 | AI29: =AH29/L29/I29 -> 0 | AK29: =AJ29*AA29 -> 0 | AL29: =AK29/L29/I29 -> 0 | AM29: 0 | AN29: =AM29*AA29 -> 0 | AO29: =AN29/L29/I29 -> 0 | AP29: =SUM(AH29,AK29,AN29) -> 0 | AQ29: =SUM(AI29,AL29,AO29) -> 0 | AR29: =Y29 -> 0 | AS29: =AP29-AR29 -> 0 | AT29: =O29/I29 -> 11.21 | AU29: =AT29-R29-T29 -> 11.21 | AV29: =(W29-AU29)/W29 -> 0.21000705 | AX29: =W29*100% -> 14.19 | AY29: =X29*50% -> 0 | AZ29: =AX29+AY29 -> 14.19 | BC29: Itu | BD29: HNK BR INDUSTRIA DE BEBIDAS LTDA. | BE29: 50.221.019/0001-36 | BF29: 387000650117 | BG29: Av Primo Schincariol | BH29: 2222 | BI29: Chácara Flórida | BJ29: 13312250 | BK29: Itu | BL29: SP
A30: 0.072 | B30: =VLOOKUP(F30,Planilha3!D:F,3,0) -> 5.948199 | C30: =B30/A30 -> 82.613875 | D30: Craft | E30: Baden | F30: 900118 | G30: 1017028 | H30: CERVEJA BADEN GOLDEN 600ML | I30: 12 | J30: 60 | K30: =J30*24 -> 1440 | L30: 80 | M30: =L30/J30 -> 1.3333333 | N30: =L30/K30 -> 0.055555556 | O30: 134.52 | P30: =O30/I30 -> 11.21 | Q30: =R30*I30 -> 0 | R30: 0 | S30: =T30*I30 -> 0 | T30: 0 | U30: =SUM(R30,T30) -> 0 | V30: =VLOOKUP(F30,'[1]Proposta HNK para Tenda'!$F:$T,15,0) -> 14.19 | W30: =VLOOKUP(F30,'[1]Proposta HNK para Tenda'!$F:$U,16,0) -> 14.19 | Y30: =L30*(Q30+S30) -> 0 | Z30: =L30*O30 -> 10761.6 | AA30: =L30*12*0.6/100 -> 5.76 | AC30: =SUM(AI30,AL30,AO30) -> 0 | AD30: =SUM(R30,T30) -> 0 | AE30: =AC30-AD30 -> 0 | AG30: 0 | AH30: =AG30*AA30 -> 0 | AI30: =AH30/L30/I30 -> 0 | AK30: =AJ30*AA30 -> 0 | AL30: =AK30/L30/I30 -> 0 | AM30: 0 | AN30: =AM30*AA30 -> 0 | AO30: =AN30/L30/I30 -> 0 | AP30: =SUM(AH30,AK30,AN30) -> 0 | AQ30: =SUM(AI30,AL30,AO30) -> 0 | AR30: =Y30 -> 0 | AS30: =AP30-AR30 -> 0 | AT30: =O30/I30 -> 11.21 | AU30: =AT30-R30-T30 -> 11.21 | AV30: =(W30-AU30)/W30 -> 0.21000705 | AX30: =W30*100% -> 14.19 | AY30: =X30*50% -> 0 | AZ30: =AX30+AY30 -> 14.19 | BC30: Itu | BD30: HNK BR INDUSTRIA DE BEBIDAS LTDA. | BE30: 50.221.019/0001-36 | BF30: 387000650117 | BG30: Av Primo Schincariol | BH30: 2222 | BI30: Chácara Flórida | BJ30: 13312250 | BK30: Itu | BL30: SP
A31: 0.042 | B31: =VLOOKUP(F31,Planilha3!D:F,3,0) -> 27.698971 | C31: =B31/A31 -> 659.49932 | D31: Craft | E31: Baden | F31: 904451 | G31: 1147973 | H31: CERVEJA BADEN IPA LA 350ML | I31: 12 | J31: 280 | K31: =J31*24 -> 6720 | L31: 840 | M31: =L31/J31 -> 3 | N31: =M31/26 -> 0.11538462 | O31: 57.73 | P31: =O31/I31 -> 4.8108333 | Q31: =R31*I31 -> 3 | R31: 0.25 | S31: =T31*I31 -> 0.72 | T31: 0.06 | U31: =SUM(R31,T31) -> 0.31 | V31: =VLOOKUP(F31,'[1]Proposta HNK para Tenda'!$F:$T,15,0) -> 6.09 | W31: =VLOOKUP(F31,'[1]Proposta HNK para Tenda'!$F:$U,16,0) -> 5.39 | Y31: =L31*(Q31+S31) -> 3124.8 | Z31: =L31*O31 -> 48493.2 | AA31: =L31*12*0.35/100 -> 35.28 | AC31: =SUM(AI31,AL31,AO31) -> 0.3143 | AD31: =SUM(R31,T31) -> 0.31 | AE31: =AC31-AD31 -> 0.0043 | AG31: 89.8 | AH31: =AG31*AA31 -> 3168.144 | AI31: =AH31/L31/I31 -> 0.3143 | AK31: =AJ31*AA31 -> 0 | AL31: =AK31/L31/I31 -> 0 | AM31: 0 | AN31: =AM31*AA31 -> 0 | AO31: =AN31/L31/I31 -> 0 | AP31: =SUM(AH31,AK31,AN31) -> 3168.144 | AQ31: =SUM(AI31,AL31,AO31) -> 0.3143 | AR31: =Y31 -> 3124.8 | AS31: =AP31-AR31 -> 43.344 | AT31: =O31/I31 -> 4.8108333 | AU31: =AT31-R31-T31 -> 4.5008333 | AV31: =(W31-AU31)/W31 -> 0.16496599 | AX31: =W31*100% -> 5.39 | AY31: =X31*50% -> 0 | AZ31: =AX31+AY31 -> 5.39 | BC31: Itu | BD31: HNK BR INDUSTRIA DE BEBIDAS LTDA. | BE31: 50.221.019/0001-36 | BF31: 387000650117 | BG31: Av Primo Schincariol | BH31: 2222 | BI31: Chácara Flórida | BJ31: 13312250 | BK31: Itu | BL31: SP
A32: 0.072 | B32: =VLOOKUP(F32,Planilha3!D:F,3,0) -> 2.958687 | C32: =B32/A32 -> 41.092875 | D32: Craft | E32: Baden | F32: 904742 | G32: 1169732 | H32: CERVEJA BADEN PEACH 600ML | I32: 12 | J32: 60 | K32: =J32*24 -> 1440 | L32: =J32*5 -> 300 | M32: =L32/J32 -> 5 | N32: =L32/K32 -> 0.20833333 | O32: 134.52 | P32: =O32/I32 -> 11.21 | Q32: =R32*I32 -> 0 | R32: 0 | S32: =T32*I32 -> 0 | T32: 0 | U32: =SUM(R32,T32) -> 0 | V32: =VLOOKUP(F32,'[1]Proposta HNK para Tenda'!$F:$T,15,0) -> 14.19 | W32: =VLOOKUP(F32,'[1]Proposta HNK para Tenda'!$F:$U,16,0) -> 14.19 | Y32: =L32*(Q32+S32) -> 0 | Z32: =L32*O32 -> 40356 | AA32: =L32*12*0.6/100 -> 21.6 | AC32: =SUM(AI32,AL32,AO32) -> 0 | AD32: =SUM(R32,T32) -> 0 | AE32: =AC32-AD32 -> 0 | AG32: 0 | AH32: =AG32*AA32 -> 0 | AI32: =AH32/L32/I32 -> 0 | AK32: =AJ32*AA32 -> 0 | AL32: =AK32/L32/I32 -> 0 | AM32: 0 | AN32: =AM32*AA32 -> 0 | AO32: =AN32/L32/I32 -> 0 | AP32: =SUM(AH32,AK32,AN32) -> 0 | AQ32: =SUM(AI32,AL32,AO32) -> 0 | AR32: =Y32 -> 0 | AS32: =AP32-AR32 -> 0 | AT32: =O32/I32 -> 11.21 | AU32: =AT32-R32-T32 -> 11.21 | AV32: =(W32-AU32)/W32 -> 0.21000705 | AX32: =W32*100% -> 14.19 | AY32: =X32*50% -> 0 | AZ32: =AX32+AY32 -> 14.19 | BC32: Itu | BD32: HNK BR INDUSTRIA DE BEBIDAS LTDA. | BE32: 50.221.019/0001-36 | BF32: 387000650117 | BG32: Av Primo Schincariol | BH32: 2222 | BI32: Chácara Flórida | BJ32: 13312250 | BK32: Itu | BL32: SP
A33: 0.042 | B33: =VLOOKUP(F33,Planilha3!D:F,3,0) -> 12.871838 | C33: =B33/A33 -> 306.47234 | D33: Craft | E33: Baden | F33: 904743 | G33: 1170232 | H33: CERVEJA BADEN PEACH LA 350ML | I33: 12 | J33: 280 | K33: =J33*24 -> 6720 | L33: 560 | M33: =L33/J33 -> 2 | N33: =L33/K33 -> 0.083333333 | O33: 57.73 | P33: =O33/I33 -> 4.8108333 | Q33: =R33*I33 -> 3 | R33: 0.25 | S33: =T33*I33 -> 0.72 | T33: 0.06 | U33: =SUM(R33,T33) -> 0.31 | V33: =VLOOKUP(F33,'[1]Proposta HNK para Tenda'!$F:$T,15,0) -> 6.09 | W33: =VLOOKUP(F33,'[1]Proposta HNK para Tenda'!$F:$U,16,0) -> 5.39 | Y33: =L33*(Q33+S33) -> 2083.2 | Z33: =L33*O33 -> 32328.8 | AA33: =L33*12*0.35/100 -> 23.52 | AC33: =SUM(AI33,AL33,AO33) -> 0.3143 | AD33: =SUM(R33,T33) -> 0.31 | AE33: =AC33-AD33 -> 0.0043 | AG33: 89.8 | AH33: =AG33*AA33 -> 2112.096 | AI33: =AH33/L33/I33 -> 0.3143 | AK33: =AJ33*AA33 -> 0 | AL33: =AK33/L33/I33 -> 0 | AM33: 0 | AN33: =AM33*AA33 -> 0 | AO33: =AN33/L33/I33 -> 0 | AP33: =SUM(AH33,AK33,AN33) -> 2112.096 | AQ33: =SUM(AI33,AL33,AO33) -> 0.3143 | AR33: =Y33 -> 2083.2 | AS33: =AP33-AR33 -> 28.896 | AT33: =O33/I33 -> 4.8108333 | AU33: =AT33-R33-T33 -> 4.5008333 | AV33: =(W33-AU33)/W33 -> 0.16496599 | AX33: =W33*100% -> 5.39 | AY33: =X33*50% -> 0 | AZ33: =AX33+AY33 -> 5.39 | BC33: Itu | BD33: HNK BR INDUSTRIA DE BEBIDAS LTDA. | BE33: 50.221.019/0001-36 | BF33: 387000650117 | BG33: Av Primo Schincariol | BH33: 2222 | BI33: Chácara Flórida | BJ33: 13312250 | BK33: Itu | BL33: SP
A34: 0.072 | B34: =VLOOKUP(F34,Planilha3!D:F,3,0) -> 5.1478175 | C34: =B34/A34 -> 71.497465 | D34: Craft | E34: Baden | F34: 900109 | G34: 1017027 | H34: CERVEJA BADEN CRISTAL 600ML | I34: 12 | J34: 60 | K34: =J34*24 -> 1440 | L34: 160 | M34: =L34/J34 -> 2.6666667 | N34: =L34/K34 -> 0.11111111 | O34: 134.52 | P34: =O34/I34 -> 11.21 | Q34: =R34*I34 -> 0 | R34: 0 | S34: =T34*I34 -> 0 | T34: 0 | U34: =SUM(R34,T34) -> 0 | V34: =VLOOKUP(F34,'[1]Proposta HNK para Tenda'!$F:$T,15,0) -> 14.19 | W34: =VLOOKUP(F34,'[1]Proposta HNK para Tenda'!$F:$U,16,0) -> 14.19 | Y34: =L34*(Q34+S34) -> 0 | Z34: =L34*O34 -> 21523.2 | AA34: =L34*12*0.6/100 -> 11.52 | AC34: =SUM(AI34,AL34,AO34) -> 0 | AD34: =SUM(R34,T34) -> 0 | AE34: =AC34-AD34 -> 0 | AG34: 0 | AH34: =AG34*AA34 -> 0 | AI34: =AH34/L34/I34 -> 0 | AK34: =AJ34*AA34 -> 0 | AL34: =AK34/L34/I34 -> 0 | AM34: 0 | AN34: =AM34*AA34 -> 0 | AO34: =AN34/L34/I34 -> 0 | AP34: =SUM(AH34,AK34,AN34) -> 0 | AQ34: =SUM(AI34,AL34,AO34) -> 0 | AR34: =Y34 -> 0 | AS34: =AP34-AR34 -> 0 | AT34: =O34/I34 -> 11.21 | AU34: =AT34-R34-T34 -> 11.21 | AV34: =(W34-AU34)/W34 -> 0.21000705 | AX34: =W34*100% -> 14.19 | AY34: =X34*50% -> 0 | AZ34: =AX34+AY34 -> 14.19 | BC34: Itu | BD34: HNK BR INDUSTRIA DE BEBIDAS LTDA. | BE34: 50.221.019/0001-36 | BF34: 387000650117 | BG34: Av Primo Schincariol | BH34: 2222 | BI34: Chácara Flórida | BJ34: 13312250 | BK34: Itu | BL34: SP
A35: 0.042 | B35: =VLOOKUP(F35,Planilha3!D:F,3,0) -> 8.3101108 | C35: =B35/A35 -> 197.85978 | D35: Craft | E35: Baden | F35: 904441 | G35: 1147975 | H35: CERVEJA BADEN CRISTAL LA 350ML | I35: 12 | J35: 280 | K35: =J35*24 -> 6720 | L35: 560 | M35: =L35/J35 -> 2 | N35: =L35/K35 -> 0.083333333 | O35: 57.73 | P35: =O35/I35 -> 4.8108333 | Q35: =R35*I35 -> 3 | R35: 0.25 | S35: =T35*I35 -> 0.72 | T35: 0.06 | U35: =SUM(R35,T35) -> 0.31 | V35: =VLOOKUP(F35,'[1]Proposta HNK para Tenda'!$F:$T,15,0) -> 6.09 | W35: =VLOOKUP(F35,'[1]Proposta HNK para Tenda'!$F:$U,16,0) -> 5.39 | Y35: =L35*(Q35+S35) -> 2083.2 | Z35: =L35*O35 -> 32328.8 | AA35: =L35*12*0.35/100 -> 23.52 | AC35: =SUM(AI35,AL35,AO35) -> 0.3143 | AD35: =SUM(R35,T35) -> 0.31 | AE35: =AC35-AD35 -> 0.0043 | AG35: 89.8 | AH35: =AG35*AA35 -> 2112.096 | AI35: =AH35/L35/I35 -> 0.3143 | AK35: =AJ35*AA35 -> 0 | AL35: =AK35/L35/I35 -> 0 | AM35: 0 | AN35: =AM35*AA35 -> 0 | AO35: =AN35/L35/I35 -> 0 | AP35: =SUM(AH35,AK35,AN35) -> 2112.096 | AQ35: =SUM(AI35,AL35,AO35) -> 0.3143 | AR35: =Y35 -> 2083.2 | AS35: =AP35-AR35 -> 28.896 | AT35: =O35/I35 -> 4.8108333 | AU35: =AT35-R35-T35 -> 4.5008333 | AV35: =(W35-AU35)/W35 -> 0.16496599 | AX35: =W35*100% -> 5.39 | AY35: =X35*50% -> 0 | AZ35: =AX35+AY35 -> 5.39 | BC35: Itu | BD35: HNK BR INDUSTRIA DE BEBIDAS LTDA. | BE35: 50.221.019/0001-36 | BF35: 387000650117 | BG35: Av Primo Schincariol | BH35: 2222 | BI35: Chácara Flórida | BJ35: 13312250 | BK35: Itu | BL35: SP
A36: 0.072 | B36: =VLOOKUP(F36,Planilha3!D:F,3,0) -> 6.1719833 | C36: =B36/A36 -> 85.72199 | D36: Craft | E36: Baden | F36: 901162 | G36: 1046689 | H36: CERVEJA BADEN WITIBIER 600ML | I36: 12 | J36: 60 | K36: =J36*24 -> 1440 | L36: 160 | M36: =L36/J36 -> 2.6666667 | N36: =L36/K36 -> 0.11111111 | O36: 134.52 | P36: =O36/I36 -> 11.21 | Q36: =R36*I36 -> 0 | R36: 0 | S36: =T36*I36 -> 0 | T36: 0 | U36: =SUM(R36,T36) -> 0 | V36: =VLOOKUP(F36,'[1]Proposta HNK para Tenda'!$F:$T,15,0) -> 14.19 | W36: =VLOOKUP(F36,'[1]Proposta HNK para Tenda'!$F:$U,16,0) -> 14.19 | Y36: =L36*(Q36+S36) -> 0 | Z36: =L36*O36 -> 21523.2 | AA36: =L36*12*0.6/100 -> 11.52 | AC36: =SUM(AI36,AL36,AO36) -> 0 | AD36: =SUM(R36,T36) -> 0 | AE36: =AC36-AD36 -> 0 | AG36: 0 | AH36: =AG36*AA36 -> 0 | AI36: =AH36/L36/I36 -> 0 | AK36: =AJ36*AA36 -> 0 | AL36: =AK36/L36/I36 -> 0 | AM36: 0 | AN36: =AM36*AA36 -> 0 | AO36: =AN36/L36/I36 -> 0 | AP36: =SUM(AH36,AK36,AN36) -> 0 | AQ36: =SUM(AI36,AL36,AO36) -> 0 | AR36: =Y36 -> 0 | AS36: =AP36-AR36 -> 0 | AT36: =O36/I36 -> 11.21 | AU36: =AT36-R36-T36 -> 11.21 | AV36: =(W36-AU36)/W36 -> 0.21000705 | AX36: =W36*100% -> 14.19 | AY36: =X36*50% -> 0 | AZ36: =AX36+AY36 -> 14.19 | BC36: Itu | BD36: HNK BR INDUSTRIA DE BEBIDAS LTDA. | BE36: 50.221.019/0001-36 | BF36: 387000650117 | BG36: Av Primo Schincariol | BH36: 2222 | BI36: Chácara Flórida | BJ36: 13312250 | BK36: Itu | BL36: SP
A37: 0.042 | B37: =VLOOKUP(F37,Planilha3!D:F,3,0) -> 21.928826 | C37: =B37/A37 -> 522.11489 | D37: Craft | E37: Baden | F37: 904193 | G37: 1150647 | H37: CERVEJA BADEN WITBIER LA 350ML | I37: 12 | J37: 280 | K37: =J37*24 -> 6720 | L37: 560 | M37: =L37/J37 -> 2 | N37: =L37/K37 -> 0.083333333 | O37: 57.73 | P37: =O37/I37 -> 4.8108333 | Q37: =R37*I37 -> 3 | R37: 0.25 | S37: =T37*I37 -> 0.72 | T37: 0.06 | U37: =SUM(R37,T37) -> 0.31 | V37: =VLOOKUP(F37,'[1]Proposta HNK para Tenda'!$F:$T,15,0) -> 6.09 | W37: =VLOOKUP(F37,'[1]Proposta HNK para Tenda'!$F:$U,16,0) -> 5.39 | Y37: =L37*(Q37+S37) -> 2083.2 | Z37: =L37*O37 -> 32328.8 | AA37: =L37*12*0.35/100 -> 23.52 | AC37: =SUM(AI37,AL37,AO37) -> 0.3143 | AD37: =SUM(R37,T37) -> 0.31 | AE37: =AC37-AD37 -> 0.0043 | AG37: 89.8 | AH37: =AG37*AA37 -> 2112.096 | AI37: =AH37/L37/I37 -> 0.3143 | AK37: =AJ37*AA37 -> 0 | AL37: =AK37/L37/I37 -> 0 | AM37: 0 | AN37: =AM37*AA37 -> 0 | AO37: =AN37/L37/I37 -> 0 | AP37: =SUM(AH37,AK37,AN37) -> 2112.096 | AQ37: =SUM(AI37,AL37,AO37) -> 0.3143 | AR37: =Y37 -> 2083.2 | AS37: =AP37-AR37 -> 28.896 | AT37: =O37/I37 -> 4.8108333 | AU37: =AT37-R37-T37 -> 4.5008333 | AV37: =(W37-AU37)/W37 -> 0.16496599 | AX37: =W37*100% -> 5.39 | AY37: =X37*50% -> 0 | AZ37: =AX37+AY37 -> 5.39 | BC37: Itu | BD37: HNK BR INDUSTRIA DE BEBIDAS LTDA. | BE37: 50.221.019/0001-36 | BF37: 387000650117 | BG37: Av Primo Schincariol | BH37: 2222 | BI37: Chácara Flórida | BJ37: 13312250 | BK37: Itu | BL37: SP
A38: 0.042 | B38: =VLOOKUP(F38,Planilha3!D:F,3,0) -> 12.387493 | C38: =B38/A38 -> 294.94032 | D38: Craft | E38: Blue Moon | F38: 904612 | G38: 1155188 | H38: CERVEJA BLUE MOON LA 350ML | I38: 12 | J38: 280 | K38: =J38*24 -> 6720 | L38: 280 | M38: =L38/J38 -> 1 | N38: =L38/K38 -> 0.041666667 | O38: 85.23 | P38: =O38/I38 -> 7.1025 | Q38: =R38*I38 -> 10.8 | R38: 0.9 | S38: =T38*I38 -> 0.24 | T38: 0.02 | U38: =SUM(R38,T38) -> 0.92 | V38: =VLOOKUP(F38,'[1]Proposta HNK para Tenda'!$F:$T,15,0) -> 8.99 | W38: =VLOOKUP(F38,'[1]Proposta HNK para Tenda'!$F:$U,16,0) -> 6.99 | Y38: =L38*(Q38+S38) -> 3091.2 | Z38: =L38*O38 -> 23864.4 | AA38: =L38*12*0.35/100 -> 11.76 | AC38: =SUM(AI38,AL38,AO38) -> 0.93051 | AD38: =SUM(R38,T38) -> 0.92 | AE38: =AC38-AD38 -> 0.01051 | AG38: 265.86 | AH38: =AG38*AA38 -> 3126.5136 | AI38: =AH38/L38/I38 -> 0.93051 | AK38: =AJ38*AA38 -> 0 | AL38: =AK38/L38/I38 -> 0 | AM38: 0 | AN38: =AM38*AA38 -> 0 | AO38: =AN38/L38/I38 -> 0 | AP38: =SUM(AH38,AK38,AN38) -> 3126.5136 | AQ38: =SUM(AI38,AL38,AO38) -> 0.93051 | AR38: =Y38 -> 3091.2 | AS38: =AP38-AR38 -> 35.3136 | AT38: =O38/I38 -> 7.1025 | AU38: =AT38-R38-T38 -> 6.1825 | AV38: =(W38-AU38)/W38 -> 0.11552217 | AX38: =W38*100% -> 6.99 | AY38: =X38*50% -> 0 | AZ38: =AX38+AY38 -> 6.99 | BC38: Itu | BD38: HNK BR INDUSTRIA DE BEBIDAS LTDA. | BE38: 50.221.019/0001-36 | BF38: 387000650117 | BG38: Av Primo Schincariol | BH38: 2222 | BI38: Chácara Flórida | BJ38: 13312250 | BK38: Itu | BL38: SP
A39: 0.0852 | B39: =VLOOKUP(F39,Planilha3!D:F,3,0) -> 5.009831 | C39: =B39/A39 -> 58.800833 | D39: Craft | E39: Blue Moon | F39: 904602 | G39: 1160869 | H39: CERVEJA BLUE MOON LN 355ML | I39: 24 | J39: 56 | K39: =J39*24 -> 1344 | L39: =J39*2 -> 112 | M39: =L39/J39 -> 2 | N39: =L39/K39 -> 0.083333333 | O39: 208.37 | P39: =O39/I39 -> 8.6820833 | Q39: =R39*I39 -> 0 | R39: 0 | S39: =T39*I39 -> 0 | T39: 0 | U39: =SUM(R39,T39) -> 0 | V39: =VLOOKUP(F39,'[1]Proposta HNK para Tenda'!$F:$T,15,0) -> 10.99 | W39: =VLOOKUP(F39,'[1]Proposta HNK para Tenda'!$F:$U,16,0) -> 10.99 | Y39: =L39*(Q39+S39) -> 0 | Z39: =L39*O39 -> 23337.44 | AA39: =L39*24*0.355/100 -> 9.5424 | AC39: =SUM(AI39,AL39,AO39) -> 0 | AD39: =SUM(R39,T39) -> 0 | AE39: =AC39-AD39 -> 0 | AG39: 0 | AH39: =AG39*AA39 -> 0 | AI39: =AH39/L39/I39 -> 0 | AK39: =AJ39*AA39 -> 0 | AL39: =AK39/L39/I39 -> 0 | AM39: 0 | AN39: =AM39*AA39 -> 0 | AO39: =AN39/L39/I39 -> 0 | AP39: =SUM(AH39,AK39,AN39) -> 0 | AQ39: =SUM(AI39,AL39,AO39) -> 0 | AR39: =Y39 -> 0 | AS39: =AP39-AR39 -> 0 | AT39: =O39/I39 -> 8.6820833 | AU39: =AT39-R39-T39 -> 8.6820833 | AV39: =(W39-AU39)/W39 -> 0.21000152 | AX39: =W39*100% -> 10.99 | AY39: =X39*50% -> 0 | AZ39: =AX39+AY39 -> 10.99 | BC39: Itu | BD39: HNK BR INDUSTRIA DE BEBIDAS LTDA. | BE39: 50.221.019/0001-36 | BF39: 387000650117 | BG39: Av Primo Schincariol | BH39: 2222 | BI39: Chácara Flórida | BJ39: 13312250 | BK39: Itu | BL39: SP
A40: 0.042 | B40: =VLOOKUP(F40,Planilha3!D:F,3,0) -> 17.452561 | C40: =B40/A40 -> 415.53717 | D40: Craft | E40: Eisenbahn | F40: 903681 | G40: 1110090 | H40: CERVEJA EISENBAHN IPA LATA 350 ML | I40: 12 | J40: 280 | K40: =J40*24 -> 6720 | L40: =J40*2 -> 560 | M40: =L40/J40 -> 2 | N40: =L40/K40 -> 0.083333333 | O40: 53.94 | P40: =O40/I40 -> 4.495 | Q40: =R40*I40 -> 3.24 | R40: 0.27 | S40: =T40*I40 -> 0 | T40: 0 | U40: =SUM(R40,T40) -> 0.27 | V40: 5.69 | W40: 5.09 | Y40: =L40*(Q40+S40) -> 1814.4 | Z40: =L40*O40 -> 30206.4 | AA40: =L40*12*0.35/100 -> 23.52 | AC40: =SUM(AI40,AL40,AO40) -> 0.26691 | AD40: =SUM(R40,T40) -> 0.27 | AE40: =AC40-AD40 -> -0.00309 | AG40: 76.26 | AH40: =AG40*AA40 -> 1793.6352 | AI40: =AH40/L40/I40 -> 0.26691 | AK40: =AJ40*AA40 -> 0 | AL40: =AK40/L40/I40 -> 0 | AM40: 0 | AN40: =AM40*AA40 -> 0 | AO40: =AN40/L40/I40 -> 0 | AP40: =SUM(AH40,AK40,AN40) -> 1793.6352 | AQ40: =SUM(AI40,AL40,AO40) -> 0.26691 | AR40: =Y40 -> 1814.4 | AS40: =AP40-AR40 -> -20.7648 | AT40: =O40/I40 -> 4.495 | AU40: =AT40-R40-T40 -> 4.225 | AV40: =(W40-AU40)/W40 -> 0.16994106 | AX40: =W40*100% -> 5.09 | AY40: =X40*50% -> 0 | AZ40: =AX40+AY40 -> 5.09 | BC40: Itu | BD40: HNK BR INDUSTRIA DE BEBIDAS LTDA. | BE40: 50.221.019/0001-36 | BF40: 387000650117 | BG40: Av Primo Schincariol | BH40: 2222 | BI40: Chácara Flórida | BJ40: 13312250 | BK40: Itu | BL40: SP
A41: 0.0426 | B41: =VLOOKUP(F41,Planilha3!D:F,3,0) -> 5.8949334 | C41: =B41/A41 -> 138.37872 | D41: Craft | E41: Eisenbahn | F41: 903741 | G41: 1080284 | H41: CERVEJA EISENBAHN IPA LN 355ML | I41: 12 | J41: 175 | K41: =J41*24 -> 4200 | L41: =175*2 -> 350 | M41: =L41/J41 -> 2 | N41: =L41/K41 -> 0.083333333 | O41: 64.37 | P41: =O41/I41 -> 5.3641667 | Q41: =R41*I41 -> 0 | R41: 0 | S41: =T41*I41 -> 0 | T41: 0 | U41: =SUM(R41,T41) -> 0 | V41: 6.79 | W41: 6.79 | Y41: =L41*(Q41+S41) -> 0 | Z41: =L41*O41 -> 22529.5 | AA41: =L41*12*0.355/100 -> 14.91 | AC41: =SUM(AI41,AL41,AO41) -> 0 | AD41: =SUM(R41,T41) -> 0 | AE41: =AC41-AD41 -> 0 | AG41: 0 | AH41: =AG41*AA41 -> 0 | AI41: =AH41/L41/I41 -> 0 | AK41: =AJ41*AA41 -> 0 | AL41: =AK41/L41/I41 -> 0 | AM41: 0 | AN41: =AM41*AA41 -> 0 | AO41: =AN41/L41/I41 -> 0 | AP41: =SUM(AH41,AK41,AN41) -> 0 | AQ41: =SUM(AI41,AL41,AO41) -> 0 | AR41: =Y41 -> 0 | AS41: =AP41-AR41 -> 0 | AT41: =O41/I41 -> 5.3641667 | AU41: =AT41-R41-T41 -> 5.3641667 | AV41: =(W41-AU41)/W41 -> 0.20999018 | AX41: =W41*100% -> 6.79 | AY41: =X41*50% -> 0 | AZ41: =AX41+AY41 -> 6.79 | BC41: Itu | BD41: HNK BR INDUSTRIA DE BEBIDAS LTDA. | BE41: 50.221.019/0001-36 | BF41: 387000650117 | BG41: Av Primo Schincariol | BH41: 2222 | BI41: Chácara Flórida | BJ41: 13312250 | BK41: Itu | BL41: SP
A42: 0.0426 | B42: =VLOOKUP(F42,Planilha3!D:F,3,0) -> 5.6291775 | C42: =B42/A42 -> 132.14032 | D42: Craft | E42: Eisenbahn | F42: 902544 | G42: 1041649 | H42: CERVEJA EISENBAHN PALE ALE LN 355ML | I42: 12 | J42: 175 | K42: =J42*24 -> 4200 | L42: =175*2 -> 350 | M42: =L42/J42 -> 2 | N42: =L42/K42 -> 0.083333333 | O42: 64.37 | P42: =O42/I42 -> 5.3641667 | Q42: =R42*I42 -> 0 | R42: 0 | S42: =T42*I42 -> 0 | T42: 0 | U42: =SUM(R42,T42) -> 0 | V42: 6.79 | W42: 6.79 | Y42: =L42*(Q42+S42) -> 0 | Z42: =L42*O42 -> 22529.5 | AA42: =L42*12*0.355/100 -> 14.91 | AC42: =SUM(AI42,AL42,AO42) -> 0 | AD42: =SUM(R42,T42) -> 0 | AE42: =AC42-AD42 -> 0 | AG42: 0 | AH42: =AG42*AA42 -> 0 | AI42: =AH42/L42/I42 -> 0 | AK42: =AJ42*AA42 -> 0 | AL42: =AK42/L42/I42 -> 0 | AM42: 0 | AN42: =AM42*AA42 -> 0 | AO42: =AN42/L42/I42 -> 0 | AP42: =SUM(AH42,AK42,AN42) -> 0 | AQ42: =SUM(AI42,AL42,AO42) -> 0 | AR42: =Y42 -> 0 | AS42: =AP42-AR42 -> 0 | AT42: =O42/I42 -> 5.3641667 | AU42: =AT42-R42-T42 -> 5.3641667 | AV42: =(W42-AU42)/W42 -> 0.20999018 | AX42: =W42*100% -> 6.79 | AY42: =X42*50% -> 0 | AZ42: =AX42+AY42 -> 6.79 | BC42: Itu | BD42: HNK BR INDUSTRIA DE BEBIDAS LTDA. | BE42: 50.221.019/0001-36 | BF42: 387000650117 | BG42: Av Primo Schincariol | BH42: 2222 | BI42: Chácara Flórida | BJ42: 13312250 | BK42: Itu | BL42: SP
A43: 0.042 | B43: =VLOOKUP(F43,Planilha3!D:F,3,0) -> 33.175375 | C43: =B43/A43 -> 789.88988 | D43: Craft | E43: Eisenbahn | F43: 903683 | G43: 1110091 | H43: CERVEJA EISENBAHN PALE ALE LT 350ML | I43: 12 | J43: 280 | K43: =J43*24 -> 6720 | L43: 560 | M43: =L43/J43 -> 2 | N43: =L43/K43 -> 0.083333333 | O43: 53.94 | P43: =O43/I43 -> 4.495 | Q43: =R43*I43 -> 3.24 | R43: 0.27 | S43: =T43*I43 -> 0 | T43: 0 | U43: =SUM(R43,T43) -> 0.27 | V43: 5.69 | W43: 5.09 | Y43: =L43*(Q43+S43) -> 1814.4 | Z43: =L43*O43 -> 30206.4 | AA43: =L43*12*0.35/100 -> 23.52 | AC43: =SUM(AI43,AL43,AO43) -> 0.26691 | AD43: =SUM(R43,T43) -> 0.27 | AE43: =AC43-AD43 -> -0.00309 | AG43: 76.26 | AH43: =AG43*AA43 -> 1793.6352 | AI43: =AH43/L43/I43 -> 0.26691 | AK43: =AJ43*AA43 -> 0 | AL43: =AK43/L43/I43 -> 0 | AM43: 0 | AN43: =AM43*AA43 -> 0 | AO43: =AN43/L43/I43 -> 0 | AP43: =SUM(AH43,AK43,AN43) -> 1793.6352 | AQ43: =SUM(AI43,AL43,AO43) -> 0.26691 | AR43: =Y43 -> 1814.4 | AS43: =AP43-AR43 -> -20.7648 | AT43: =O43/I43 -> 4.495 | AU43: =AT43-R43-T43 -> 4.225 | AV43: =(W43-AU43)/W43 -> 0.16994106 | AX43: =W43*100% -> 5.09 | AY43: =X43*50% -> 0 | AZ43: =AX43+AY43 -> 5.09 | BC43: Itu | BD43: HNK BR INDUSTRIA DE BEBIDAS LTDA. | BE43: 50.221.019/0001-36 | BF43: 387000650117 | BG43: Av Primo Schincariol | BH43: 2222 | BI43: Chácara Flórida | BJ43: 13312250 | BK43: Itu | BL43: SP
A44: 0.042 | B44: 0 | C44: =B44/A44 -> 0 | D44: Craft | E44: Eisenbahn | F44: 904773 | G44: 1170235 | H44: CERVEJA EISENBAHN SESSION IPA LA 350ML | I44: 12 | J44: 280 | K44: =J44*24 -> 6720 | L44: 560 | M44: =L44/J44 -> 2 | N44: =L44/K44 -> 0.083333333 | O44: 53.94 | P44: =O44/I44 -> 4.495 | Q44: =R44*I44 -> 3.24 | R44: 0.27 | S44: =T44*I44 -> 0 | T44: 0 | U44: =SUM(R44,T44) -> 0.27 | V44: 5.69 | W44: 5.09 | Y44: =L44*(Q44+S44) -> 1814.4 | Z44: =L44*O44 -> 30206.4 | AA44: =L44*12*0.35/100 -> 23.52 | AC44: =SUM(AI44,AL44,AO44) -> 0.26691 | AD44: =SUM(R44,T44) -> 0.27 | AE44: =AC44-AD44 -> -0.00309 | AG44: 76.26 | AH44: =AG44*AA44 -> 1793.6352 | AI44: =AH44/L44/I44 -> 0.26691 | AK44: =AJ44*AA44 -> 0 | AL44: =AK44/L44/I44 -> 0 | AM44: 0 | AN44: =AM44*AA44 -> 0 | AO44: =AN44/L44/I44 -> 0 | AP44: =SUM(AH44,AK44,AN44) -> 1793.6352 | AQ44: =SUM(AI44,AL44,AO44) -> 0.26691 | AR44: =Y44 -> 1814.4 | AS44: =AP44-AR44 -> -20.7648 | AT44: =O44/I44 -> 4.495 | AU44: =AT44-R44-T44 -> 4.225 | AV44: =(W44-AU44)/W44 -> 0.16994106 | AX44: =W44*100% -> 5.09 | AY44: =X44*50% -> 0 | AZ44: =AX44+AY44 -> 5.09 | BC44: Itu | BD44: HNK BR INDUSTRIA DE BEBIDAS LTDA. | BE44: 50.221.019/0001-36 | BF44: 387000650117 | BG44: Av Primo Schincariol | BH44: 2222 | BI44: Chácara Flórida | BJ44: 13312250 | BK44: Itu | BL44: SP
A45: 0.0426 | B45: =VLOOKUP(F45,Planilha3!D:F,3,0) -> 3.9785144 | C45: =B45/A45 -> 93.392357 | D45: Craft | E45: Eisenbahn | F45: 902581 | G45: 1017033 | H45: CERVEJA EISENBAHN WEIZENBIER LN 355ML | I45: 12 | J45: 175 | K45: =J45*24 -> 4200 | L45: 350 | M45: =L45/J45 -> 2 | N45: =L45/K45 -> 0.083333333 | O45: 64.37 | P45: =O45/I45 -> 5.3641667 | Q45: =R45*I45 -> 0 | R45: 0 | S45: =T45*I45 -> 0 | T45: 0 | U45: =SUM(R45,T45) -> 0 | V45: 6.79 | W45: 6.79 | Y45: =L45*(Q45+S45) -> 0 | Z45: =L45*O45 -> 22529.5 | AA45: =L45*12*0.355/100 -> 14.91 | AC45: =SUM(AI45,AL45,AO45) -> 0 | AD45: =SUM(R45,T45) -> 0 | AE45: =AC45-AD45 -> 0 | AG45: 0 | AH45: =AG45*AA45 -> 0 | AI45: =AH45/L45/I45 -> 0 | AK45: =AJ45*AA45 -> 0 | AL45: =AK45/L45/I45 -> 0 | AM45: 0 | AN45: =AM45*AA45 -> 0 | AO45: =AN45/L45/I45 -> 0 | AP45: =SUM(AH45,AK45,AN45) -> 0 | AQ45: =SUM(AI45,AL45,AO45) -> 0 | AR45: =Y45 -> 0 | AS45: =AP45-AR45 -> 0 | AT45: =O45/I45 -> 5.3641667 | AU45: =AT45-R45-T45 -> 5.3641667 | AV45: =(W45-AU45)/W45 -> 0.20999018 | AX45: =W45*100% -> 6.79 | AY45: =X45*50% -> 0 | AZ45: =AX45+AY45 -> 6.79 | BC45: Itu | BD45: HNK BR INDUSTRIA DE BEBIDAS LTDA. | BE45: 50.221.019/0001-36 | BF45: 387000650117 | BG45: Av Primo Schincariol | BH45: 2222 | BI45: Chácara Flórida | BJ45: 13312250 | BK45: Itu | BL45: SP
A46: 0.0426 | B46: =VLOOKUP(F46,Planilha3!D:F,3,0) -> 2.5961263 | C46: =B46/A46 -> 60.941932 | D46: Craft | E46: Lagunitas | F46: 903901 | G46: 1170142 | H46: CERVEJA LAGUNITAS LN 355ML | I46: 12 | J46: 126 | K46: =J46*24 -> 3024 | L46: 126 | M46: =L46/J46 -> 1 | N46: =L46/K46 -> 0.041666667 | O46: 104.19 | P46: =O46/I46 -> 8.6825 | Q46: =R46*I46 -> 0 | R46: 0 | S46: =T46*I46 -> 0 | T46: 0 | U46: =SUM(R46,T46) -> 0 | V46: =VLOOKUP(F46,'[1]Proposta HNK para Tenda'!$F:$T,15,0) -> 10.99 | W46: =VLOOKUP(F46,'[1]Proposta HNK para Tenda'!$F:$U,16,0) -> 10.99 | Y46: =L46*(Q46+S46) -> 0 | Z46: =L46*O46 -> 13127.94 | AA46: =L46*12*0.355/100 -> 5.3676 | AC46: =SUM(AI46,AL46,AO46) -> 0 | AD46: =SUM(R46,T46) -> 0 | AE46: =AC46-AD46 -> 0 | AG46: 0 | AH46: =AG46*AA46 -> 0 | AI46: =AH46/L46/I46 -> 0 | AK46: =AJ46*AA46 -> 0 | AL46: =AK46/L46/I46 -> 0 | AM46: 0 | AN46: =AM46*AA46 -> 0 | AO46: =AN46/L46/I46 -> 0 | AP46: =SUM(AH46,AK46,AN46) -> 0 | AQ46: =SUM(AI46,AL46,AO46) -> 0 | AR46: =Y46 -> 0 | AS46: =AP46-AR46 -> 0 | AT46: =O46/I46 -> 8.6825 | AU46: =AT46-R46-T46 -> 8.6825 | AV46: =(W46-AU46)/W46 -> 0.2099636 | AX46: =W46*100% -> 10.99 | AY46: =X46*50% -> 0 | AZ46: =AX46+AY46 -> 10.99 | BC46: Itu | BD46: HNK BR INDUSTRIA DE BEBIDAS LTDA. | BE46: 50.221.019/0001-36 | BF46: 387000650117 | BG46: Av Primo Schincariol | BH46: 2222 | BI46: Chácara Flórida | BJ46: 13312250 | BK46: Itu | BL46: SP
A47: 0.042 | B47: =VLOOKUP(F47,Planilha3!D:F,3,0) -> 5.5383412 | C47: =B47/A47 -> 131.86527 | D47: Craft | E47: Lagunitas | F47: 904782 | G47: 1169716 | H47: CERVEJA LAGUNITAS LA 350ML IPA | I47: 12 | J47: 280 | K47: =J47*24 -> 6720 | L47: 280 | M47: =L47/J47 -> 1 | N47: =L47/K47 -> 0.041666667 | O47: 85.23 | P47: =O47/I47 -> 7.1025 | Q47: =R47*I47 -> 10.8 | R47: 0.9 | S47: =T47*I47 -> 0.24 | T47: 0.02 | U47: =SUM(R47,T47) -> 0.92 | V47: =VLOOKUP(F47,'[1]Proposta HNK para Tenda'!$F:$T,15,0) -> 8.99 | W47: =VLOOKUP(F47,'[1]Proposta HNK para Tenda'!$F:$U,16,0) -> 6.99 | Y47: =L47*(Q47+S47) -> 3091.2 | Z47: =L47*O47 -> 23864.4 | AA47: =L47*12*0.35/100 -> 11.76 | AC47: =SUM(AI47,AL47,AO47) -> 0.93051 | AD47: =SUM(R47,T47) -> 0.92 | AE47: =AC47-AD47 -> 0.01051 | AG47: 265.86 | AH47: =AG47*AA47 -> 3126.5136 | AI47: =AH47/L47/I47 -> 0.93051 | AK47: =AJ47*AA47 -> 0 | AL47: =AK47/L47/I47 -> 0 | AM47: 0 | AN47: =AM47*AA47 -> 0 | AO47: =AN47/L47/I47 -> 0 | AP47: =SUM(AH47,AK47,AN47) -> 3126.5136 | AQ47: =SUM(AI47,AL47,AO47) -> 0.93051 | AR47: =Y47 -> 3091.2 | AS47: =AP47-AR47 -> 35.3136 | AT47: =O47/I47 -> 7.1025 | AU47: =AT47-R47-T47 -> 6.1825 | AV47: =(W47-AU47)/W47 -> 0.11552217 | AX47: =W47*100% -> 6.99 | AY47: =X47*50% -> 0 | AZ47: =AX47+AY47 -> 6.99 | BC47: Itu | BD47: HNK BR INDUSTRIA DE BEBIDAS LTDA. | BE47: 50.221.019/0001-36 | BF47: 387000650117 | BG47: Av Primo Schincariol | BH47: 2222 | BI47: Chácara Flórida | BJ47: 13312250 | BK47: Itu | BL47: SP
A48: =0.35*12/100 -> 0.042 | B48: =VLOOKUP(F48,Planilha3!D:F,3,0) -> 24.465583 | C48: =B48/A48 -> 582.51388 | D48: Nab | E48: Fys | F48: 903795 | G48: 1155646 | H48: REFRIGERANTE FYS LIMÃO 350 ML | I48: 12 | J48: 286 | K48: =J48*24 -> 6864 | L48: =J48*3 -> 858 | M48: =L48/J48 -> 3 | N48: =L48/K48 -> 0.125 | O48: 28.46 | P48: =O48/I48 -> 2.3716667 | Q48: =R48*I48 -> 1.68 | R48: 0.14 | S48: =I48*T48 -> 0 | T48: 0 | U48: =SUM(R48,T48) -> 0.14 | V48: =VLOOKUP(F48,'[1]Proposta HNK para Tenda'!$F:$T,15,0) -> 2.79 | W48: =VLOOKUP(F48,'[1]Proposta HNK para Tenda'!$F:$U,16,0) -> 2.49 | Y48: =L48*(Q48+S48) -> 1441.44 | Z48: =L48*O48 -> 24418.68 | AA48: =L48*12*0.35/100 -> 36.036 | AC48: =SUM(AI48,AL48,AO48) -> 0.135485 | AD48: =SUM(R48,T48) -> 0.14 | AE48: =AC48-AD48 -> -0.004515 | AG48: 38.71 | AH48: =AG48*AA48 -> 1394.9536 | AI48: =AH48/L48/I48 -> 0.135485 | AK48: =AJ48*AA48 -> 0 | AL48: =AK48/L48/I48 -> 0 | AM48: 0 | AN48: =AM48*AA48 -> 0 | AO48: =AN48/L48/I48 -> 0 | AP48: =SUM(AH48,AK48,AN48) -> 1394.9536 | AQ48: =SUM(AI48,AL48,AO48) -> 0.135485 | AR48: =Y48 -> 1441.44 | AS48: =AP48-AR48 -> -46.48644 | AT48: =O48/I48 -> 2.3716667 | AU48: =AT48-R48-T48 -> 2.2316667 | AV48: =(W48-AU48)/W48 -> 0.10374833 | AX48: =W48*100% -> 2.49 | AY48: =X48*50% -> 0 | AZ48: =AX48+AY48 -> 2.49 | BC48: Itu | BD48: HNK BR INDUSTRIA DE BEBIDAS LTDA. | BE48: 50.221.019/0001-36 | BF48: 387000650117 | BG48: Av Primo Schincariol | BH48: 2222 | BI48: Chácara Flórida | BJ48: 13312250 | BK48: Itu | BL48: SP
A49: =0.35*12/100 -> 0.042 | B49: =VLOOKUP(F49,Planilha3!D:F,3,0) -> 0.161625 | C49: =B49/A49 -> 3.8482143 | D49: Nab | E49: Fys | F49: 905282 | G49: 1228747 | H49: REFRIGERANTE FYS LIMÃO ZERO 350 ML | I49: 12 | J49: 286 | K49: =J49*24 -> 6864 | L49: =J49*2 -> 572 | M49: =L49/J49 -> 2 | N49: =L49/K49 -> 0.083333333 | O49: 28.46 | P49: =O49/I49 -> 2.3716667 | Q49: =R49*I49 -> 1.68 | R49: 0.14 | S49: =I49*T49 -> 0 | T49: 0 | U49: =SUM(R49,T49) -> 0.14 | V49: 2.79 | W49: 2.49 | Y49: =L49*(Q49+S49) -> 960.96 | Z49: =L49*O49 -> 16279.12 | AA49: =L49*12*0.35/100 -> 24.024 | AC49: =SUM(AI49,AL49,AO49) -> 0.135485 | AD49: =SUM(R49,T49) -> 0.14 | AE49: =AC49-AD49 -> -0.004515 | AG49: 38.71 | AH49: =AG49*AA49 -> 929.96904 | AI49: =AH49/L49/I49 -> 0.135485 | AK49: =AJ49*AA49 -> 0 | AL49: =AK49/L49/I49 -> 0 | AM49: 0 | AN49: =AM49*AA49 -> 0 | AO49: =AN49/L49/I49 -> 0 | AP49: =SUM(AH49,AK49,AN49) -> 929.96904 | AQ49: =SUM(AI49,AL49,AO49) -> 0.135485 | AR49: =Y49 -> 960.96 | AS49: =AP49-AR49 -> -30.99096 | AT49: =O49/I49 -> 2.3716667 | AU49: =AT49-R49-T49 -> 2.2316667 | AV49: =(W49-AU49)/W49 -> 0.10374833 | AX49: =W49*100% -> 2.49 | AY49: =X49*50% -> 0 | AZ49: =AX49+AY49 -> 2.49 | BC49: Itu | BD49: HNK BR INDUSTRIA DE BEBIDAS LTDA. | BE49: 50.221.019/0001-36 | BF49: 387000650117 | BG49: Av Primo Schincariol | BH49: 2222 | BI49: Chácara Flórida | BJ49: 13312250 | BK49: Itu | BL49: SP
A50: =0.35*12/100 -> 0.042 | B50: =VLOOKUP(F50,Planilha3!D:F,3,0) -> 22.60358 | C50: =B50/A50 -> 538.18049 | D50: Nab | E50: Fys | F50: 903791 | G50: 1155674 | H50: REFRIGERANTE FYS GUARANÁ 350 ML | I50: 12 | J50: 286 | K50: =J50*24 -> 6864 | L50: =J50*3 -> 858 | M50: =L50/J50 -> 3 | N50: =L50/K50 -> 0.125 | O50: 28.46 | P50: =O50/I50 -> 2.3716667 | Q50: =R50*I50 -> 1.68 | R50: 0.14 | S50: =I50*T50 -> 0 | T50: 0 | U50: =SUM(R50,T50) -> 0.14 | V50: =VLOOKUP(F50,'[1]Proposta HNK para Tenda'!$F:$T,15,0) -> 2.79 | W50: =VLOOKUP(F50,'[1]Proposta HNK para Tenda'!$F:$U,16,0) -> 2.49 | Y50: =L50*(Q50+S50) -> 1441.44 | Z50: =L50*O50 -> 24418.68 | AA50: =L50*12*0.35/100 -> 36.036 | AC50: =SUM(AI50,AL50,AO50) -> 0.135485 | AD50: =SUM(R50,T50) -> 0.14 | AE50: =AC50-AD50 -> -0.004515 | AG50: 38.71 | AH50: =AG50*AA50 -> 1394.9536 | AI50: =AH50/L50/I50 -> 0.135485 | AK50: =AJ50*AA50 -> 0 | AL50: =AK50/L50/I50 -> 0 | AM50: 0 | AN50: =AM50*AA50 -> 0 | AO50: =AN50/L50/I50 -> 0 | AP50: =SUM(AH50,AK50,AN50) -> 1394.9536 | AQ50: =SUM(AI50,AL50,AO50) -> 0.135485 | AR50: =Y50 -> 1441.44 | AS50: =AP50-AR50 -> -46.48644 | AT50: =O50/I50 -> 2.3716667 | AU50: =AT50-R50-T50 -> 2.2316667 | AV50: =(W50-AU50)/W50 -> 0.10374833 | AX50: =W50*100% -> 2.49 | AY50: =X50*50% -> 0 | AZ50: =AX50+AY50 -> 2.49 | BC50: Itu | BD50: HNK BR INDUSTRIA DE BEBIDAS LTDA. | BE50: 50.221.019/0001-36 | BF50: 387000650117 | BG50: Av Primo Schincariol | BH50: 2222 | BI50: Chácara Flórida | BJ50: 13312250 | BK50: Itu | BL50: SP
A51: =0.35*12/100 -> 0.042 | B51: =VLOOKUP(F51,Planilha3!D:F,3,0) -> 3.56375 | C51: =B51/A51 -> 84.85119 | D51: Nab | E51: Fys | F51: 905283 | G51: 1228749 | H51: REFRIGERANTE FYS GUARANÁ ZERO 350 ML | I51: 12 | J51: 286 | K51: =J51*24 -> 6864 | L51: =J51*2 -> 572 | M51: =L51/J51 -> 2 | N51: =L51/K51 -> 0.083333333 | O51: 28.46 | P51: =O51/I51 -> 2.3716667 | Q51: =R51*I51 -> 1.68 | R51: 0.14 | S51: =I51*T51 -> 0 | T51: 0 | U51: =SUM(R51,T51) -> 0.14 | V51: 2.79 | W51: 2.49 | Y51: =L51*(Q51+S51) -> 960.96 | Z51: =L51*O51 -> 16279.12 | AA51: =L51*12*0.35/100 -> 24.024 | AC51: =SUM(AI51,AL51,AO51) -> 0.135485 | AD51: =SUM(R51,T51) -> 0.14 | AE51: =AC51-AD51 -> -0.004515 | AG51: 38.71 | AH51: =AG51*AA51 -> 929.96904 | AI51: =AH51/L51/I51 -> 0.135485 | AK51: =AJ51*AA51 -> 0 | AL51: =AK51/L51/I51 -> 0 | AM51: 0 | AN51: =AM51*AA51 -> 0 | AO51: =AN51/L51/I51 -> 0 | AP51: =SUM(AH51,AK51,AN51) -> 929.96904 | AQ51: =SUM(AI51,AL51,AO51) -> 0.135485 | AR51: =Y51 -> 960.96 | AS51: =AP51-AR51 -> -30.99096 | AT51: =O51/I51 -> 2.3716667 | AU51: =AT51-R51-T51 -> 2.2316667 | AV51: =(W51-AU51)/W51 -> 0.10374833 | AX51: =W51*100% -> 2.49 | AY51: =X51*50% -> 0 | AZ51: =AX51+AY51 -> 2.49 | BC51: Itu | BD51: HNK BR INDUSTRIA DE BEBIDAS LTDA. | BE51: 50.221.019/0001-36 | BF51: 387000650117 | BG51: Av Primo Schincariol | BH51: 2222 | BI51: Chácara Flórida | BJ51: 13312250 | BK51: Itu | BL51: SP
A52: =0.35*12/100 -> 0.042 | B52: =VLOOKUP(F52,Planilha3!D:F,3,0) -> 14.755467 | C52: =B52/A52 -> 351.32064 | D52: Nab | E52: Fys | F52: 903793 | G52: 1155658 | H52: REFRIGERANTE FYS LARANJA 350 ML | I52: 12 | J52: 286 | K52: =J52*24 -> 6864 | L52: =J52*3 -> 858 | M52: =L52/J52 -> 3 | N52: =L52/K52 -> 0.125 | O52: 28.46 | P52: =O52/I52 -> 2.3716667 | Q52: =R52*I52 -> 1.68 | R52: 0.14 | S52: =I52*T52 -> 0 | T52: 0 | U52: =SUM(R52,T52) -> 0.14 | V52: =VLOOKUP(F52,'[1]Proposta HNK para Tenda'!$F:$T,15,0) -> 2.79 | W52: =VLOOKUP(F52,'[1]Proposta HNK para Tenda'!$F:$U,16,0) -> 2.49 | Y52: =L52*(Q52+S52) -> 1441.44 | Z52: =L52*O52 -> 24418.68 | AA52: =L52*12*0.35/100 -> 36.036 | AC52: =SUM(AI52,AL52,AO52) -> 0.135485 | AD52: =SUM(R52,T52) -> 0.14 | AE52: =AC52-AD52 -> -0.004515 | AG52: 38.71 | AH52: =AG52*AA52 -> 1394.9536 | AI52: =AH52/L52/I52 -> 0.135485 | AK52: =AJ52*AA52 -> 0 | AL52: =AK52/L52/I52 -> 0 | AM52: 0 | AN52: =AM52*AA52 -> 0 | AO52: =AN52/L52/I52 -> 0 | AP52: =SUM(AH52,AK52,AN52) -> 1394.9536 | AQ52: =SUM(AI52,AL52,AO52) -> 0.135485 | AR52: =Y52 -> 1441.44 | AS52: =AP52-AR52 -> -46.48644 | AT52: =O52/I52 -> 2.3716667 | AU52: =AT52-R52-T52 -> 2.2316667 | AV52: =(W52-AU52)/W52 -> 0.10374833 | AX52: =W52*100% -> 2.49 | AY52: =X52*50% -> 0 | AZ52: =AX52+AY52 -> 2.49 | BC52: Itu | BD52: HNK BR INDUSTRIA DE BEBIDAS LTDA. | BE52: 50.221.019/0001-36 | BF52: 387000650117 | BG52: Av Primo Schincariol | BH52: 2222 | BI52: Chácara Flórida | BJ52: 13312250 | BK52: Itu | BL52: SP
A53: =0.35*12/100 -> 0.042 | B53: =VLOOKUP(F53,Planilha3!D:F,3,0) -> 38.107263 | C53: =B53/A53 -> 907.31578 | D53: Nab | E53: Fys Tônica | F53: 903797 | G53: 1155678 | H53: REFRIGERANTE FYS TÔNICA 350 ML | I53: 12 | J53: 286 | K53: =J53*24 -> 6864 | L53: =J53*5 -> 1430 | M53: =L53/J53 -> 5 | N53: =L53/K53 -> 0.20833333 | O53: 31.52 | P53: =O53/I53 -> 2.6266667 | Q53: =R53*I53 -> 1.68 | R53: 0.14 | S53: =I53*T53 -> 0 | T53: 0 | U53: =SUM(R53,T53) -> 0.14 | V53: =VLOOKUP(F53,'[1]Proposta HNK para Tenda'!$F:$T,15,0) -> 3.09 | W53: =VLOOKUP(F53,'[1]Proposta HNK para Tenda'!$F:$U,16,0) -> 2.79 | Y53: =L53*(Q53+S53) -> 2402.4 | Z53: =L53*O53 -> 45073.6 | AA53: =L53*12*0.35/100 -> 60.06 | AC53: =SUM(AI53,AL53,AO53) -> 0.135485 | AD53: =SUM(R53,T53) -> 0.14 | AE53: =AC53-AD53 -> -0.004515 | AG53: 38.71 | AH53: =AG53*AA53 -> 2324.9226 | AI53: =AH53/L53/I53 -> 0.135485 | AK53: =AJ53*AA53 -> 0 | AL53: =AK53/L53/I53 -> 0 | AM53: 0 | AN53: =AM53*AA53 -> 0 | AO53: =AN53/L53/I53 -> 0 | AP53: =SUM(AH53,AK53,AN53) -> 2324.9226 | AQ53: =SUM(AI53,AL53,AO53) -> 0.135485 | AR53: =Y53 -> 2402.4 | AS53: =AP53-AR53 -> -77.4774 | AT53: =O53/I53 -> 2.6266667 | AU53: =AT53-R53-T53 -> 2.4866667 | AV53: =(W53-AU53)/W53 -> 0.10872162 | AX53: =W53*100% -> 2.79 | AY53: =X53*50% -> 0 | AZ53: =AX53+AY53 -> 2.79 | BC53: Itu | BD53: HNK BR INDUSTRIA DE BEBIDAS LTDA. | BE53: 50.221.019/0001-36 | BF53: 387000650117 | BG53: Av Primo Schincariol | BH53: 2222 | BI53: Chácara Flórida | BJ53: 13312250 | BK53: Itu | BL53: SP
A54: =0.35*12/100 -> 0.042 | B54: =VLOOKUP(F54,Planilha3!D:F,3,0) -> 27.361385 | C54: =B54/A54 -> 651.46155 | D54: Nab | E54: Fys Tônica | F54: 904496 | G54: 1155679 | H54: REFRIGERANTE FYS TÔNICA ZERO 350 ML | I54: 12 | J54: 286 | K54: =J54*24 -> 6864 | L54: =J54*3 -> 858 | M54: =L54/J54 -> 3 | N54: =L54/K54 -> 0.125 | O54: 31.52 | P54: =O54/I54 -> 2.6266667 | Q54: =R54*I54 -> 1.68 | R54: 0.14 | S54: =I54*T54 -> 0 | T54: 0 | U54: =SUM(R54,T54) -> 0.14 | V54: 3.09 | W54: 2.79 | Y54: =L54*(Q54+S54) -> 1441.44 | Z54: =L54*O54 -> 27044.16 | AA54: =L54*12*0.35/100 -> 36.036 | AC54: =SUM(AI54,AL54,AO54) -> 0.135485 | AD54: =SUM(R54,T54) -> 0.14 | AE54: =AC54-AD54 -> -0.004515 | AG54: 38.71 | AH54: =AG54*AA54 -> 1394.9536 | AI54: =AH54/L54/I54 -> 0.135485 | AK54: =AJ54*AA54 -> 0 | AL54: =AK54/L54/I54 -> 0 | AM54: 0 | AN54: =AM54*AA54 -> 0 | AO54: =AN54/L54/I54 -> 0 | AP54: =SUM(AH54,AK54,AN54) -> 1394.9536 | AQ54: =SUM(AI54,AL54,AO54) -> 0.135485 | AR54: =Y54 -> 1441.44 | AS54: =AP54-AR54 -> -46.48644 | AT54: =O54/I54 -> 2.6266667 | AU54: =AT54-R54-T54 -> 2.4866667 | AV54: =(W54-AU54)/W54 -> 0.10872162 | AX54: =W54*100% -> 2.79 | AY54: =X54*50% -> 0 | AZ54: =AX54+AY54 -> 2.79 | BC54: Itu | BD54: HNK BR INDUSTRIA DE BEBIDAS LTDA. | BE54: 50.221.019/0001-36 | BF54: 387000650117 | BG54: Av Primo Schincariol | BH54: 2222 | BI54: Chácara Flórida | BJ54: 13312250 | BK54: Itu | BL54: SP
A55: =0.355*24/100 -> 0.0852 | B55: =VLOOKUP(F55,Planilha3!D:F,3,0) -> 335.37163 | C55: =B55/A55 -> 3936.2868 | D55: Nab | E55: Itubaina | F55: 900525 | G55: 90725 | H55: REFRIGERANTE ITUBAINA RETRO LN 355 ML | I55: 12 | J55: 175 | K55: =J55*24 -> 4200 | L55: =K55*1 -> 4200 | M55: =L55/J55 -> 24 | N55: =L55/K55 -> 1 | O55: 34.58 | P55: =O55/I55 -> 2.8816667 | Q55: =R55*I55 -> 0 | R55: 0 | S55: =I55*T55 -> 0 | T55: 0 | U55: =SUM(R55,T55) -> 0 | V55: =VLOOKUP(F55,'[1]Proposta HNK para Tenda'!$F:$T,15,0) -> 3.39 | W55: =VLOOKUP(F55,'[1]Proposta HNK para Tenda'!$F:$U,16,0) -> 3.39 | Y55: =L55*(Q55+S55) -> 0 | Z55: =L55*O55 -> 145236 | AA55: =L55*24*0.355/100 -> 357.84 | AC55: =SUM(AI55,AL55,AO55) -> 0 | AD55: =SUM(R55,T55) -> 0 | AE55: =AC55-AD55 -> 0 | AG55: 0 | AH55: =AG55*AA55 -> 0 | AI55: =AH55/L55/I55 -> 0 | AK55: =AJ55*AA55 -> 0 | AL55: =AK55/L55/I55 -> 0 | AM55: 0 | AN55: =AM55*AA55 -> 0 | AO55: =AN55/L55/I55 -> 0 | AP55: =SUM(AH55,AK55,AN55) -> 0 | AQ55: =SUM(AI55,AL55,AO55) -> 0 | AR55: =Y55 -> 0 | AS55: =AP55-AR55 -> 0 | AT55: =O55/I55 -> 2.8816667 | AU55: =AT55-R55-T55 -> 2.8816667 | AV55: =(W55-AU55)/W55 -> 0.14995084 | AX55: =W55*100% -> 3.39 | AY55: =X55*50% -> 0 | AZ55: =AX55+AY55 -> 3.39 | BC55: Itu | BD55: HNK BR INDUSTRIA DE BEBIDAS LTDA. | BE55: 50.221.019/0001-36 | BF55: 387000650117 | BG55: Av Primo Schincariol | BH55: 2222 | BI55: Chácara Flórida | BJ55: 13312250 | BK55: Itu | BL55: SP
A56: =0.35*12/100 -> 0.042 | B56: =VLOOKUP(F56,Planilha3!D:F,3,0) -> 791.97115 | C56: =B56/A56 -> 18856.456 | D56: Nab | E56: Itubaina | F56: 902321 | G56: 1015460 | H56: REFRIGERANTE ITUBAINA RETRO LATA 350 ML | I56: 12 | J56: 286 | K56: =J56*24 -> 6864 | L56: =K56*3 -> 20592 | M56: =L56/J56 -> 72 | N56: =L56/K56 -> 3 | O56: 29.48 | P56: =O56/I56 -> 2.4566667 | Q56: =R56*I56 -> 0.84 | R56: 0.07 | S56: =I56*T56 -> 0 | T56: 0 | U56: =SUM(R56,T56) -> 0.07 | V56: =VLOOKUP(F56,'[1]Proposta HNK para Tenda'!$F:$T,15,0) -> 2.89 | W56: =VLOOKUP(F56,'[1]Proposta HNK para Tenda'!$F:$U,16,0) -> 2.59 | Y56: =L56*(Q56+S56) -> 17297.28 | Z56: =L56*O56 -> 607052.16 | AA56: =L56*12*0.35/100 -> 864.864 | AC56: =SUM(AI56,AL56,AO56) -> 0.08449 | AD56: =SUM(R56,T56) -> 0.07 | AE56: =AC56-AD56 -> 0.01449 | AG56: 24.14 | AH56: =AG56*AA56 -> 20877.817 | AI56: =AH56/L56/I56 -> 0.08449 | AK56: =AJ56*AA56 -> 0 | AL56: =AK56/L56/I56 -> 0 | AM56: 0 | AN56: =AM56*AA56 -> 0 | AO56: =AN56/L56/I56 -> 0 | AP56: =SUM(AH56,AK56,AN56) -> 20877.817 | AQ56: =SUM(AI56,AL56,AO56) -> 0.08449 | AR56: =Y56 -> 17297.28 | AS56: =AP56-AR56 -> 3580.537 | AT56: =O56/I56 -> 2.4566667 | AU56: =AT56-R56-T56 -> 2.3866667 | AV56: =(W56-AU56)/W56 -> 0.078507079 | AX56: =W56*100% -> 2.59 | AY56: =X56*50% -> 0 | AZ56: =AX56+AY56 -> 2.59 | BC56: Itu | BD56: HNK BR INDUSTRIA DE BEBIDAS LTDA. | BE56: 50.221.019/0001-36 | BF56: 387000650117 | BG56: Av Primo Schincariol | BH56: 2222 | BI56: Chácara Flórida | BJ56: 13312250 | BK56: Itu | BL56: SP
A57: =0.5*12/100 -> 0.06 | B57: =VLOOKUP(F57,Planilha3!D:F,3,0) -> 472.85525 | C57: =B57/A57 -> 7880.9208 | D57: Nab | E57: Itubaina | F57: 903318 | G57: 1059549 | H57: REFRIGERANTE ITUBAINA PET 500 ML | I57: 12 | J57: 176 | K57: =J57*24 -> 4224 | L57: =K57*2 -> 8448 | M57: =L57/J57 -> 48 | N57: =M57/24 -> 2 | O57: 35.6 | P57: =O57/I57 -> 2.9666667 | Q57: =R57*I57 -> 0.6 | R57: 0.05 | S57: =I57*T57 -> 0 | T57: 0 | U57: =SUM(R57,T57) -> 0.05 | V57: =VLOOKUP(F57,'[1]Proposta HNK para Tenda'!$F:$T,15,0) -> 3.49 | W57: =VLOOKUP(F57,'[1]Proposta HNK para Tenda'!$F:$U,16,0) -> 3.19 | Y57: =L57*(Q57+S57) -> 5068.8 | Z57: =L57*O57 -> 300748.8 | AA57: =L57*12*0.5/100 -> 506.88 | AC57: =SUM(AI57,AL57,AO57) -> 0.0515 | AD57: =SUM(R57,T57) -> 0.05 | AE57: =AC57-AD57 -> 0.0015 | AG57: 10.3 | AH57: =AG57*AA57 -> 5220.864 | AI57: =AH57/L57/I57 -> 0.0515 | AK57: =AJ57*AA57 -> 0 | AL57: =AK57/L57/I57 -> 0 | AM57: 0 | AN57: =AM57*AA57 -> 0 | AO57: =AN57/L57/I57 -> 0 | AP57: =SUM(AH57,AK57,AN57) -> 5220.864 | AQ57: =SUM(AI57,AL57,AO57) -> 0.0515 | AR57: =Y57 -> 5068.8 | AS57: =AP57-AR57 -> 152.064 | AT57: =O57/I57 -> 2.9666667 | AU57: =AT57-R57-T57 -> 2.9166667 | AV57: =(W57-AU57)/W57 -> 0.085684431 | AX57: =W57*100% -> 3.19 | AY57: =X57*50% -> 0 | AZ57: =AX57+AY57 -> 3.19 | BC57: Itu | BD57: HNK BR INDUSTRIA DE BEBIDAS LTDA. | BE57: 50.221.019/0001-36 | BF57: 387000650117 | BG57: Av Primo Schincariol | BH57: 2222 | BI57: Chácara Flórida | BJ57: 13312250 | BK57: Itu | BL57: SP
N58: =SUM(N5:N57) -> 113.73932 | Y58: =SUBTOTAL(9,Y5:Y57) -> 2606749.2 | Z58: =SUBTOTAL(9,Z5:Z57) -> 38692344 | AA58: =SUBTOTAL(9,AA5:AA57) -> 30361.505 | AH58: =SUBTOTAL(9,AH5:AH57) -> 1067795.8 | AK58: =SUBTOTAL(9,AK5:AK57) -> 174579.83 | AN58: =SUBTOTAL(9,AN5:AN57) -> 1512745.7 | AP58: =SUBTOTAL(9,AP5:AP57) -> 2755121.3 | AR58: =SUM(AR5:AR57) -> 2606749.2 | AS58: =AP58-AR58 -> 148372.06 | XEN58: =SUM(XEN5:XFD57) -> 0
AG60: Gerado | AH60: =AP58 -> 2755121.3
AG61: Sell in pedido | AH61: =Y58 -> 2606749.2
AG62: Diferença | AH62: =AH60-AH61 -> 148372.06 | AI62: 366046.2
W64: Fechamento por categoria | AE64: =AH60/Z58 -> 0.071205851 | AG64: % Gerado | AH64: =AH60/Z58 -> 0.071205851
W65: Craft | Y65: =SUM(Y29:Y47) -> 21000 | AG65: % Liberdo | AH65: =Y58/Z58 -> 0.067371189
W66: Premiun | Y66: =SUM(Y10:Y25) -> 1631013.4
W67: Mainstream | Y67: =SUM(Y5:Y6,Y7) -> 920270.4
W68: Refrigerante | Y68: =SUM(Y48:Y57) -> 32456.16
Y69: =SUM(Y65:Y68) -> 2604739.9

Sheet Contra Assaí Ultimo Tri
T1: 0.2 | U1: 0.75
T2: 0.08 | U2: 0.3 | AI2: =SUBTOTAL(9,AI5:AI47) -> 3116511.7 | AL2: =SUBTOTAL(9,AL5:AL47) -> 780649.74 | AO2: =SUBTOTAL(9,AO5:AO47) -> 5525350.1
B3: =SUBTOTAL(9,B5:B47) -> #N/A | W3: SUGESTÃO DE PREÇO OUT'25 | Z3: =SUBTOTAL(9,Z5:Z47) -> 9417451.2 | AB3: =SUBTOTAL(9,AB5:AB47) -> 89092.45 | AD3: Total de Investimento Gerado | AE3: TT Investimento Liberado | AF3: Diferença | AI3: Verba Calendario TPR | AL3: Back Margem | AO3: Verba Adicional | AQ3: =SUBTOTAL(9,AQ5:AQ47) -> 9422511.5 | AW3: Margem entregue no promo
A4: Coeficiente | B4: HL Act Restrito | C4: Em caixas | D4: Categoria | E4: Marcas | F4: CÓDIGO SAP HNK | G4: CÓDIGO | H4: PRODUTO | I4: CX | J4: PALETE | K4: CARGA | L4: QTDE COMPRA | M4: QTDE PALETE | N4: QTDE CARRO | O4: CUSTO CX NF | P4: Custo Unitário | Q4: VERBA SELL IN CX | R4: * VERBA SELL IN UND | S4: VERBA ADIC CX | T4: * VERBA ADIC UND | U4: Total Investimento Liberado | V4: Investimento solicitado pelo Assaí | W4: PREÇO REGULAR | X4: PREÇO PROMO | Y4: PREÇO LIBERADO TELE | Z4: VERBA TOTAL SELL IN | AA4: TOTAL PEDIDO NF | AB4: HL | AH4: R$/HL | AI4: Verba Gerado | AJ4: Verba unidade | AK4: R$/HL | AL4: Verba Gerado | AM4: Verba unidade | AN4: R$/HL | AO4: Verba Gerado | AP4: Verba unidade | AQ4: Gerado total | AR4: Unidade total | AS4: VERBA TOTAL SELL IN | AT4: Saving | AU4: CUSTO UNI. NF | AV4: NOVO CUSTO | AY4: 50% Volume preço Promo | AZ4: 50% Volume preço Televendas | BA4: Preço Médio | BB4: Margem entregue | BD4: Cidade | BE4: Razão social | BF4: CNPJ | BG4: Inscrição estadual | BH4: Endereço | BI4: Número | BJ4: Bairro | BK4: Cidade | BL4: Estado | BM4: Cep
A5: 0.03228 | B5: =VLOOKUP(F5,Planilha3!D:F,3,0) -> 1663.6933 | C5: =B5/A5 -> 51539.444 | D5: Mainstream | E5: Amstel | F5: 904113 | G5: 1052772 | H5: CERVEJA AMSTEL 269ML | I5: 12 | J5: 336 | K5: =J5*24 -> 8064 | L5: 645120 | M5: =L5/J5 -> 1920 | N5: =L5/K5 -> 80 | O5: 33.16 | P5: =O5/I5 -> 2.7633333 | Q5: =R5*I5 -> 0.6 | R5: 0.05 | S5: =T5*I5 -> 3.6 | T5: 0.3 | U5: =SUM(R5,T5) -> 0.35 | V5: 0.35 | W5: =VLOOKUP(F5,'[1]Proposta HNK para Tenda'!$F:$T,15,0) -> 3.29 | X5: =VLOOKUP(F5,'[1]Proposta HNK para Tenda'!$F:$U,16,0) -> 3.09 | Y5: 2.79 | Z5: =L5*(Q5+S5) -> 2709504 | AA5: =L5*O5 -> 21392179 | AB5: =L5*12*0.269/100 -> 20824.474 | AD5: =SUM(AJ5,AM5,AP5) -> 0.3681265 | AE5: =SUM(R5,T5) -> 0.35 | AF5: =AD5-AE5 -> 0.0181265 | AH5: 19.98 | AI5: =AH5*AB5 -> 416072.98 | AJ5: =AI5/L5/I5 -> 0.0537462 | AK5: 23.87 | AL5: =AK5*AB5 -> 497080.18 | AM5: =AL5/L5/I5 -> 0.0642103 | AN5: 93 | AO5: =AN5*AB5 -> 1936676 | AP5: =AO5/L5/I5 -> 0.25017 | AQ5: =SUM(AI5,AL5,AO5) -> 2849829.2 | AR5: =SUM(AJ5,AM5,AP5) -> 0.3681265 | AS5: =Z5 -> 2709504 | AT5: =AQ5-AS5 -> 140325.21 | AU5: =O5/I5 -> 2.7633333 | AV5: =AU5-R5-T5 -> 2.4133333 | AW5: =(X5-AV5)/X5 -> 0.21898598 | AY5: =X5*50% -> 1.545 | AZ5: =Y5*50% -> 1.395 | BA5: =AY5+AZ5 -> 2.94 | BB5: =(X5-Y5)/X5 -> 0.097087379 | BD5: Itu | BE5: HNK BR INDUSTRIA DE BEBIDAS LTDA. | BF5: 50.221.019/0001-36 | BG5: 387000650117 | BH5: Av Primo Schincariol | BI5: 2222 | BJ5: Chácara Flórida | BK5: 13312250 | BL5: Itu | BM5: SP
A6: 0.042 | B6: =VLOOKUP(F6,Planilha3!D:F,3,0) -> 1031.9338 | C6: =B6/A6 -> 24569.852 | D6: Mainstream | E6: Amstel | F6: 904952 | G6: 1193288 | H6: CERVEJA AMSTEL 350ML SLEEK | I6: 12 | J6: 280 | K6: =J6*24 -> 6720 | L6: 302400 | M6: =L6/J6 -> 1080 | N6: =L6/K6 -> 45 | O6: 39.21 | P6: =O6/I6 -> 3.2675 | Q6: =R6*I6 -> 1.2 | R6: 0.1 | S6: =T6*I6 -> 3.24 | T6: 0.27 | U6: =SUM(R6,T6) -> 0.37 | V6: 0.37 | W6: =VLOOKUP(F6,'[1]Proposta HNK para Tenda'!$F:$T,15,0) -> 3.89 | X6: =VLOOKUP(F6,'[1]Proposta HNK para Tenda'!$F:$U,16,0) -> 3.69 | Y6: 3.29 | Z6: =L6*(Q6+S6) -> 1342656 | AA6: =L6*O6 -> 11857104 | AB6: =L6*12*0.35/100 -> 12700.8 | AD6: =SUM(AJ6,AM6,AP6) -> 0.378 | AE6: =SUM(R6,T6) -> 0.37 | AF6: =AD6-AE6 -> 0.008 | AH6: 21.4 | AI6: =AH6*AB6 -> 271797.12 | AJ6: =AI6/L6/I6 -> 0.0749 | AK6: 21.6 | AL6: =AK6*AB6 -> 274337.28 | AM6: =AL6/L6/I6 -> 0.0756 | AN6: 65 | AO6: =AN6*AB6 -> 825552 | AP6: =AO6/L6/I6 -> 0.2275 | AQ6: =SUM(AI6,AL6,AO6) -> 1371686.4 | AR6: =SUM(AJ6,AM6,AP6) -> 0.378 | AS6: =Z6 -> 1342656 | AT6: =AQ6-AS6 -> 29030.4 | AU6: =O6/I6 -> 3.2675 | AV6: =AU6-R6-T6 -> 2.8975 | AW6: =(X6-AV6)/X6 -> 0.21476965 | AY6: =X6*50% -> 1.845 | AZ6: =Y6*50% -> 1.645 | BA6: =AY6+AZ6 -> 3.49 | BB6: =(X6-Y6)/X6 -> 0.10840108 | BD6: Jacarei | BE6: HNK BR INDUSTRIA DE BEBIDAS LTDA. | BF6: 50.221.019/0104-41 | BG6: 392558326113 | BH6: Av Presidente Humberto de Alencar Castelo Branco | BI6: 2911 | BJ6: Conjunto Habitacional Marinho | BK6: 12321150 | BL6: Jacareí | BM6: SP
A7: 0.072 | B7: =VLOOKUP(F7,Planilha3!D:F,3,0) -> 40.23064 | C7: =B7/A7 -> 558.75888 | D7: Mainstream | E7: Amstel | F7: 905052 | G7: 1207152 | H7: CERVEJA AMSTEL LN 355ML | I7: 12 | J7: 175 | K7: =J7*24 -> 4200 | L7: 8400 | M7: =L7/J7 -> 48 | N7: =L7/K7 -> 2 | O7: 47.28 | P7: =O7/I7 -> 3.94 | Q7: =R7*I7 -> 0.6 | R7: 0.05 | S7: =T7*I7 -> 9 | T7: 0.75 | U7: =SUM(R7,T7) -> 0.8 | V7: 0.8 | W7: =VLOOKUP(F7,'[1]Proposta HNK para Tenda'!$F:$T,15,0) -> 4.69 | X7: =VLOOKUP(F7,'[1]Proposta HNK para Tenda'!$F:$U,16,0) -> 4.49 | Z7: =L7*(Q7+S7) -> 80640 | AA7: =L7*O7 -> 397152 | AB7: =L7*12*0.355/100 -> 357.84 | AD7: =SUM(AJ7,AM7,AP7) -> 0.1662465 | AE7: =SUM(R7,T7) -> 0.8 | AF7: =AD7-AE7 -> -0.6337535 | AH7: 21.03 | AI7: =AH7*AB7 -> 7525.3752 | AJ7: =AI7/L7/I7 -> 0.0746565 | AK7: 25.8 | AL7: =AK7*AB7 -> 9232.272 | AM7: =AL7/L7/I7 -> 0.09159 | AN7: 0 | AO7: =AN7*AB7 -> 0 | AP7: =AO7/L7/I7 -> 0 | AQ7: =SUM(AI7,AL7,AO7) -> 16757.647 | AR7: =SUM(AJ7,AM7,AP7) -> 0.1662465 | AS7: =Z7 -> 80640 | AT7: =AQ7-AS7 -> -63882.353 | AU7: =O7/I7 -> 3.94 | AV7: =AU7-R7-T7 -> 3.14 | AW7: =(X7-AV7)/X7 -> 0.30066815 | AY7: =X7*100% -> 4.49 | AZ7: =Y7*50% -> 0 | BA7: =AY7+AZ7 -> 4.49 | BD7: Itu | BE7: HNK BR INDUSTRIA DE BEBIDAS LTDA. | BF7: 50.221.019/0001-36 | BG7: 387000650117 | BH7: Av Primo Schincariol | BI7: 2222 | BJ7: Chácara Flórida | BK7: 13312250 | BL7: Itu | BM7: SP
A8: =0.275*12/100 -> 0.033 | B8: =VLOOKUP(F8,Planilha3!D:F,3,0) -> #N/A | C8: =B8/A8 -> #N/A | D8: Mainstream | E8: Amstel | F8: 904632 | G8: 1155684 | H8: CERVEJA AMSTEL ULTRA 269 ML | I8: 12 | J8: 364 | K8: =J8*24 -> 8736 | L8: =K8*2 -> 17472 | M8: =L8/J8 -> 48 | N8: =L8/K8 -> 2 | O8: 39.26 | P8: =O8/I8 -> 3.2716667 | Q8: =R8*I8 -> 1.2 | R8: 0.1 | S8: =T8*I8 -> 1.56 | T8: 0.13 | U8: =SUM(R8,T8) -> 0.23 | V8: 0.23 | W8: 3.99 | X8: 3.49 | Z8: =L8*(Q8+S8) -> 48222.72 | AA8: =L8*O8 -> 685950.72 | AB8: =L8*12*0.275/100 -> 576.576 | AD8: =SUM(AJ8,AM8,AP8) -> 0.2377375 | AE8: =SUM(R8,T8) -> 0.23 | AF8: =AD8-AE8 -> 0.0077375 | AH8: 86.45 | AI8: =AH8*AB8 -> 49844.995 | AJ8: =AI8/L8/I8 -> 0.2377375 | AK8: 0 | AL8: =AK8*AB8 -> 0 | AM8: =AL8/L8/I8 -> 0 | AN8: 0 | AO8: =AN8*AB8 -> 0 | AP8: =AO8/L8/I8 -> 0 | AQ8: =SUM(AI8,AL8,AO8) -> 49844.995 | AR8: =SUM(AJ8,AM8,AP8) -> 0.2377375 | AS8: =Z8 -> 48222.72 | AT8: =AQ8-AS8 -> 1622.2752 | AU8: =O8/I8 -> 3.2716667 | AV8: =AU8-R8-T8 -> 3.0416667 | AW8: =(X8-AV8)/X8 -> 0.12846227 | AY8: =X8*100% -> 3.49 | AZ8: =Y8*50% -> 0 | BA8: =AY8+AZ8 -> 3.49 | BD8: Itu | BE8: HNK BR INDUSTRIA DE BEBIDAS LTDA. | BF8: 50.221.019/0001-36 | BG8: 387000650117 | BH8: Av Primo Schincariol | BI8: 2222 | BJ8: Chácara Flórida | BK8: 13312250 | BL8: Itu | BM8: SP
A9: =0.275*12/100 -> 0.033 | B9: =VLOOKUP(F9,Planilha3!D:F,3,0) -> 7.6058015 | C9: =B9/A9 -> 230.47883 | D9: Mainstream | E9: Amstel | F9: 904631 | G9: 1160860 | H9: CERVEJA AMSTEL ULTRA LN 275 ML | I9: 12 | J9: 196 | K9: =J9*24 -> 4704 | L9: =K9*1 -> 4704 | M9: =L9/J9 -> 24 | N9: =L9/K9 -> 1 | O9: 47.13 | P9: =O9/I9 -> 3.9275 | Q9: =R9*I9 -> 0 | R9: 0 | S9: =T9*I9 -> 0 | T9: 0 | U9: =SUM(R9,T9) -> 0 | V9: 0 | W9: =VLOOKUP(F9,'[1]Proposta HNK para Tenda'!$F:$T,15,0) -> 4.79 | X9: =VLOOKUP(F9,'[1]Proposta HNK para Tenda'!$F:$U,16,0) -> 4.79 | Z9: =L9*(Q9+S9) -> 0 | AA9: =L9*O9 -> 221699.52 | AB9: =L9*12*0.275/100 -> 155.232 | AD9: =SUM(AJ9,AM9,AP9) -> 0 | AE9: =SUM(R9,T9) -> 0 | AF9: =AD9-AE9 -> 0 | AH9: 0 | AI9: =AH9*AB9 -> 0 | AJ9: =AI9/L9/I9 -> 0 | AL9: =AK9*AB9 -> 0 | AM9: =AL9/L9/I9 -> 0 | AN9: 0 | AO9: =AN9*AB9 -> 0 | AP9: =AO9/L9/I9 -> 0 | AQ9: =SUM(AI9,AL9,AO9) -> 0 | AR9: =SUM(AJ9,AM9,AP9) -> 0 | AS9: =Z9 -> 0 | AT9: =AQ9-AS9 -> 0 | AU9: =O9/I9 -> 3.9275 | AV9: =AU9-R9-T9 -> 3.9275 | AW9: =(X9-AV9)/X9 -> 0.18006263 | AY9: =X9*100% -> 4.79 | AZ9: =Y9*50% -> 0 | BA9: =AY9+AZ9 -> 4.79 | BD9: Itu | BE9: HNK BR INDUSTRIA DE BEBIDAS LTDA. | BF9: 50.221.019/0001-36 | BG9: 387000650117 | BH9: Av Primo Schincariol | BI9: 2222 | BJ9: Chácara Flórida | BK9: 13312250 | BL9: Itu | BM9: SP
A10: 0.03228 | B10: =VLOOKUP(F10,Planilha3!D:F,3,0) -> 113.71405 | C10: =B10/A10 -> 3522.7399 | D10: Premium | E10: Eisenbahn | F10: 904194 | G10: 1153719 | H10: CERVEJA EISENBAHN PILSEN 269ML | I10: 12 | J10: 364 | K10: =J10*24 -> 8736 | L10: 8736 | M10: =L10/J10 -> 24 | N10: =L10/K10 -> 1 | O10: 31.52 | P10: =O10/I10 -> 2.6266667 | Q10: =R10*I10 -> 0 | R10: 0 | S10: =T10*I10 -> 0 | T10: 0 | U10: =SUM(R10,T10) -> 0 | V10: 0 | W10: 3.09 | X10: 3.09 | Z10: =L10*(Q10+S10) -> 0 | AA10: =L10*O10 -> 275358.72 | AB10: =L10*12*0.269/100 -> 281.99808 | AD10: =SUM(AJ10,AM10,AP10) -> 0 | AE10: =SUM(R10,T10) -> 0 | AF10: =AD10-AE10 -> 0 | AH10: 0 | AI10: =AH10*AB10 -> 0 | AJ10: =AI10/L10/I10 -> 0 | AL10: =AK10*AB10 -> 0 | AM10: =AL10/L10/I10 -> 0 | AN10: 0 | AO10: =AN10*AB10 -> 0 | AP10: =AO10/L10/I10 -> 0 | AQ10: =SUM(AI10,AL10,AO10) -> 0 | AR10: =SUM(AJ10,AM10,AP10) -> 0 | AS10: =Z10 -> 0 | AT10: =AQ10-AS10 -> 0 | AU10: =O10/I10 -> 2.6266667 | AV10: =AU10-R10-T10 -> 2.6266667 | AW10: =(X10-AV10)/X10 -> 0.14994606 | AY10: =X10*100% -> 3.09 | AZ10: =Y10*50% -> 0 | BA10: =AY10+AZ10 -> 3.09 | BD10: Itu | BE10: HNK BR INDUSTRIA DE BEBIDAS LTDA. | BF10: 50.221.019/0001-36 | BG10: 387000650117 | BH10: Av Primo Schincariol | BI10: 2222 | BJ10: Chácara Flórida | BK10: 13312250 | BL10: Itu | BM10: SP
A11: 0.042 | B11: =VLOOKUP(F11,Planilha3!D:F,3,0) -> 719.15382 | C11: =B11/A11 -> 17122.71 | D11: Premium | E11: Eisenbahn | F11: 903750 | G11: 1055249 | H11: CERVEJA EISENBAHN PILSEN 350ML | I11: 12 | J11: 280 | K11: =J11*24 -> 6720 | L11: 13440 | M11: =L11/J11 -> 48 | N11: =L11/K11 -> 2 | O11: 40.7 | P11: =O11/I11 -> 3.3916667 | Q11: =R11*I11 -> 0 | R11: 0 | S11: =T11*I11 -> 0 | T11: 0 | U11: =SUM(R11,T11) -> 0 | V11: 0 | W11: 3.99 | X11: 3.99 | Z11: =L11*(Q11+S11) -> 0 | AA11: =L11*O11 -> 547008 | AB11: =L11*12*0.35/100 -> 564.48 | AD11: =SUM(AJ11,AM11,AP11) -> 0 | AE11: =SUM(R11,T11) -> 0 | AF11: =AD11-AE11 -> 0 | AH11: 0 | AI11: =AH11*AB11 -> 0 | AJ11: =AI11/L11/I11 -> 0 | AL11: =AK11*AB11 -> 0 | AM11: =AL11/L11/I11 -> 0 | AN11: 0 | AO11: =AN11*AB11 -> 0 | AP11: =AO11/L11/I11 -> 0 | AQ11: =SUM(AI11,AL11,AO11) -> 0 | AR11: =SUM(AJ11,AM11,AP11) -> 0 | AS11: =Z11 -> 0 | AT11: =AQ11-AS11 -> 0 | AU11: =O11/I11 -> 3.3916667 | AV11: =AU11-R11-T11 -> 3.3916667 | AW11: =(X11-AV11)/X11 -> 0.14995823 | AY11: =X11*100% -> 3.99 | AZ11: =Y11*50% -> 0 | BA11: =AY11+AZ11 -> 3.99 | BD11: Itu | BE11: HNK BR INDUSTRIA DE BEBIDAS LTDA. | BF11: 50.221.019/0001-36 | BG11: 387000650117 | BH11: Av Primo Schincariol | BI11: 2222 | BJ11: Chácara Flórida | BK11: 13312250 | BL11: Itu | BM11: SP
A12: 0.0426 | B12: =VLOOKUP(F12,Planilha3!D:F,3,0) -> 44.325777 | C12: =B12/A12 -> 1040.5112 | D12: Premium | E12: Eisenbahn | F12: 901781 | G12: 1016972 | H12: CERVEJA EISENBAHN PILSEN LN 355ML | I12: 12 | J12: 175 | K12: =J12*24 -> 4200 | L12: 58800 | M12: =L12/J12 -> 336 | N12: =L12/K12 -> 14 | O12: 51.92 | P12: =O12/I12 -> 4.3266667 | Q12: =R12*I12 -> 3 | R12: 0.25 | S12: =T12*I12 -> 0.36 | T12: 0.03 | U12: =SUM(R12,T12) -> 0.28 | V12: 0.28 | W12: 5.09 | X12: 4.19 | Z12: =L12*(Q12+S12) -> 197568 | AA12: =L12*O12 -> 3052896 | AB12: =L12*12*0.355/100 -> 2504.88 | AD12: =SUM(AJ12,AM12,AP12) -> 0.28826 | AE12: =SUM(R12,T12) -> 0.28 | AF12: =AD12-AE12 -> 0.00826 | AH12: 81.2 | AI12: =AH12*AB12 -> 203396.26 | AJ12: =AI12/L12/I12 -> 0.28826 | AL12: =AK12*AB12 -> 0 | AM12: =AL12/L12/I12 -> 0 | AN12: 0 | AO12: =AN12*AB12 -> 0 | AP12: =AO12/L12/I12 -> 0 | AQ12: =SUM(AI12,AL12,AO12) -> 203396.26 | AR12: =SUM(AJ12,AM12,AP12) -> 0.28826 | AS12: =Z12 -> 197568 | AT12: =AQ12-AS12 -> 5828.256 | AU12: =O12/I12 -> 4.3266667 | AV12: =AU12-R12-T12 -> 4.0466667 | AW12: =(X12-AV12)/X12 -> 0.034208433 | AY12: =X12*100% -> 4.19 | AZ12: =Y12*50% -> 0 | BA12: =AY12+AZ12 -> 4.19 | BD12: Itu | BE12: HNK BR INDUSTRIA DE BEBIDAS LTDA. | BF12: 50.221.019/0001-36 | BG12: 387000650117 | BH12: Av Primo Schincariol | BI12: 2222 | BJ12: Chácara Flórida | BK12: 13312250 | BL12: Itu | BM12: SP
A13: 0.042 | B13: =VLOOKUP(F13,Planilha3!D:F,3,0) -> 32.20274 | C13: =B13/A13 -> 766.73189 | D13: Premium | E13: Eisenbahn | F13: 904772 | G13: 1170146 | H13: CERVEJA EISENBAHN UNFILTERED LA 350ML | I13: 12 | J13: 280 | K13: =J13*24 -> 6720 | L13: 6720 | M13: =L13/J13 -> 24 | N13: =L13/K13 -> 1 | O13: 40.7 | P13: =O13/I13 -> 3.3916667 | Q13: =R13*I13 -> 0 | R13: 0 | S13: =T13*I13 -> 0 | T13: 0 | U13: =SUM(R13,T13) -> 0 | V13: 0 | W13: 3.99 | X13: 3.99 | Z13: =L13*(Q13+S13) -> 0 | AA13: =L13*O13 -> 273504 | AB13: =L13*12*0.35/100 -> 282.24 | AD13: =SUM(AJ13,AM13,AP13) -> 0 | AE13: =SUM(R13,T13) -> 0 | AF13: =AD13-AE13 -> 0 | AH13: 0 | AI13: =AH13*AB13 -> 0 | AJ13: =AI13/L13/I13 -> 0 | AL13: =AK13*AB13 -> 0 | AM13: =AL13/L13/I13 -> 0 | AN13: 0 | AO13: =AN13*AB13 -> 0 | AP13: =AO13/L13/I13 -> 0 | AQ13: =SUM(AI13,AL13,AO13) -> 0 | AR13: =SUM(AJ13,AM13,AP13) -> 0 | AS13: =Z13 -> 0 | AT13: =AQ13-AS13 -> 0 | AU13: =O13/I13 -> 3.3916667 | AV13: =AU13-R13-T13 -> 3.3916667 | AW13: =(X13-AV13)/X13 -> 0.14995823 | AY13: =X13*100% -> 3.99 | AZ13: =Y13*50% -> 0 | BA13: =AY13+AZ13 -> 3.99 | BD13: Itu | BE13: HNK BR INDUSTRIA DE BEBIDAS LTDA. | BF13: 50.221.019/0001-36 | BG13: 387000650117 | BH13: Av Primo Schincariol | BI13: 2222 | BJ13: Chácara Flórida | BK13: 13312250 | BL13: Itu | BM13: SP
A14: 0.0426 | B14: =VLOOKUP(F14,Planilha3!D:F,3,0) -> 1.8908876 | C14: =B14/A14 -> 44.387033 | D14: Premium | E14: Eisenbahn | F14: 904771 | G14: 1170180 | H14: CERVEJA EISENBAHN UNFILTERED LN 355ML | I14: 12 | J14: 175 | K14: =J14*24 -> 4200 | L14: =J14*10 -> 1750 | M14: =L14/J14 -> 10 | N14: =L14/K14 -> 0.41666667 | O14: 51.92 | P14: =O14/I14 -> 4.3266667 | Q14: =R14*I14 -> 3 | R14: 0.25 | S14: =T14*I14 -> 0.36 | T14: 0.03 | U14: =SUM(R14,T14) -> 0.28 | V14: 0.28 | W14: 5.09 | X14: 4.19 | Z14: =L14*(Q14+S14) -> 5880 | AA14: =L14*O14 -> 90860 | AB14: =L14*12*0.355/100 -> 74.55 | AD14: =SUM(AJ14,AM14,AP14) -> 0.28826 | AE14: =SUM(R14,T14) -> 0.28 | AF14: =AD14-AE14 -> 0.00826 | AH14: 81.2 | AI14: =AH14*AB14 -> 6053.46 | AJ14: =AI14/L14/I14 -> 0.28826 | AL14: =AK14*AB14 -> 0 | AM14: =AL14/L14/I14 -> 0 | AN14: 0 | AO14: =AN14*AB14 -> 0 | AP14: =AO14/L14/I14 -> 0 | AQ14: =SUM(AI14,AL14,AO14) -> 6053.46 | AR14: =SUM(AJ14,AM14,AP14) -> 0.28826 | AS14: =Z14 -> 5880 | AT14: =AQ14-AS14 -> 173.46 | AU14: =O14/I14 -> 4.3266667 | AV14: =AU14-R14-T14 -> 4.0466667 | AW14: =(X14-AV14)/X14 -> 0.034208433 | AY14: =X14*100% -> 4.19 | AZ14: =Y14*50% -> 0 | BA14: =AY14+AZ14 -> 4.19 | BD14: Itu | BE14: HNK BR INDUSTRIA DE BEBIDAS LTDA. | BF14: 50.221.019/0001-36 | BG14: 387000650117 | BH14: Av Primo Schincariol | BI14: 2222 | BJ14: Chácara Flórida | BK14: 13312250 | BL14: Itu | BM14: SP
A15: =0.269*8/100 -> 0.02152 | B15: =VLOOKUP(F15,Planilha3!D:F,3,0) -> 105.66937 | C15: =B15/A15 -> 4910.2865 | D15: Premium | E15: Heineken | F15: 904895 | G15: 1208101 | H15: CERVEJA HEINEKEN 0% ALCOOL LA 269ML | I15: 8 | J15: 520 | K15: =J15*26 -> 13520 | L15: 27040 | M15: =L15/J15 -> 52 | N15: =L15/K15 -> 2 | O15: 31.21 | P15: =O15/I15 -> 3.90125 | Q15: =R15*I15 -> 0.8 | R15: 0.1 | S15: =T15*I15 -> 0.64 | T15: 0.08 | U15: =SUM(R15,T15) -> 0.18 | V15: 0.18 | W15: =VLOOKUP(F15,'[1]Proposta HNK para Tenda'!$F:$T,15,0) -> 4.59 | X15: =VLOOKUP(F15,'[1]Proposta HNK para Tenda'!$F:$U,16,0) -> 3.99 | Z15: =L15*(Q15+S15) -> 38937.6 | AA15: =L15*O15 -> 843918.4 | AB15: =L15*8*0.269/100 -> 581.9008 | AD15: =SUM(AJ15,AM15,AP15) -> 0.1905596 | AE15: =SUM(R15,T15) -> 0.18 | AF15: =AD15-AE15 -> 0.0105596 | AH15: 70.84 | AI15: =AH15*AB15 -> 41221.853 | AJ15: =AI15/L15/I15 -> 0.1905596 | AL15: =AK15*AB15 -> 0 | AM15: =AL15/L15/I15 -> 0 | AN15: 0 | AO15: =AN15*AB15 -> 0 | AP15: =AO15/L15/I15 -> 0 | AQ15: =SUM(AI15,AL15,AO15) -> 41221.853 | AR15: =SUM(AJ15,AM15,AP15) -> 0.1905596 | AS15: =Z15 -> 38937.6 | AT15: =AQ15-AS15 -> 2284.2527 | AU15: =O15/I15 -> 3.90125 | AV15: =AU15-R15-T15 -> 3.72125 | AW15: =(X15-AV15)/X15 -> 0.06735589 | AY15: =X15*100% -> 3.99 | AZ15: =Y15*50% -> 0 | BA15: =AY15+AZ15 -> 3.99 | BD15: Ponta Grossa | BE15: HNK BR INDUSTRIA DE BEBIDAS LTDA. | BF15: 50.221.019/0097-88 | BG15: 911.300.50.81 | BH15: Av Tocantins | BI15: 199 | BJ15: Cara-Cara | BK15: 84043610 | BL15: Ponta Grossa | BM15: PR
A16: 0.042 | B16: =VLOOKUP(F16,Planilha3!D:F,3,0) -> 151.60164 | C16: =B16/A16 -> 3609.5629 | D16: Premium | E16: Heineken | F16: 904961 | G16: 1193325 | H16: CERVEJA HEINEKEN 0% ALCOOL LA 350ML SLEEK | I16: 12 | J16: 280 | K16: =J16*26 -> 7280 | L16: 109200 | M16: =L16/J16 -> 390 | N16: =L16/K16 -> 15 | O16: 58.04 | P16: =O16/I16 -> 4.8366667 | Q16: =R16*I16 -> 1.2 | R16: 0.1 | S16: =T16*I16 -> 4.2 | T16: 0.35 | U16: =SUM(R16,T16) -> 0.45 | V16: 0.45 | W16: =VLOOKUP(F16,'[1]Proposta HNK para Tenda'!$F:$T,15,0) -> 5.69 | X16: =VLOOKUP(F16,'[1]Proposta HNK para Tenda'!$F:$U,16,0) -> 5.29 | Z16: =L16*(Q16+S16) -> 589680 | AA16: =L16*O16 -> 6337968 | AB16: =L16*12*0.35/100 -> 4586.4 | AD16: =SUM(AJ16,AM16,AP16) -> 0.47901 | AE16: =SUM(R16,T16) -> 0.45 | AF16: =AD16-AE16 -> 0.02901 | AH16: 33.86 | AI16: =AH16*AB16 -> 155295.5 | AJ16: =AI16/L16/I16 -> 0.11851 | AL16: =AK16*AB16 -> 0 | AM16: =AL16/L16/I16 -> 0 | AN16: 103 | AO16: =AN16*AB16 -> 472399.2 | AP16: =AO16/L16/I16 -> 0.3605 | AQ16: =SUM(AI16,AL16,AO16) -> 627694.7 | AR16: =SUM(AJ16,AM16,AP16) -> 0.47901 | AS16: =Z16 -> 589680 | AT16: =AQ16-AS16 -> 38014.704 | AU16: =O16/I16 -> 4.8366667 | AV16: =AU16-R16-T16 -> 4.3866667 | AW16: =(X16-AV16)/X16 -> 0.17076244 | AY16: =X16*100% -> 5.29 | AZ16: =Y16*50% -> 0 | BA16: =AY16+AZ16 -> 5.29 | BD16: Ponta Grossa | BE16: HNK BR INDUSTRIA DE BEBIDAS LTDA. | BF16: 50.221.019/0097-88 | BG16: 911.300.50.81 | BH16: Av Tocantins | BI16: 199 | BJ16: Cara-Cara | BK16: 84043610 | BL16: Ponta Grossa | BM16: PR
A17: 0.0792 | B17: =VLOOKUP(F17,Planilha3!D:F,3,0) -> 143.24875 | C17: =B17/A17 -> 1808.6964 | D17: Premium | E17: Heineken | F17: 903996 | G17: 1140139 | H17: CERVEJA HEINEKEN 0% ALCOOL LN 330ML | I17: 24 | J17: 91 | K17: =J17*26 -> 2366 | L17: 7098 | M17: =L17/J17 -> 78 | N17: =L17/K17 -> 3 | O17: 142.6 | P17: =O17/I17 -> 5.9416667 | Q17: =R17*I17 -> 1.2 | R17: 0.05 | S17: =T17*I17 -> 0.24 | T17: 0.01 | U17: =SUM(R17,T17) -> 0.06 | V17: 0.06 | W17: =VLOOKUP(F17,'[1]Proposta HNK para Tenda'!$F:$T,15,0) -> 6.99 | X17: =VLOOKUP(F17,'[1]Proposta HNK para Tenda'!$F:$U,16,0) -> 6.59 | Z17: =L17*(Q17+S17) -> 10221.12 | AA17: =L17*O17 -> 1012174.8 | AB17: =L17*24*0.33/100 -> 562.1616 | AD17: =SUM(AJ17,AM17,AP17) -> 0.068508 | AE17: =SUM(R17,T17) -> 0.06 | AF17: =AD17-AE17 -> 0.008508 | AH17: 20.76 | AI17: =AH17*AB17 -> 11670.475 | AJ17: =AI17/L17/I17 -> 0.068508 | AL17: =AK17*AB17 -> 0 | AM17: =AL17/L17/I17 -> 0 | AN17: 0 | AO17: =AN17*AB17 -> 0 | AP17: =AO17/L17/I17 -> 0 | AQ17: =SUM(AI17,AL17,AO17) -> 11670.475 | AR17: =SUM(AJ17,AM17,AP17) -> 0.068508 | AS17: =Z17 -> 10221.12 | AT17: =AQ17-AS17 -> 1449.3548 | AU17: =O17/I17 -> 5.9416667 | AV17: =AU17-R17-T17 -> 5.8816667 | AW17: =(X17-AV17)/X17 -> 0.10748609 | AY17: =X17*100% -> 6.59 | AZ17: =Y17*50% -> 0 | BA17: =AY17+AZ17 -> 6.59 | BD17: Ponta Grossa | BE17: HNK BR INDUSTRIA DE BEBIDAS LTDA. | BF17: 50.221.019/0097-88 | BG17: 911.300.50.81 | BH17: Av Tocantins | BI17: 199 | BJ17: Cara-Cara | BK17: 84043610 | BL17: Ponta Grossa | BM17: PR
A18: =0.269*8/100 -> 0.02152 | B18: =VLOOKUP(F18,Planilha3!D:F,3,0) -> 1756.2216 | C18: =B18/A18 -> 81608.811 | D18: Premium | E18: Heineken | F18: 904721 | G18: 1169727 | H18: CERVEJA HEINEKEN 269ML | I18: 8 | J18: 520 | K18: =J18*26 -> 13520 | L18: =K18*45 -> 608400 | M18: =L18/J18 -> 1170 | N18: =L18/K18 -> 45 | O18: 31.21 | P18: =O18/I18 -> 3.90125 | Q18: =R18*I18 -> 0.8 | R18: 0.1 | S18: =T18*I18 -> 1.44 | T18: 0.18 | U18: =SUM(R18,T18) -> 0.28 | V18: 0.4 | W18: =VLOOKUP(F18,'[1]Proposta HNK para Tenda'!$F:$T,15,0) -> 4.59 | X18: =VLOOKUP(F18,'[1]Proposta HNK para Tenda'!$F:$U,16,0) -> 3.99 | Z18: =L18*(Q18+S18) -> 1362816 | AA18: =L18*O18 -> 18988164 | AB18: =L18*8*0.269/100 -> 13092.768 | AD18: =SUM(AJ18,AM18,AP18) -> 0.1905596 | AE18: =SUM(R18,T18) -> 0.28 | AF18: =AD18-AE18 -> -0.0894404 | AH18: 70.84 | AI18: =AH18*AB18 -> 927491.69 | AJ18: =AI18/L18/I18 -> 0.1905596 | AL18: =AK18*AB18 -> 0 | AM18: =AL18/L18/I18 -> 0 | AN18: 0 | AO18: =AN18*AB18 -> 0 | AP18: =AO18/L18/I18 -> 0 | AQ18: =SUM(AI18,AL18,AO18) -> 927491.69 | AR18: =SUM(AJ18,AM18,AP18) -> 0.1905596 | AS18: =Z18 -> 1362816 | AT18: =AQ18-AS18 -> -435324.31 | AU18: =O18/I18 -> 3.90125 | AV18: =AU18-R18-T18 -> 3.62125 | AW18: =(X18-AV18)/X18 -> 0.092418546 | AY18: =X18*100% -> 3.99 | AZ18: =Y18*50% -> 0 | BA18: =AY18+AZ18 -> 3.99 | BD18: Ponta Grossa | BE18: HNK BR INDUSTRIA DE BEBIDAS LTDA. | BF18: 50.221.019/0097-88 | BG18: 911.300.50.81 | BH18: Av Tocantins | BI18: 199 | BJ18: Cara-Cara | BK18: 84043610 | BL18: Ponta Grossa | BM18: PR
A19: 0.042 | B19: =VLOOKUP(F19,Planilha3!D:F,3,0) -> 2524.72 | C19: =B19/A19 -> 60112.38 | D19: Premium | E19: Heineken | F19: 904932 | G19: 1193319 | H19: CERVEJA HEINEKEN 350ML SLEEK | I19: 12 | J19: 280 | K19: =J19*26 -> 7280 | L19: 509600 | M19: =L19/J19 -> 1820 | N19: =L19/K19 -> 70 | O19: 58.04 | P19: =O19/I19 -> 4.8366667 | Q19: =R19*I19 -> 1.2 | R19: 0.1 | S19: =T19*I19 -> 4.2 | T19: 0.35 | U19: =SUM(R19,T19) -> 0.45 | V19: 0.45 | W19: =VLOOKUP(F19,'[1]Proposta HNK para Tenda'!$F:$T,15,0) -> 5.69 | X19: =VLOOKUP(F19,'[1]Proposta HNK para Tenda'!$F:$U,16,0) -> 5.29 | Y19: 4.99 | Z19: =L19*(Q19+S19) -> 2751840 | AA19: =L19*O19 -> 29577184 | AB19: =L19*12*0.35/100 -> 21403.2 | AD19: =SUM(AJ19,AM19,AP19) -> 0.47901 | AE19: =SUM(R19,T19) -> 0.45 | AF19: =AD19-AE19 -> 0.02901 | AH19: 33.86 | AI19: =AH19*AB19 -> 724712.35 | AJ19: =AI19/L19/I19 -> 0.11851 | AL19: =AK19*AB19 -> 0 | AM19: =AL19/L19/I19 -> 0 | AN19: 103 | AO19: =AN19*AB19 -> 2204529.6 | AP19: =AO19/L19/I19 -> 0.3605 | AQ19: =SUM(AI19,AL19,AO19) -> 2929242 | AR19: =SUM(AJ19,AM19,AP19) -> 0.47901 | AS19: =Z19 -> 2751840 | AT19: =AQ19-AS19 -> 177401.95 | AU19: =O19/I19 -> 4.8366667 | AV19: =AU19-R19-T19 -> 4.3866667 | AW19: =(X19-AV19)/X19 -> 0.17076244 | AY19: =X19*50% -> 2.645 | AZ19: =Y19*50% -> 2.495 | BA19: =AY19+AZ19 -> 5.14 | BB19: =(X19-Y19)/X19 -> 0.056710775 | BD19: Jacarei | BE19: HNK BR INDUSTRIA DE BEBIDAS LTDA. | BF19: 50.221.019/0104-41 | BG19: 392558326113 | BH19: Av Presidente Humberto de Alencar Castelo Branco | BI19: 2911 | BJ19: Conjunto Habitacional Marinho | BK19: 12321150 | BL19: Jacareí | BM19: SP
A20: =0.25*24/100 -> 0.06 | B20: =VLOOKUP(F20,Planilha3!D:F,3,0) -> 501.62261 | C20: =B20/A20 -> 8360.3768 | D20: Premium | E20: Heineken | F20: 905291 | G20: 1016561 | H20: CERVEJA HEINEKEN LN 250ML | I20: 24 | J20: 104 | K20: =J20*26 -> 2704 | L20: 24336 | M20: =L20/J20 -> 234 | N20: =L20/K20 -> 9 | O20: 107.92 | P20: =O20/I20 -> 4.4966667 | Q20: =R20*I20 -> 1.2 | R20: 0.05 | S20: =T20*I20 -> 0.72 | T20: 0.03 | U20: =SUM(R20,T20) -> 0.08 | V20: 0.08 | W20: 5.29 | X20: 4.99 | Z20: =L20*(Q20+S20) -> 46725.12 | AA20: =L20*O20 -> 2626341.1 | AB20: =L20*24*0.25/100 -> 1460.16 | AD20: =SUM(AJ20,AM20,AP20) -> 0.237075 | AE20: =SUM(R20,T20) -> 0.08 | AF20: =AD20-AE20 -> 0.157075 | AH20: 35.8 | AI20: =AH20*AB20 -> 52273.728 | AJ20: =AI20/L20/I20 -> 0.0895 | AL20: =AK20*AB20 -> 0 | AM20: =AL20/L20/I20 -> 0 | AN20: 59.03 | AO20: =AN20*AB20 -> 86193.245 | AP20: =AO20/L20/I20 -> 0.147575 | AQ20: =SUM(AI20,AL20,AO20) -> 138466.97 | AR20: =SUM(AJ20,AM20,AP20) -> 0.237075 | AS20: =Z20 -> 46725.12 | AT20: =AQ20-AS20 -> 91741.853 | AU20: =O20/I20 -> 4.4966667 | AV20: =AU20-R20-T20 -> 4.4166667 | AW20: =(X20-AV20)/X20 -> 0.11489646 | AY20: =X20*100% -> 4.99 | AZ20: =Y20*50% -> 0 | BA20: =AY20+AZ20 -> 4.99 | BD20: Jacarei | BE20: HNK BR INDUSTRIA DE BEBIDAS LTDA. | BF20: 50.221.019/0104-41 | BG20: 392558326113 | BH20: Av Presidente Humberto de Alencar Castelo Branco | BI20: 2911 | BJ20: Conjunto Habitacional Marinho | BK20: 12321150 | BL20: Jacareí | BM20: SP
A21: 0.0792 | B21: =VLOOKUP(F21,Planilha3!D:F,3,0) -> 1279.3007 | C21: =B21/A21 -> 16152.787 | D21: Premium | E21: Heineken | F21: 903478 | G21: 1045807 | H21: CERVEJA HEINEKEN LN 330 ML | I21: 24 | J21: 91 | K21: =J21*26 -> 2366 | L21: 70980 | M21: =L21/J21 -> 780 | N21: =L21/K21 -> 30 | O21: 142.6 | P21: =O21/I21 -> 5.9416667 | Q21: =R21*I21 -> 1.2 | R21: 0.05 | S21: =T21*I21 -> 0.24 | T21: 0.01 | U21: =SUM(R21,T21) -> 0.06 | V21: 0.06 | W21: =VLOOKUP(F21,'[1]Proposta HNK para Tenda'!$F:$T,15,0) -> 6.99 | X21: =VLOOKUP(F21,'[1]Proposta HNK para Tenda'!$F:$U,16,0) -> 6.59 | Z21: =L21*(Q21+S21) -> 102211.2 | AA21: =L21*O21 -> 10121748 | AB21: =L21*24*0.33/100 -> 5621.616 | AD21: =SUM(AJ21,AM21,AP21) -> 0.068508 | AE21: =SUM(R21,T21) -> 0.06 | AF21: =AD21-AE21 -> 0.008508 | AH21: 20.76 | AI21: =AH21*AB21 -> 116704.75 | AJ21: =AI21/L21/I21 -> 0.068508 | AL21: =AK21*AB21 -> 0 | AM21: =AL21/L21/I21 -> 0 | AN21: 0 | AO21: =AN21*AB21 -> 0 | AP21: =AO21/L21/I21 -> 0 | AQ21: =SUM(AI21,AL21,AO21) -> 116704.75 | AR21: =SUM(AJ21,AM21,AP21) -> 0.068508 | AS21: =Z21 -> 102211.2 | AT21: =AQ21-AS21 -> 14493.548 | AU21: =O21/I21 -> 5.9416667 | AV21: =AU21-R21-T21 -> 5.8816667 | AW21: =(X21-AV21)/X21 -> 0.10748609 | AY21: =X21*100% -> 6.59 | AZ21: =Y21*50% -> 0 | BA21: =AY21+AZ21 -> 6.59 | BD21: Araraquara | BE21: HNK BR INDUSTRIA DE BEBIDAS LTDA. | BF21: 50.221.019/0105-22 | BG21: 181661963118 | BH21: Av Marginal 01 | BI21: 701 | BJ21: Chácara Catani | BK21: 14808080 | BL21: Araraquara | BM21: SP
A22: 0.072 | B22: =VLOOKUP(F22,Planilha3!D:F,3,0) -> 156.38563 | C22: =B22/A22 -> 2172.0226 | D22: Premium | E22: Heineken | F22: 903480 | G22: 99187 | H22: CERVEJA HEINEKEN ONE WAY 600ML | I22: 12 | J22: 96 | K22: =J22*26 -> 2496 | L22: 2496 | M22: =L22/J22 -> 26 | N22: =L22/K22 -> 1 | O22: 137.6 | P22: =O22/I22 -> 11.466667 | Q22: =R22*I22 -> 0 | R22: 0 | S22: =T22*I22 -> 0 | T22: 0 | U22: =SUM(R22,T22) -> 0 | V22: 0 | W22: =VLOOKUP(F22,'[1]Proposta HNK para Tenda'!$F:$T,15,0) -> 13.49 | X22: =VLOOKUP(F22,'[1]Proposta HNK para Tenda'!$F:$U,16,0) -> 13.49 | Z22: =L22*(Q22+S22) -> 0 | AA22: =L22*O22 -> 343449.6 | AB22: =L22*12*0.6/100 -> 179.712 | AD22: =SUM(AJ22,AM22,AP22) -> 0 | AE22: =SUM(R22,T22) -> 0 | AF22: =AD22-AE22 -> 0 | AH22: 0 | AI22: =AH22*AB22 -> 0 | AJ22: =AI22/L22/I22 -> 0 | AL22: =AK22*AB22 -> 0 | AM22: =AL22/L22/I22 -> 0 | AN22: 0 | AO22: =AN22*AB22 -> 0 | AP22: =AO22/L22/I22 -> 0 | AQ22: =SUM(AI22,AL22,AO22) -> 0 | AR22: =SUM(AJ22,AM22,AP22) -> 0 | AS22: =Z22 -> 0 | AT22: =AQ22-AS22 -> 0 | AU22: =O22/I22 -> 11.466667 | AV22: =AU22-R22-T22 -> 11.466667 | AW22: =(X22-AV22)/X22 -> 0.14998765 | AY22: =X22*100% -> 13.49 | AZ22: =Y22*50% -> 0 | BA22: =AY22+AZ22 -> 13.49 | BD22: Jacarei | BE22: HNK BR INDUSTRIA DE BEBIDAS LTDA. | BF22: 50.221.019/0104-41 | BG22: 392558326113 | BH22: Av Presidente Humberto de Alencar Castelo Branco | BI22: 2911 | BJ22: Conjunto Habitacional Marinho | BK22: 12321150 | BL22: Jacareí | BM22: SP
A23: 0.0792 | B23: 26 | C23: =B23/A23 -> 328.28283 | D23: Premium | E23: Sol | F23: 904701 | G23: 1022426 | H23: CERVEJA SOL PREMIUM LN 330ML | I23: 24 | J23: 91 | K23: 2366 | L23: 910 | M23: =L23/J23 -> 10 | N23: =L23/K23 -> 0.38461538 | O23: 122.2 | P23: =O23/I23 -> 5.0916667 | Q23: =R23*I23 -> 1.44 | R23: 0.06 | S23: =T23*I23 -> 1.2 | T23: 0.05 | U23: =SUM(R23,T23) -> 0.11 | V23: 0.11 | W23: 5.49 | X23: 5.09 | Z23: =L23*(Q23+S23) -> 2402.4 | AA23: =L23*O23 -> 111202 | AB23: =L23*24*0.33/100 -> 72.072 | AD23: =SUM(AJ23,AM23,AP23) -> 0.119493 | AE23: =SUM(R23,T23) -> 0.11 | AF23: =AD23-AE23 -> 0.009493 | AH23: 36.21 | AI23: =AH23*AB23 -> 2609.7271 | AJ23: =AI23/L23/I23 -> 0.119493 | AL23: =AK23*AB23 -> 0 | AM23: =AL23/L23/I23 -> 0 | AN23: 0 | AO23: =AN23*AB23 -> 0 | AP23: =AO23/L23/I23 -> 0 | AQ23: =SUM(AI23,AL23,AO23) -> 2609.7271 | AR23: =SUM(AJ23,AM23,AP23) -> 0.119493 | AS23: =Z23 -> 2402.4 | AT23: =AQ23-AS23 -> 207.32712 | AU23: =O23/I23 -> 5.0916667 | AV23: =AU23-R23-T23 -> 4.9816667 | AW23: =(X23-AV23)/X23 -> 0.021283563 | AY23: =X23*100% -> 5.09 | AZ23: =Y23*50% -> 0 | BA23: =AY23+AZ23 -> 5.09 | BD23: Jacarei | BE23: HNK BR INDUSTRIA DE BEBIDAS LTDA. | BF23: 50.221.019/0104-41 | BG23: 392558326113 | BH23: Av Presidente Humberto de Alencar Castelo Branco | BI23: 2911 | BJ23: Conjunto Habitacional Marinho | BK23: 12321150 | BL23: Jacareí | BM23: SP
A24: 0.0792 | B24: 26 | C24: =B24/A24 -> 328.28283 | D24: Premium | E24: Sol | F24: 905271 | G24: 1228753 | H24: CERVEJA SOL 0% PREMIUM LN 330ML | I24: 24 | J24: 91 | K24: 2366 | L24: =K24*1 -> 2366 | M24: =L24/J24 -> 26 | N24: =L24/K24 -> 1 | O24: 122.2 | P24: =O24/I24 -> 5.0916667 | Q24: =R24*I24 -> 1.44 | R24: 0.06 | S24: =T24*I24 -> 1.2 | T24: 0.05 | U24: =SUM(R24,T24) -> 0.11 | V24: 0.11 | W24: 5.99 | X24: 5.79 | Z24: =L24*(Q24+S24) -> 6246.24 | AA24: =L24*O24 -> 289125.2 | AB24: =L24*24*0.33/100 -> 187.3872 | AD24: =SUM(AJ24,AM24,AP24) -> 0.119493 | AE24: =SUM(R24,T24) -> 0.11 | AF24: =AD24-AE24 -> 0.009493 | AH24: 36.21 | AI24: =AH24*AB24 -> 6785.2905 | AJ24: =AI24/L24/I24 -> 0.119493 | AL24: =AK24*AB24 -> 0 | AM24: =AL24/L24/I24 -> 0 | AN24: 0 | AO24: =AN24*AB24 -> 0 | AP24: =AO24/L24/I24 -> 0 | AQ24: =SUM(AI24,AL24,AO24) -> 6785.2905 | AR24: =SUM(AJ24,AM24,AP24) -> 0.119493 | AS24: =Z24 -> 6246.24 | AT24: =AQ24-AS24 -> 539.05051 | AU24: =O24/I24 -> 5.0916667 | AV24: =AU24-R24-T24 -> 4.9816667 | AW24: =(X24-AV24)/X24 -> 0.13960852 | AY24: =X24*100% -> 5.79 | AZ24: =Y24*50% -> 0 | BA24: =AY24+AZ24 -> 5.79 | BD24: Jacarei | BE24: HNK BR INDUSTRIA DE BEBIDAS LTDA. | BF24: 50.221.019/0104-41 | BG24: 392558326113 | BH24: Av Presidente Humberto de Alencar Castelo Branco | BI24: 2911 | BJ24: Conjunto Habitacional Marinho | BK24: 12321150 | BL24: Jacareí | BM24: SP
A25: =5*2/100 -> 0.1 | B25: =VLOOKUP(F25,Planilha3!D:F,3,0) -> 282.36335 | C25: =B25/A25 -> 2823.6335 | D25: Premium | E25: Heineken | F25: 903483 | G25: 75013 | H25: CHOPP HEINEKEN 5LT | I25: 2 | J25: 90 | K25: =J25*26 -> 2340 | L25: 9360 | M25: =L25/J25 -> 104 | N25: =L25/K25 -> 4 | O25: 177.63 | P25: =O25/I25 -> 88.815 | Q25: =R25*I25 -> 0 | R25: 0 | S25: =T25*I25 -> 0 | T25: 0 | U25: =SUM(R25,T25) -> 0 | V25: 0 | W25: =VLOOKUP(F25,'[1]Proposta HNK para Tenda'!$F:$T,15,0) -> 113.99 | X25: =VLOOKUP(F25,'[1]Proposta HNK para Tenda'!$F:$U,16,0) -> 113.99 | Z25: =L25*(Q25+S25) -> 0 | AA25: =L25*O25 -> 1662616.8 | AB25: =L25*2*5/100 -> 936 | AD25: =SUM(AJ25,AM25,AP25) -> 0 | AE25: =SUM(R25,T25) -> 0 | AF25: =AD25-AE25 -> 0 | AH25: 0 | AI25: =AH25*AB25 -> 0 | AJ25: =AI25/L25/I25 -> 0 | AL25: =AK25*AB25 -> 0 | AM25: =AL25/L25/I25 -> 0 | AN25: 0 | AO25: =AN25*AB25 -> 0 | AP25: =AO25/L25/I25 -> 0 | AQ25: =SUM(AI25,AL25,AO25) -> 0 | AR25: =SUM(AJ25,AM25,AP25) -> 0 | AS25: =Z25 -> 0 | AT25: =AQ25-AS25 -> 0 | AU25: =O25/I25 -> 88.815 | AV25: =AU25-R25-T25 -> 88.815 | AW25: =(X25-AV25)/X25 -> 0.22085271 | AY25: =X25*100% -> 113.99 | AZ25: =Y25*50% -> 0 | BA25: =AY25+AZ25 -> 113.99 | BD25: Ponta Grossa | BE25: HNK BR INDUSTRIA DE BEBIDAS LTDA. | BF25: 50.221.019/0097-88 | BG25: 911.300.50.81 | BH25: Av Tocantins | BI25: 199 | BJ25: Cara-Cara | BK25: 84043610 | BL25: Ponta Grossa | BM25: PR
A26: =0.355*6/100 -> 0.0213 | C26: =B26/A26 -> 0 | D26: Premium | E26: Praya | F26: 631974 | G26: 1228751 | H26: CERVEJA PRAYA LAGER 355ML | I26: 6 | J26: 350 | K26: =J26*26 -> 9100 | L26: =K26*1 -> 9100 | M26: =L26/J26 -> 26 | N26: =L26/K26 -> 1 | O26: 33.07 | P26: =O26/I26 -> 5.5116667 | Q26: =R26*I26 -> 0 | R26: 0 | S26: =T26*I26 -> 0 | T26: 0 | U26: =SUM(R26,T26) -> 0 | V26: 0 | W26: 6.99 | X26: 6.49 | Z26: =L26*(Q26+S26) -> 0 | AA26: =L26*O26 -> 300937 | AB26: =L26*I26*0.35/100 -> 191.1 | AD26: =SUM(AJ26,AM26,AP26) -> 0 | AE26: =SUM(R26,T26) -> 0 | AF26: =AD26-AE26 -> 0 | AH26: 0 | AI26: =AH26*AB26 -> 0 | AJ26: =AI26/L26/I26 -> 0 | AL26: =AK26*AB26 -> 0 | AM26: =AL26/L26/I26 -> 0 | AN26: 0 | AO26: =AN26*AB26 -> 0 | AP26: =AO26/L26/I26 -> 0 | AQ26: =SUM(AI26,AL26,AO26) -> 0 | AR26: =SUM(AJ26,AM26,AP26) -> 0 | AS26: =Z26 -> 0 | AT26: =AQ26-AS26 -> 0 | AU26: =O26/I26 -> 5.5116667 | AV26: =AU26-R26-T26 -> 5.5116667 | AW26: =(X26-AV26)/X26 -> 0.15074474 | AY26: =X26*100% -> 6.49 | AZ26: =Y26*50% -> 0 | BA26: =AY26+AZ26 -> 6.49 | BD26: Itu | BE26: HNK BR INDUSTRIA DE BEBIDAS LTDA. | BF26: 50.221.019/0001-36 | BG26: 387000650117 | BH26: Av Primo Schincariol | BI26: 2222 | BJ26: Chácara Flórida | BK26: 13312250 | BL26: Itu | BM26: SP
A27: =0.355*24/100 -> 0.0852 | C27: =B27/A27 -> 0 | D27: Premium | E27: Praya | F27: 634958 | G27: 1149563 | H27: CERVEJA PRAYA RECEITA CLÁSSICA LN 355ML | I27: 24 | J27: 84 | K27: =J27*26 -> 2184 | L27: =K27*2 -> 4368 | M27: =L27/J27 -> 52 | N27: =L27/K27 -> 2 | O27: 170.82 | P27: =O27/I27 -> 7.1175 | Q27: =R27*I27 -> 0 | R27: 0 | S27: =T27*I27 -> 0 | T27: 0 | U27: =SUM(R27,T27) -> 0 | V27: 0 | W27: 9.49 | X27: 8.49 | Z27: =L27*(Q27+S27) -> 0 | AA27: =L27*O27 -> 746141.76 | AB27: =L27*I27*0.35/100 -> 366.912 | AD27: =SUM(AJ27,AM27,AP27) -> 0 | AE27: =SUM(R27,T27) -> 0 | AF27: =AD27-AE27 -> 0 | AH27: 0 | AI27: =AH27*AB27 -> 0 | AJ27: =AI27/L27/I27 -> 0 | AL27: =AK27*AB27 -> 0 | AM27: =AL27/L27/I27 -> 0 | AN27: 0 | AO27: =AN27*AB27 -> 0 | AP27: =AO27/L27/I27 -> 0 | AQ27: =SUM(AI27,AL27,AO27) -> 0 | AR27: =SUM(AJ27,AM27,AP27) -> 0 | AS27: =Z27 -> 0 | AT27: =AQ27-AS27 -> 0 | AU27: =O27/I27 -> 7.1175 | AV27: =AU27-R27-T27 -> 7.1175 | AW27: =(X27-AV27)/X27 -> 0.16166078 | AY27: =X27*100% -> 8.49 | AZ27: =Y27*50% -> 0 | BA27: =AY27+AZ27 -> 8.49 | BD27: Itu | BE27: HNK BR INDUSTRIA DE BEBIDAS LTDA. | BF27: 50.221.019/0001-36 | BG27: 387000650117 | BH27: Av Primo Schincariol | BI27: 2222 | BJ27: Chácara Flórida | BK27: 13312250 | BL27: Itu | BM27: SP
A28: =0.6*12/100 -> 0.072 | C28: =B28/A28 -> 0 | D28: Premium | E28: Praya | F28: 634957 | G28: 1149565 | H28: CERVEJA PRAYA RECEITA CLÁSSICA 600ML | I28: 12 | J28: 60 | K28: =J28*26 -> 1560 | L28: =J28*15 -> 900 | M28: =L28/J28 -> 15 | N28: =L28/K28 -> 0.57692308 | O28: 136.71 | P28: =O28/I28 -> 11.3925 | Q28: =R28*I28 -> 0 | R28: 0 | S28: =T28*I28 -> 0 | T28: 0 | U28: =SUM(R28,T28) -> 0 | V28: 0 | W28: 15.19 | X28: 13.29 | Z28: =L28*(Q28+S28) -> 0 | AA28: =L28*O28 -> 123039 | AB28: =L28*I28*0.6/100 -> 64.8 | AD28: =SUM(AJ28,AM28,AP28) -> 0 | AE28: =SUM(R28,T28) -> 0 | AF28: =AD28-AE28 -> 0 | AH28: 0 | AI28: =AH28*AB28 -> 0 | AJ28: =AI28/L28/I28 -> 0 | AL28: =AK28*AB28 -> 0 | AM28: =AL28/L28/I28 -> 0 | AN28: 0 | AO28: =AN28*AB28 -> 0 | AP28: =AO28/L28/I28 -> 0 | AQ28: =SUM(AI28,AL28,AO28) -> 0 | AR28: =SUM(AJ28,AM28,AP28) -> 0 | AS28: =Z28 -> 0 | AT28: =AQ28-AS28 -> 0 | AU28: =O28/I28 -> 11.3925 | AV28: =AU28-R28-T28 -> 11.3925 | AW28: =(X28-AV28)/X28 -> 0.14277652 | AY28: =X28*100% -> 13.29 | AZ28: =Y28*50% -> 0 | BA28: =AY28+AZ28 -> 13.29 | BD28: Itu | BE28: HNK BR INDUSTRIA DE BEBIDAS LTDA. | BF28: 50.221.019/0001-36 | BG28: 387000650117 | BH28: Av Primo Schincariol | BI28: 2222 | BJ28: Chácara Flórida | BK28: 13312250 | BL28: Itu | BM28: SP
A29: 0.072 | B29: =VLOOKUP(F29,Planilha3!D:F,3,0) -> 7.4611665 | C29: =B29/A29 -> 103.62731 | D29: Craft | E29: Baden | F29: 902832 | G29: 1046669 | H29: CERVEJA BADEN IPA 600ML | I29: 12 | J29: 60 | K29: =J29*24 -> 1440 | L29: 120 | M29: =L29/J29 -> 2 | N29: =L29/K29 -> 0.083333333 | O29: 134.52 | P29: =O29/I29 -> 11.21 | Q29: =R29*I29 -> 0 | R29: 0 | S29: =T29*I29 -> 0 | T29: 0 | U29: =SUM(R29,T29) -> 0 | V29: 0 | W29: =VLOOKUP(F29,'[1]Proposta HNK para Tenda'!$F:$T,15,0) -> 14.19 | X29: =VLOOKUP(F29,'[1]Proposta HNK para Tenda'!$F:$U,16,0) -> 14.19 | Z29: =L29*(Q29+S29) -> 0 | AA29: =L29*O29 -> 16142.4 | AB29: =L29*12*0.6/100 -> 8.64 | AD29: =SUM(AJ29,AM29,AP29) -> 0 | AE29: =SUM(R29,T29) -> 0 | AF29: =AD29-AE29 -> 0 | AH29: 0 | AI29: =AH29*AB29 -> 0 | AJ29: =AI29/L29/I29 -> 0 | AL29: =AK29*AB29 -> 0 | AM29: =AL29/L29/I29 -> 0 | AN29: 0 | AO29: =AN29*AB29 -> 0 | AP29: =AO29/L29/I29 -> 0 | AQ29: =SUM(AI29,AL29,AO29) -> 0 | AR29: =SUM(AJ29,AM29,AP29) -> 0 | AS29: =Z29 -> 0 | AT29: =AQ29-AS29 -> 0 | AU29: =O29/I29 -> 11.21 | AV29: =AU29-R29-T29 -> 11.21 | AW29: =(X29-AV29)/X29 -> 0.21000705 | AY29: =X29*100% -> 14.19 | AZ29: =Y29*50% -> 0 | BA29: =AY29+AZ29 -> 14.19 | BD29: Itu | BE29: HNK BR INDUSTRIA DE BEBIDAS LTDA. | BF29: 50.221.019/0001-36 | BG29: 387000650117 | BH29: Av Primo Schincariol | BI29: 2222 | BJ29: Chácara Flórida | BK29: 13312250 | BL29: Itu | BM29: SP
A30: 0.072 | B30: =VLOOKUP(F30,Planilha3!D:F,3,0) -> 5.948199 | C30: =B30/A30 -> 82.613875 | D30: Craft | E30: Baden | F30: 900118 | G30: 1017028 | H30: CERVEJA BADEN GOLDEN 600ML | I30: 12 | J30: 60 | K30: =J30*24 -> 1440 | L30: 120 | M30: =L30/J30 -> 2 | N30: =L30/K30 -> 0.083333333 | O30: 134.52 | P30: =O30/I30 -> 11.21 | Q30: =R30*I30 -> 0 | R30: 0 | S30: =T30*I30 -> 0 | T30: 0 | U30: =SUM(R30,T30) -> 0 | V30: 0 | W30: =VLOOKUP(F30,'[1]Proposta HNK para Tenda'!$F:$T,15,0) -> 14.19 | X30: =VLOOKUP(F30,'[1]Proposta HNK para Tenda'!$F:$U,16,0) -> 14.19 | Z30: =L30*(Q30+S30) -> 0 | AA30: =L30*O30 -> 16142.4 | AB30: =L30*12*0.6/100 -> 8.64 | AD30: =SUM(AJ30,AM30,AP30) -> 0 | AE30: =SUM(R30,T30) -> 0 | AF30: =AD30-AE30 -> 0 | AH30: 0 | AI30: =AH30*AB30 -> 0 | AJ30: =AI30/L30/I30 -> 0 | AL30: =AK30*AB30 -> 0 | AM30: =AL30/L30/I30 -> 0 | AN30: 0 | AO30: =AN30*AB30 -> 0 | AP30: =AO30/L30/I30 -> 0 | AQ30: =SUM(AI30,AL30,AO30) -> 0 | AR30: =SUM(AJ30,AM30,AP30) -> 0 | AS30: =Z30 -> 0 | AT30: =AQ30-AS30 -> 0 | AU30: =O30/I30 -> 11.21 | AV30: =AU30-R30-T30 -> 11.21 | AW30: =(X30-AV30)/X30 -> 0.21000705 | AY30: =X30*100% -> 14.19 | AZ30: =Y30*50% -> 0 | BA30: =AY30+AZ30 -> 14.19 | BD30: Itu | BE30: HNK BR INDUSTRIA DE BEBIDAS LTDA. | BF30: 50.221.019/0001-36 | BG30: 387000650117 | BH30: Av Primo Schincariol | BI30: 2222 | BJ30: Chácara Flórida | BK30: 13312250 | BL30: Itu | BM30: SP
A31: 0.042 | B31: =VLOOKUP(F31,Planilha3!D:F,3,0) -> 27.698971 | C31: =B31/A31 -> 659.49932 | D31: Craft | E31: Baden | F31: 904451 | G31: 1147973 | H31: CERVEJA BADEN IPA LA 350ML | I31: 12 | J31: 280 | K31: =J31*24 -> 6720 | L31: 6720 | M31: =L31/J31 -> 24 | N31: =M31/26 -> 0.92307692 | O31: 57.73 | P31: =O31/I31 -> 4.8108333 | Q31: =R31*I31 -> 3 | R31: 0.25 | S31: =T31*I31 -> 0.72 | T31: 0.06 | U31: =SUM(R31,T31) -> 0.31 | V31: 0.31 | W31: =VLOOKUP(F31,'[1]Proposta HNK para Tenda'!$F:$T,15,0) -> 6.09 | X31: =VLOOKUP(F31,'[1]Proposta HNK para Tenda'!$F:$U,16,0) -> 5.39 | Z31: =L31*(Q31+S31) -> 24998.4 | AA31: =L31*O31 -> 387945.6 | AB31: =L31*12*0.35/100 -> 282.24 | AD31: =SUM(AJ31,AM31,AP31) -> 0.3143 | AE31: =SUM(R31,T31) -> 0.31 | AF31: =AD31-AE31 -> 0.0043 | AH31: 89.8 | AI31: =AH31*AB31 -> 25345.152 | AJ31: =AI31/L31/I31 -> 0.3143 | AL31: =AK31*AB31 -> 0 | AM31: =AL31/L31/I31 -> 0 | AN31: 0 | AO31: =AN31*AB31 -> 0 | AP31: =AO31/L31/I31 -> 0 | AQ31: =SUM(AI31,AL31,AO31) -> 25345.152 | AR31: =SUM(AJ31,AM31,AP31) -> 0.3143 | AS31: =Z31 -> 24998.4 | AT31: =AQ31-AS31 -> 346.752 | AU31: =O31/I31 -> 4.8108333 | AV31: =AU31-R31-T31 -> 4.5008333 | AW31: =(X31-AV31)/X31 -> 0.16496599 | AY31: =X31*100% -> 5.39 | AZ31: =Y31*50% -> 0 | BA31: =AY31+AZ31 -> 5.39 | BD31: Itu | BE31: HNK BR INDUSTRIA DE BEBIDAS LTDA. | BF31: 50.221.019/0001-36 | BG31: 387000650117 | BH31: Av Primo Schincariol | BI31: 2222 | BJ31: Chácara Flórida | BK31: 13312250 | BL31: Itu | BM31: SP
A32: 0.072 | B32: =VLOOKUP(F32,Planilha3!D:F,3,0) -> 2.958687 | C32: =B32/A32 -> 41.092875 | D32: Craft | E32: Baden | F32: 904742 | G32: 1169732 | H32: CERVEJA BADEN PEACH 600ML | I32: 12 | J32: 60 | K32: =J32*24 -> 1440 | L32: 120 | M32: =L32/J32 -> 2 | N32: =L32/K32 -> 0.083333333 | O32: 134.52 | P32: =O32/I32 -> 11.21 | Q32: =R32*I32 -> 0 | R32: 0 | S32: =T32*I32 -> 0 | T32: 0 | U32: =SUM(R32,T32) -> 0 | V32: 0 | W32: =VLOOKUP(F32,'[1]Proposta HNK para Tenda'!$F:$T,15,0) -> 14.19 | X32: =VLOOKUP(F32,'[1]Proposta HNK para Tenda'!$F:$U,16,0) -> 14.19 | Z32: =L32*(Q32+S32) -> 0 | AA32: =L32*O32 -> 16142.4 | AB32: =L32*12*0.6/100 -> 8.64 | AD32: =SUM(AJ32,AM32,AP32) -> 0 | AE32: =SUM(R32,T32) -> 0 | AF32: =AD32-AE32 -> 0 | AH32: 0 | AI32: =AH32*AB32 -> 0 | AJ32: =AI32/L32/I32 -> 0 | AL32: =AK32*AB32 -> 0 | AM32: =AL32/L32/I32 -> 0 | AN32: 0 | AO32: =AN32*AB32 -> 0 | AP32: =AO32/L32/I32 -> 0 | AQ32: =SUM(AI32,AL32,AO32) -> 0 | AR32: =SUM(AJ32,AM32,AP32) -> 0 | AS32: =Z32 -> 0 | AT32: =AQ32-AS32 -> 0 | AU32: =O32/I32 -> 11.21 | AV32: =AU32-R32-T32 -> 11.21 | AW32: =(X32-AV32)/X32 -> 0.21000705 | AY32: =X32*100% -> 14.19 | AZ32: =Y32*50% -> 0 | BA32: =AY32+AZ32 -> 14.19 | BD32: Itu | BE32: HNK BR INDUSTRIA DE BEBIDAS LTDA. | BF32: 50.221.019/0001-36 | BG32: 387000650117 | BH32: Av Primo Schincariol | BI32: 2222 | BJ32: Chácara Flórida | BK32: 13312250 | BL32: Itu | BM32: SP
A33: 0.042 | B33: =VLOOKUP(F33,Planilha3!D:F,3,0) -> 12.871838 | C33: =B33/A33 -> 306.47234 | D33: Craft | E33: Baden | F33: 904743 | G33: 1170232 | H33: CERVEJA BADEN PEACH LA 350ML | I33: 12 | J33: 280 | K33: =J33*24 -> 6720 | L33: 3920 | M33: =L33/J33 -> 14 | N33: =L33/K33 -> 0.58333333 | O33: 57.73 | P33: =O33/I33 -> 4.8108333 | Q33: =R33*I33 -> 3 | R33: 0.25 | S33: =T33*I33 -> 0.72 | T33: 0.06 | U33: =SUM(R33,T33) -> 0.31 | V33: 0.31 | W33: =VLOOKUP(F33,'[1]Proposta HNK para Tenda'!$F:$T,15,0) -> 6.09 | X33: =VLOOKUP(F33,'[1]Proposta HNK para Tenda'!$F:$U,16,0) -> 5.39 | Z33: =L33*(Q33+S33) -> 14582.4 | AA33: =L33*O33 -> 226301.6 | AB33: =L33*12*0.35/100 -> 164.64 | AD33: =SUM(AJ33,AM33,AP33) -> 0.3143 | AE33: =SUM(R33,T33) -> 0.31 | AF33: =AD33-AE33 -> 0.0043 | AH33: 89.8 | AI33: =AH33*AB33 -> 14784.672 | AJ33: =AI33/L33/I33 -> 0.3143 | AL33: =AK33*AB33 -> 0 | AM33: =AL33/L33/I33 -> 0 | AN33: 0 | AO33: =AN33*AB33 -> 0 | AP33: =AO33/L33/I33 -> 0 | AQ33: =SUM(AI33,AL33,AO33) -> 14784.672 | AR33: =SUM(AJ33,AM33,AP33) -> 0.3143 | AS33: =Z33 -> 14582.4 | AT33: =AQ33-AS33 -> 202.272 | AU33: =O33/I33 -> 4.8108333 | AV33: =AU33-R33-T33 -> 4.5008333 | AW33: =(X33-AV33)/X33 -> 0.16496599 | AY33: =X33*100% -> 5.39 | AZ33: =Y33*50% -> 0 | BA33: =AY33+AZ33 -> 5.39 | BD33: Itu | BE33: HNK BR INDUSTRIA DE BEBIDAS LTDA. | BF33: 50.221.019/0001-36 | BG33: 387000650117 | BH33: Av Primo Schincariol | BI33: 2222 | BJ33: Chácara Flórida | BK33: 13312250 | BL33: Itu | BM33: SP
A34: 0.072 | B34: =VLOOKUP(F34,Planilha3!D:F,3,0) -> 5.1478175 | C34: =B34/A34 -> 71.497465 | D34: Craft | E34: Baden | F34: 900109 | G34: 1017027 | H34: CERVEJA BADEN CRISTAL 600ML | I34: 12 | J34: 60 | K34: =J34*24 -> 1440 | L34: 240 | M34: =L34/J34 -> 4 | N34: =L34/K34 -> 0.16666667 | O34: 134.52 | P34: =O34/I34 -> 11.21 | Q34: =R34*I34 -> 0 | R34: 0 | S34: =T34*I34 -> 0 | T34: 0 | U34: =SUM(R34,T34) -> 0 | V34: 0 | W34: =VLOOKUP(F34,'[1]Proposta HNK para Tenda'!$F:$T,15,0) -> 14.19 | X34: =VLOOKUP(F34,'[1]Proposta HNK para Tenda'!$F:$U,16,0) -> 14.19 | Z34: =L34*(Q34+S34) -> 0 | AA34: =L34*O34 -> 32284.8 | AB34: =L34*12*0.6/100 -> 17.28 | AD34: =SUM(AJ34,AM34,AP34) -> 0 | AE34: =SUM(R34,T34) -> 0 | AF34: =AD34-AE34 -> 0 | AH34: 0 | AI34: =AH34*AB34 -> 0 | AJ34: =AI34/L34/I34 -> 0 | AL34: =AK34*AB34 -> 0 | AM34: =AL34/L34/I34 -> 0 | AN34: 0 | AO34: =AN34*AB34 -> 0 | AP34: =AO34/L34/I34 -> 0 | AQ34: =SUM(AI34,AL34,AO34) -> 0 | AR34: =SUM(AJ34,AM34,AP34) -> 0 | AS34: =Z34 -> 0 | AT34: =AQ34-AS34 -> 0 | AU34: =O34/I34 -> 11.21 | AV34: =AU34-R34-T34 -> 11.21 | AW34: =(X34-AV34)/X34 -> 0.21000705 | AY34: =X34*100% -> 14.19 | AZ34: =Y34*50% -> 0 | BA34: =AY34+AZ34 -> 14.19 | BD34: Itu | BE34: HNK BR INDUSTRIA DE BEBIDAS LTDA. | BF34: 50.221.019/0001-36 | BG34: 387000650117 | BH34: Av Primo Schincariol | BI34: 2222 | BJ34: Chácara Flórida | BK34: 13312250 | BL34: Itu | BM34: SP
A35: 0.042 | B35: =VLOOKUP(F35,Planilha3!D:F,3,0) -> 8.3101108 | C35: =B35/A35 -> 197.85978 | D35: Craft | E35: Baden | F35: 904441 | G35: 1147975 | H35: CERVEJA BADEN CRISTAL LA 350ML | I35: 12 | J35: 280 | K35: =J35*24 -> 6720 | L35: 6720 | M35: =L35/J35 -> 24 | N35: =L35/K35 -> 1 | O35: 57.73 | P35: =O35/I35 -> 4.8108333 | Q35: =R35*I35 -> 3 | R35: 0.25 | S35: =T35*I35 -> 0.72 | T35: 0.06 | U35: =SUM(R35,T35) -> 0.31 | V35: 0.31 | W35: =VLOOKUP(F35,'[1]Proposta HNK para Tenda'!$F:$T,15,0) -> 6.09 | X35: =VLOOKUP(F35,'[1]Proposta HNK para Tenda'!$F:$U,16,0) -> 5.39 | Z35: =L35*(Q35+S35) -> 24998.4 | AA35: =L35*O35 -> 387945.6 | AB35: =L35*12*0.35/100 -> 282.24 | AD35: =SUM(AJ35,AM35,AP35) -> 0.3143 | AE35: =SUM(R35,T35) -> 0.31 | AF35: =AD35-AE35 -> 0.0043 | AH35: 89.8 | AI35: =AH35*AB35 -> 25345.152 | AJ35: =AI35/L35/I35 -> 0.3143 | AL35: =AK35*AB35 -> 0 | AM35: =AL35/L35/I35 -> 0 | AN35: 0 | AO35: =AN35*AB35 -> 0 | AP35: =AO35/L35/I35 -> 0 | AQ35: =SUM(AI35,AL35,AO35) -> 25345.152 | AR35: =SUM(AJ35,AM35,AP35) -> 0.3143 | AS35: =Z35 -> 24998.4 | AT35: =AQ35-AS35 -> 346.752 | AU35: =O35/I35 -> 4.8108333 | AV35: =AU35-R35-T35 -> 4.5008333 | AW35: =(X35-AV35)/X35 -> 0.16496599 | AY35: =X35*100% -> 5.39 | AZ35: =Y35*50% -> 0 | BA35: =AY35+AZ35 -> 5.39 | BD35: Itu | BE35: HNK BR INDUSTRIA DE BEBIDAS LTDA. | BF35: 50.221.019/0001-36 | BG35: 387000650117 | BH35: Av Primo Schincariol | BI35: 2222 | BJ35: Chácara Flórida | BK35: 13312250 | BL35: Itu | BM35: SP
A36: 0.072 | B36: =VLOOKUP(F36,Planilha3!D:F,3,0) -> 6.1719833 | C36: =B36/A36 -> 85.72199 | D36: Craft | E36: Baden | F36: 901162 | G36: 1046689 | H36: CERVEJA BADEN WITIBIER 600ML | I36: 12 | J36: 60 | K36: =J36*24 -> 1440 | L36: 120 | M36: =L36/J36 -> 2 | N36: =L36/K36 -> 0.083333333 | O36: 134.52 | P36: =O36/I36 -> 11.21 | Q36: =R36*I36 -> 0 | R36: 0 | S36: =T36*I36 -> 0 | T36: 0 | U36: =SUM(R36,T36) -> 0 | V36: 0 | W36: =VLOOKUP(F36,'[1]Proposta HNK para Tenda'!$F:$T,15,0) -> 14.19 | X36: =VLOOKUP(F36,'[1]Proposta HNK para Tenda'!$F:$U,16,0) -> 14.19 | Z36: =L36*(Q36+S36) -> 0 | AA36: =L36*O36 -> 16142.4 | AB36: =L36*12*0.6/100 -> 8.64 | AD36: =SUM(AJ36,AM36,AP36) -> 0 | AE36: =SUM(R36,T36) -> 0 | AF36: =AD36-AE36 -> 0 | AH36: 0 | AI36: =AH36*AB36 -> 0 | AJ36: =AI36/L36/I36 -> 0 | AL36: =AK36*AB36 -> 0 | AM36: =AL36/L36/I36 -> 0 | AN36: 0 | AO36: =AN36*AB36 -> 0 | AP36: =AO36/L36/I36 -> 0 | AQ36: =SUM(AI36,AL36,AO36) -> 0 | AR36: =SUM(AJ36,AM36,AP36) -> 0 | AS36: =Z36 -> 0 | AT36: =AQ36-AS36 -> 0 | AU36: =O36/I36 -> 11.21 | AV36: =AU36-R36-T36 -> 11.21 | AW36: =(X36-AV36)/X36 -> 0.21000705 | AY36: =X36*100% -> 14.19 | AZ36: =Y36*50% -> 0 | BA36: =AY36+AZ36 -> 14.19 | BD36: Itu | BE36: HNK BR INDUSTRIA DE BEBIDAS LTDA. | BF36: 50.221.019/0001-36 | BG36: 387000650117 | BH36: Av Primo Schincariol | BI36: 2222 | BJ36: Chácara Flórida | BK36: 13312250 | BL36: Itu | BM36: SP
A37: 0.042 | B37: =VLOOKUP(F37,Planilha3!D:F,3,0) -> 21.928826 | C37: =B37/A37 -> 522.11489 | D37: Craft | E37: Baden | F37: 904193 | G37: 1150647 | H37: CERVEJA BADEN WITBIER LA 350ML | I37: 12 | J37: 280 | K37: =J37*24 -> 6720 | L37: 6720 | M37: =L37/J37 -> 24 | N37: =L37/K37 -> 1 | O37: 57.73 | P37: =O37/I37 -> 4.8108333 | Q37: =R37*I37 -> 3 | R37: 0.25 | S37: =T37*I37 -> 0.72 | T37: 0.06 | U37: =SUM(R37,T37) -> 0.31 | V37: 0.31 | W37: =VLOOKUP(F37,'[1]Proposta HNK para Tenda'!$F:$T,15,0) -> 6.09 | X37: =VLOOKUP(F37,'[1]Proposta HNK para Tenda'!$F:$U,16,0) -> 5.39 | Z37: =L37*(Q37+S37) -> 24998.4 | AA37: =L37*O37 -> 387945.6 | AB37: =L37*12*0.35/100 -> 282.24 | AD37: =SUM(AJ37,AM37,AP37) -> 0.3143 | AE37: =SUM(R37,T37) -> 0.31 | AF37: =AD37-AE37 -> 0.0043 | AH37: 89.8 | AI37: =AH37*AB37 -> 25345.152 | AJ37: =AI37/L37/I37 -> 0.3143 | AL37: =AK37*AB37 -> 0 | AM37: =AL37/L37/I37 -> 0 | AN37: 0 | AO37: =AN37*AB37 -> 0 | AP37: =AO37/L37/I37 -> 0 | AQ37: =SUM(AI37,AL37,AO37) -> 25345.152 | AR37: =SUM(AJ37,AM37,AP37) -> 0.3143 | AS37: =Z37 -> 24998.4 | AT37: =AQ37-AS37 -> 346.752 | AU37: =O37/I37 -> 4.8108333 | AV37: =AU37-R37-T37 -> 4.5008333 | AW37: =(X37-AV37)/X37 -> 0.16496599 | AY37: =X37*100% -> 5.39 | AZ37: =Y37*50% -> 0 | BA37: =AY37+AZ37 -> 5.39 | BD37: Itu | BE37: HNK BR INDUSTRIA DE BEBIDAS LTDA. | BF37: 50.221.019/0001-36 | BG37: 387000650117 | BH37: Av Primo Schincariol | BI37: 2222 | BJ37: Chácara Flórida | BK37: 13312250 | BL37: Itu | BM37: SP
A38: 0.042 | B38: =VLOOKUP(F38,Planilha3!D:F,3,0) -> 12.387493 | C38: =B38/A38 -> 294.94032 | D38: Craft | E38: Blue Moon | F38: 904612 | G38: 1155188 | H38: CERVEJA BLUE MOON LA 350ML | I38: 12 | J38: 280 | K38: =J38*24 -> 6720 | L38: 560 | M38: =L38/J38 -> 2 | N38: =L38/K38 -> 0.083333333 | O38: 85.23 | P38: =O38/I38 -> 7.1025 | Q38: =R38*I38 -> 10.8 | R38: 0.9 | S38: =T38*I38 -> 0.24 | T38: 0.02 | U38: =SUM(R38,T38) -> 0.92 | V38: 0.92 | W38: =VLOOKUP(F38,'[1]Proposta HNK para Tenda'!$F:$T,15,0) -> 8.99 | X38: =VLOOKUP(F38,'[1]Proposta HNK para Tenda'!$F:$U,16,0) -> 6.99 | Z38: =L38*(Q38+S38) -> 6182.4 | AA38: =L38*O38 -> 47728.8 | AB38: =L38*12*0.35/100 -> 23.52 | AD38: =SUM(AJ38,AM38,AP38) -> 0.93051 | AE38: =SUM(R38,T38) -> 0.92 | AF38: =AD38-AE38 -> 0.01051 | AH38: 265.86 | AI38: =AH38*AB38 -> 6253.0272 | AJ38: =AI38/L38/I38 -> 0.93051 | AL38: =AK38*AB38 -> 0 | AM38: =AL38/L38/I38 -> 0 | AN38: 0 | AO38: =AN38*AB38 -> 0 | AP38: =AO38/L38/I38 -> 0 | AQ38: =SUM(AI38,AL38,AO38) -> 6253.0272 | AR38: =SUM(AJ38,AM38,AP38) -> 0.93051 | AS38: =Z38 -> 6182.4 | AT38: =AQ38-AS38 -> 70.6272 | AU38: =O38/I38 -> 7.1025 | AV38: =AU38-R38-T38 -> 6.1825 | AW38: =(X38-AV38)/X38 -> 0.11552217 | AY38: =X38*100% -> 6.99 | AZ38: =Y38*50% -> 0 | BA38: =AY38+AZ38 -> 6.99 | BD38: Itu | BE38: HNK BR INDUSTRIA DE BEBIDAS LTDA. | BF38: 50.221.019/0001-36 | BG38: 387000650117 | BH38: Av Primo Schincariol | BI38: 2222 | BJ38: Chácara Flórida | BK38: 13312250 | BL38: Itu | BM38: SP
A39: 0.0852 | B39: =VLOOKUP(F39,Planilha3!D:F,3,0) -> 5.009831 | C39: =B39/A39 -> 58.800833 | D39: Craft | E39: Blue Moon | F39: 904602 | G39: 1160869 | H39: CERVEJA BLUE MOON LN 355ML | I39: 24 | J39: 56 | K39: =J39*24 -> 1344 | L39: 168 | M39: =L39/J39 -> 3 | N39: =L39/K39 -> 0.125 | O39: 208.37 | P39: =O39/I39 -> 8.6820833 | Q39: =R39*I39 -> 0 | R39: 0 | S39: =T39*I39 -> 0 | T39: 0 | U39: =SUM(R39,T39) -> 0 | V39: 0 | W39: =VLOOKUP(F39,'[1]Proposta HNK para Tenda'!$F:$T,15,0) -> 10.99 | X39: =VLOOKUP(F39,'[1]Proposta HNK para Tenda'!$F:$U,16,0) -> 10.99 | Z39: =L39*(Q39+S39) -> 0 | AA39: =L39*O39 -> 35006.16 | AB39: =L39*24*0.355/100 -> 14.3136 | AD39: =SUM(AJ39,AM39,AP39) -> 0 | AE39: =SUM(R39,T39) -> 0 | AF39: =AD39-AE39 -> 0 | AH39: 0 | AI39: =AH39*AB39 -> 0 | AJ39: =AI39/L39/I39 -> 0 | AL39: =AK39*AB39 -> 0 | AM39: =AL39/L39/I39 -> 0 | AN39: 0 | AO39: =AN39*AB39 -> 0 | AP39: =AO39/L39/I39 -> 0 | AQ39: =SUM(AI39,AL39,AO39) -> 0 | AR39: =SUM(AJ39,AM39,AP39) -> 0 | AS39: =Z39 -> 0 | AT39: =AQ39-AS39 -> 0 | AU39: =O39/I39 -> 8.6820833 | AV39: =AU39-R39-T39 -> 8.6820833 | AW39: =(X39-AV39)/X39 -> 0.21000152 | AY39: =X39*100% -> 10.99 | AZ39: =Y39*50% -> 0 | BA39: =AY39+AZ39 -> 10.99 | BD39: Itu | BE39: HNK BR INDUSTRIA DE BEBIDAS LTDA. | BF39: 50.221.019/0001-36 | BG39: 387000650117 | BH39: Av Primo Schincariol | BI39: 2222 | BJ39: Chácara Flórida | BK39: 13312250 | BL39: Itu | BM39: SP
A40: 0.042 | B40: =VLOOKUP(F40,Planilha3!D:F,3,0) -> 17.452561 | C40: =B40/A40 -> 415.53717 | D40: Craft | E40: Eisenbahn | F40: 903681 | G40: 1110090 | H40: CERVEJA EISENBAHN IPA LATA 350 ML | I40: 12 | J40: 280 | K40: =J40*24 -> 6720 | L40: 3920 | M40: =L40/J40 -> 14 | N40: =L40/K40 -> 0.58333333 | O40: 53.94 | P40: =O40/I40 -> 4.495 | Q40: =R40*I40 -> 3.24 | R40: 0.27 | S40: =T40*I40 -> 0 | T40: 0 | U40: =SUM(R40,T40) -> 0.27 | V40: 0.27 | W40: 5.69 | X40: 5.09 | Z40: =L40*(Q40+S40) -> 12700.8 | AA40: =L40*O40 -> 211444.8 | AB40: =L40*12*0.35/100 -> 164.64 | AD40: =SUM(AJ40,AM40,AP40) -> 0.26691 | AE40: =SUM(R40,T40) -> 0.27 | AF40: =AD40-AE40 -> -0.00309 | AH40: 76.26 | AI40: =AH40*AB40 -> 12555.446 | AJ40: =AI40/L40/I40 -> 0.26691 | AL40: =AK40*AB40 -> 0 | AM40: =AL40/L40/I40 -> 0 | AN40: 0 | AO40: =AN40*AB40 -> 0 | AP40: =AO40/L40/I40 -> 0 | AQ40: =SUM(AI40,AL40,AO40) -> 12555.446 | AR40: =SUM(AJ40,AM40,AP40) -> 0.26691 | AS40: =Z40 -> 12700.8 | AT40: =AQ40-AS40 -> -145.3536 | AU40: =O40/I40 -> 4.495 | AV40: =AU40-R40-T40 -> 4.225 | AW40: =(X40-AV40)/X40 -> 0.16994106 | AY40: =X40*100% -> 5.09 | AZ40: =Y40*50% -> 0 | BA40: =AY40+AZ40 -> 5.09 | BD40: Itu | BE40: HNK BR INDUSTRIA DE BEBIDAS LTDA. | BF40: 50.221.019/0001-36 | BG40: 387000650117 | BH40: Av Primo Schincariol | BI40: 2222 | BJ40: Chácara Flórida | BK40: 13312250 | BL40: Itu | BM40: SP
A41: 0.0426 | B41: =VLOOKUP(F41,Planilha3!D:F,3,0) -> 5.8949334 | C41: =B41/A41 -> 138.37872 | D41: Craft | E41: Eisenbahn | F41: 903741 | G41: 1080284 | H41: CERVEJA EISENBAHN IPA LN 355ML | I41: 12 | J41: 175 | K41: =J41*24 -> 4200 | L41: 700 | M41: =L41/J41 -> 4 | N41: =L41/K41 -> 0.16666667 | O41: 64.37 | P41: =O41/I41 -> 5.3641667 | Q41: =R41*I41 -> 0 | R41: 0 | S41: =T41*I41 -> 0 | T41: 0 | U41: =SUM(R41,T41) -> 0 | V41: 0 | W41: 6.79 | X41: 6.79 | Z41: =L41*(Q41+S41) -> 0 | AA41: =L41*O41 -> 45059 | AB41: =L41*12*0.355/100 -> 29.82 | AD41: =SUM(AJ41,AM41,AP41) -> 0 | AE41: =SUM(R41,T41) -> 0 | AF41: =AD41-AE41 -> 0 | AH41: 0 | AI41: =AH41*AB41 -> 0 | AJ41: =AI41/L41/I41 -> 0 | AL41: =AK41*AB41 -> 0 | AM41: =AL41/L41/I41 -> 0 | AN41: 0 | AO41: =AN41*AB41 -> 0 | AP41: =AO41/L41/I41 -> 0 | AQ41: =SUM(AI41,AL41,AO41) -> 0 | AR41: =SUM(AJ41,AM41,AP41) -> 0 | AS41: =Z41 -> 0 | AT41: =AQ41-AS41 -> 0 | AU41: =O41/I41 -> 5.3641667 | AV41: =AU41-R41-T41 -> 5.3641667 | AW41: =(X41-AV41)/X41 -> 0.20999018 | AY41: =X41*100% -> 6.79 | AZ41: =Y41*50% -> 0 | BA41: =AY41+AZ41 -> 6.79 | BD41: Itu | BE41: HNK BR INDUSTRIA DE BEBIDAS LTDA. | BF41: 50.221.019/0001-36 | BG41: 387000650117 | BH41: Av Primo Schincariol | BI41: 2222 | BJ41: Chácara Flórida | BK41: 13312250 | BL41: Itu | BM41: SP
A42: 0.0426 | B42: =VLOOKUP(F42,Planilha3!D:F,3,0) -> 5.6291775 | C42: =B42/A42 -> 132.14032 | D42: Craft | E42: Eisenbahn | F42: 902544 | G42: 1041649 | H42: CERVEJA EISENBAHN PALE ALE LN 355ML | I42: 12 | J42: 175 | K42: =J42*24 -> 4200 | L42: 700 | M42: =L42/J42 -> 4 | N42: =L42/K42 -> 0.16666667 | O42: 64.37 | P42: =O42/I42 -> 5.3641667 | Q42: =R42*I42 -> 0 | R42: 0 | S42: =T42*I42 -> 0 | T42: 0 | U42: =SUM(R42,T42) -> 0 | V42: 0 | W42: 6.79 | X42: 6.79 | Z42: =L42*(Q42+S42) -> 0 | AA42: =L42*O42 -> 45059 | AB42: =L42*12*0.355/100 -> 29.82 | AD42: =SUM(AJ42,AM42,AP42) -> 0 | AE42: =SUM(R42,T42) -> 0 | AF42: =AD42-AE42 -> 0 | AH42: 0 | AI42: =AH42*AB42 -> 0 | AJ42: =AI42/L42/I42 -> 0 | AL42: =AK42*AB42 -> 0 | AM42: =AL42/L42/I42 -> 0 | AN42: 0 | AO42: =AN42*AB42 -> 0 | AP42: =AO42/L42/I42 -> 0 | AQ42: =SUM(AI42,AL42,AO42) -> 0 | AR42: =SUM(AJ42,AM42,AP42) -> 0 | AS42: =Z42 -> 0 | AT42: =AQ42-AS42 -> 0 | AU42: =O42/I42 -> 5.3641667 | AV42: =AU42-R42-T42 -> 5.3641667 | AW42: =(X42-AV42)/X42 -> 0.20999018 | AY42: =X42*100% -> 6.79 | AZ42: =Y42*50% -> 0 | BA42: =AY42+AZ42 -> 6.79 | BD42: Itu | BE42: HNK BR INDUSTRIA DE BEBIDAS LTDA. | BF42: 50.221.019/0001-36 | BG42: 387000650117 | BH42: Av Primo Schincariol | BI42: 2222 | BJ42: Chácara Flórida | BK42: 13312250 | BL42: Itu | BM42: SP
A43: 0.042 | B43: =VLOOKUP(F43,Planilha3!D:F,3,0) -> 33.175375 | C43: =B43/A43 -> 789.88988 | D43: Craft | E43: Eisenbahn | F43: 903683 | G43: 1110091 | H43: CERVEJA EISENBAHN PALE ALE LT 350ML | I43: 12 | J43: 280 | K43: =J43*24 -> 6720 | L43: 840 | M43: =L43/J43 -> 3 | N43: =L43/K43 -> 0.125 | O43: 53.94 | P43: =O43/I43 -> 4.495 | Q43: =R43*I43 -> 3.24 | R43: 0.27 | S43: =T43*I43 -> 0 | T43: 0 | U43: =SUM(R43,T43) -> 0.27 | V43: 0.27 | W43: 5.69 | X43: 5.09 | Z43: =L43*(Q43+S43) -> 2721.6 | AA43: =L43*O43 -> 45309.6 | AB43: =L43*12*0.35/100 -> 35.28 | AD43: =SUM(AJ43,AM43,AP43) -> 0.26691 | AE43: =SUM(R43,T43) -> 0.27 | AF43: =AD43-AE43 -> -0.00309 | AH43: 76.26 | AI43: =AH43*AB43 -> 2690.4528 | AJ43: =AI43/L43/I43 -> 0.26691 | AL43: =AK43*AB43 -> 0 | AM43: =AL43/L43/I43 -> 0 | AN43: 0 | AO43: =AN43*AB43 -> 0 | AP43: =AO43/L43/I43 -> 0 | AQ43: =SUM(AI43,AL43,AO43) -> 2690.4528 | AR43: =SUM(AJ43,AM43,AP43) -> 0.26691 | AS43: =Z43 -> 2721.6 | AT43: =AQ43-AS43 -> -31.1472 | AU43: =O43/I43 -> 4.495 | AV43: =AU43-R43-T43 -> 4.225 | AW43: =(X43-AV43)/X43 -> 0.16994106 | AY43: =X43*100% -> 5.09 | AZ43: =Y43*50% -> 0 | BA43: =AY43+AZ43 -> 5.09 | BD43: Itu | BE43: HNK BR INDUSTRIA DE BEBIDAS LTDA. | BF43: 50.221.019/0001-36 | BG43: 387000650117 | BH43: Av Primo Schincariol | BI43: 2222 | BJ43: Chácara Flórida | BK43: 13312250 | BL43: Itu | BM43: SP
A44: 0.042 | B44: 0 | C44: =B44/A44 -> 0 | D44: Craft | E44: Eisenbahn | F44: 904773 | G44: 1170235 | H44: CERVEJA EISENBAHN SESSION IPA LA 350ML | I44: 12 | J44: 280 | K44: =J44*24 -> 6720 | L44: 1400 | M44: =L44/J44 -> 5 | N44: =L44/K44 -> 0.20833333 | O44: 53.94 | P44: =O44/I44 -> 4.495 | Q44: =R44*I44 -> 3.24 | R44: 0.27 | S44: =T44*I44 -> 0 | T44: 0 | U44: =SUM(R44,T44) -> 0.27 | V44: 0.27 | W44: 5.69 | X44: 5.09 | Z44: =L44*(Q44+S44) -> 4536 | AA44: =L44*O44 -> 75516 | AB44: =L44*12*0.35/100 -> 58.8 | AD44: =SUM(AJ44,AM44,AP44) -> 0.26691 | AE44: =SUM(R44,T44) -> 0.27 | AF44: =AD44-AE44 -> -0.00309 | AH44: 76.26 | AI44: =AH44*AB44 -> 4484.088 | AJ44: =AI44/L44/I44 -> 0.26691 | AL44: =AK44*AB44 -> 0 | AM44: =AL44/L44/I44 -> 0 | AN44: 0 | AO44: =AN44*AB44 -> 0 | AP44: =AO44/L44/I44 -> 0 | AQ44: =SUM(AI44,AL44,AO44) -> 4484.088 | AR44: =SUM(AJ44,AM44,AP44) -> 0.26691 | AS44: =Z44 -> 4536 | AT44: =AQ44-AS44 -> -51.912 | AU44: =O44/I44 -> 4.495 | AV44: =AU44-R44-T44 -> 4.225 | AW44: =(X44-AV44)/X44 -> 0.16994106 | AY44: =X44*100% -> 5.09 | AZ44: =Y44*50% -> 0 | BA44: =AY44+AZ44 -> 5.09 | BD44: Itu | BE44: HNK BR INDUSTRIA DE BEBIDAS LTDA. | BF44: 50.221.019/0001-36 | BG44: 387000650117 | BH44: Av Primo Schincariol | BI44: 2222 | BJ44: Chácara Flórida | BK44: 13312250 | BL44: Itu | BM44: SP
A45: 0.0426 | B45: =VLOOKUP(F45,Planilha3!D:F,3,0) -> 3.9785144 | C45: =B45/A45 -> 93.392357 | D45: Craft | E45: Eisenbahn | F45: 902581 | G45: 1017033 | H45: CERVEJA EISENBAHN WEIZENBIER LN 355ML | I45: 12 | J45: 175 | K45: =J45*24 -> 4200 | L45: 350 | M45: =L45/J45 -> 2 | N45: =L45/K45 -> 0.083333333 | O45: 64.37 | P45: =O45/I45 -> 5.3641667 | Q45: =R45*I45 -> 0 | R45: 0 | S45: =T45*I45 -> 0 | T45: 0 | U45: =SUM(R45,T45) -> 0 | V45: 0 | W45: 6.79 | X45: 6.79 | Z45: =L45*(Q45+S45) -> 0 | AA45: =L45*O45 -> 22529.5 | AB45: =L45*12*0.355/100 -> 14.91 | AD45: =SUM(AJ45,AM45,AP45) -> 0 | AE45: =SUM(R45,T45) -> 0 | AF45: =AD45-AE45 -> 0 | AH45: 0 | AI45: =AH45*AB45 -> 0 | AJ45: =AI45/L45/I45 -> 0 | AL45: =AK45*AB45 -> 0 | AM45: =AL45/L45/I45 -> 0 | AN45: 0 | AO45: =AN45*AB45 -> 0 | AP45: =AO45/L45/I45 -> 0 | AQ45: =SUM(AI45,AL45,AO45) -> 0 | AR45: =SUM(AJ45,AM45,AP45) -> 0 | AS45: =Z45 -> 0 | AT45: =AQ45-AS45 -> 0 | AU45: =O45/I45 -> 5.3641667 | AV45: =AU45-R45-T45 -> 5.3641667 | AW45: =(X45-AV45)/X45 -> 0.20999018 | AY45: =X45*100% -> 6.79 | AZ45: =Y45*50% -> 0 | BA45: =AY45+AZ45 -> 6.79 | BD45: Itu | BE45: HNK BR INDUSTRIA DE BEBIDAS LTDA. | BF45: 50.221.019/0001-36 | BG45: 387000650117 | BH45: Av Primo Schincariol | BI45: 2222 | BJ45: Chácara Flórida | BK45: 13312250 | BL45: Itu | BM45: SP
A46: 0.0426 | B46: =VLOOKUP(F46,Planilha3!D:F,3,0) -> 2.5961263 | C46: =B46/A46 -> 60.941932 | D46: Craft | E46: Lagunitas | F46: 903901 | G46: 1170142 | H46: CERVEJA LAGUNITAS LN 355ML | I46: 12 | J46: 126 | K46: =J46*24 -> 3024 | L46: 126 | M46: =L46/J46 -> 1 | N46: =L46/K46 -> 0.041666667 | O46: 104.19 | P46: =O46/I46 -> 8.6825 | Q46: =R46*I46 -> 0 | R46: 0 | S46: =T46*I46 -> 0 | T46: 0 | U46: =SUM(R46,T46) -> 0 | V46: 0 | W46: =VLOOKUP(F46,'[1]Proposta HNK para Tenda'!$F:$T,15,0) -> 10.99 | X46: =VLOOKUP(F46,'[1]Proposta HNK para Tenda'!$F:$U,16,0) -> 10.99 | Z46: =L46*(Q46+S46) -> 0 | AA46: =L46*O46 -> 13127.94 | AB46: =L46*12*0.355/100 -> 5.3676 | AD46: =SUM(AJ46,AM46,AP46) -> 0 | AE46: =SUM(R46,T46) -> 0 | AF46: =AD46-AE46 -> 0 | AH46: 0 | AI46: =AH46*AB46 -> 0 | AJ46: =AI46/L46/I46 -> 0 | AL46: =AK46*AB46 -> 0 | AM46: =AL46/L46/I46 -> 0 | AN46: 0 | AO46: =AN46*AB46 -> 0 | AP46: =AO46/L46/I46 -> 0 | AQ46: =SUM(AI46,AL46,AO46) -> 0 | AR46: =SUM(AJ46,AM46,AP46) -> 0 | AS46: =Z46 -> 0 | AT46: =AQ46-AS46 -> 0 | AU46: =O46/I46 -> 8.6825 | AV46: =AU46-R46-T46 -> 8.6825 | AW46: =(X46-AV46)/X46 -> 0.2099636 | AY46: =X46*100% -> 10.99 | AZ46: =Y46*50% -> 0 | BA46: =AY46+AZ46 -> 10.99 | BD46: Itu | BE46: HNK BR INDUSTRIA DE BEBIDAS LTDA. | BF46: 50.221.019/0001-36 | BG46: 387000650117 | BH46: Av Primo Schincariol | BI46: 2222 | BJ46: Chácara Flórida | BK46: 13312250 | BL46: Itu | BM46: SP
A47: 0.042 | B47: =VLOOKUP(F47,Planilha3!D:F,3,0) -> 5.5383412 | C47: =B47/A47 -> 131.86527 | D47: Craft | E47: Lagunitas | F47: 904782 | G47: 1169716 | H47: CERVEJA LAGUNITAS LA 350ML IPA | I47: 12 | J47: 280 | K47: =J47*24 -> 6720 | L47: 560 | M47: =L47/J47 -> 2 | N47: =L47/K47 -> 0.083333333 | O47: 85.23 | P47: =O47/I47 -> 7.1025 | Q47: =R47*I47 -> 10.8 | R47: 0.9 | S47: =T47*I47 -> 0.24 | T47: 0.02 | U47: =SUM(R47,T47) -> 0.92 | V47: 0.92 | W47: =VLOOKUP(F47,'[1]Proposta HNK para Tenda'!$F:$T,15,0) -> 8.99 | X47: =VLOOKUP(F47,'[1]Proposta HNK para Tenda'!$F:$U,16,0) -> 6.99 | Z47: =L47*(Q47+S47) -> 6182.4 | AA47: =L47*O47 -> 47728.8 | AB47: =L47*12*0.35/100 -> 23.52 | AD47: =SUM(AJ47,AM47,AP47) -> 0.93051 | AE47: =SUM(R47,T47) -> 0.92 | AF47: =AD47-AE47 -> 0.01051 | AH47: 265.86 | AI47: =AH47*AB47 -> 6253.0272 | AJ47: =AI47/L47/I47 -> 0.93051 | AL47: =AK47*AB47 -> 0 | AM47: =AL47/L47/I47 -> 0 | AN47: 0 | AO47: =AN47*AB47 -> 0 | AP47: =AO47/L47/I47 -> 0 | AQ47: =SUM(AI47,AL47,AO47) -> 6253.0272 | AR47: =SUM(AJ47,AM47,AP47) -> 0.93051 | AS47: =Z47 -> 6182.4 | AT47: =AQ47-AS47 -> 70.6272 | AU47: =O47/I47 -> 7.1025 | AV47: =AU47-R47-T47 -> 6.1825 | AW47: =(X47-AV47)/X47 -> 0.11552217 | AY47: =X47*100% -> 6.99 | AZ47: =Y47*50% -> 0 | BA47: =AY47+AZ47 -> 6.99 | BD47: Itu | BE47: HNK BR INDUSTRIA DE BEBIDAS LTDA. | BF47: 50.221.019/0001-36 | BG47: 387000650117 | BH47: Av Primo Schincariol | BI47: 2222 | BJ47: Chácara Flórida | BK47: 13312250 | BL47: Itu | BM47: SP
N48: =SUM(N5:N47) -> 338.05128 | Z48: =SUBTOTAL(9,Z5:Z47) -> 9417451.2 | AA48: =SUBTOTAL(9,AA5:AA47) -> 1.1395322e+08 | AB48: =SUBTOTAL(9,AB5:AB47) -> 89092.45 | AI48: =SUBTOTAL(9,AI5:AI47) -> 3116511.7 | AL48: =SUBTOTAL(9,AL5:AL47) -> 780649.74 | AO48: =SUBTOTAL(9,AO5:AO47) -> 5525350.1 | AQ48: =SUBTOTAL(9,AQ5:AQ47) -> 9422511.5 | AS48: =SUM(AS5:AS47) -> 9417451.2 | AT48: =AQ48-AS48 -> 5060.3474 | XEO48: =SUM(XEO5:XFD47) -> 0
AH50: Gerado | AI50: =AQ48 -> 9422511.5
AH51: Sell in pedido | AI51: =Z48 -> 9417451.2
AH52: Diferença | AI52: =AI50-AI51 -> 5060.3474 | AJ52: 366046.2
X54: Fechamento por categoria | AF54: =AI50/AA48 -> 0.082687538 | AH54: % Gerado | AI54: =AI50/AA48 -> 0.082687538
X55: Craft | Z55: =SUM(Z29:Z47) -> 121900.8 | AH55: % Liberdo | AI55: =Z48/AA48 -> 0.082643131
X56: Premiun | Z56: =SUM(Z10:Z25) -> 5114527.7
X57: Mainstream | Z57: =SUM(Z5:Z6,Z7) -> 4132800
X58: Refrigerante | Z58: =SUM(#REF!) -> #REF!
Z59: =SUM(Z55:Z58) -> #REF!

Sheet Planilha4
C2: PRODUTO | D2: Total Investimento Liberado | E2: Investimento solicitado pelo Assaí
C3: CERVEJA AMSTEL LN 355ML | D3: 0.25 | E3: 0.8
C4: CERVEJA HEINEKEN 269ML | D4: 0.18 | E4: 0.4

Sheet Proposta Final Assaí Ultimo Tri
T1: 0.2 | U1: 0.75 | X1: 1468816 | Z1: =Z18+AA50 -> 1566174.6
T2: 0.08 | U2: 0.3 | AI2: =SUBTOTAL(9,AI5:AI47) -> 2977758.6 | AL2: =SUBTOTAL(9,AL5:AL47) -> 811717.25 | AO2: =SUBTOTAL(9,AO5:AO47) -> 5646392.3
B3: =SUBTOTAL(9,B5:B47) -> #N/A | W3: SUGESTÃO DE PREÇO OUT'25 | Z3: =SUBTOTAL(9,Z5:Z47) -> 9523544.6 | AB3: =SUBTOTAL(9,AB5:AB47) -> 89748.895 | AD3: Total de Investimento Gerado | AE3: TT Investimento Liberado | AF3: Diferença | AI3: Verba Calendario TPR | AL3: Back Margem | AO3: Verba Adicional | AQ3: =SUBTOTAL(9,AQ5:AQ47) -> 9435868.2 | AW3: Margem entregue no promo
A4: Coeficiente | B4: HL Act Restrito | C4: Em caixas | D4: Categoria | E4: Marcas | F4: CÓDIGO SAP HNK | G4: CÓDIGO | H4: PRODUTO | I4: CX | J4: PALETE | K4: CARGA | L4: QTDE COMPRA | M4: QTDE PALETE | N4: QTDE CARRO | O4: CUSTO CX NF | P4: Custo Unitário | Q4: VERBA SELL IN CX | R4: * VERBA SELL IN UND | S4: VERBA ADIC CX | T4: * VERBA ADIC UND | U4: Total Investimento Liberado | V4: Investimento solicitado pelo Assaí | W4: PREÇO REGULAR | X4: PREÇO PROMO | Y4: PREÇO LIBERADO TELE | Z4: VERBA TOTAL SELL IN | AA4: TOTAL PEDIDO NF | AB4: HL | AH4: R$/HL | AI4: Verba Gerado | AJ4: Verba unidade | AK4: R$/HL | AL4: Verba Gerado | AM4: Verba unidade | AN4: R$/HL | AO4: Verba Gerado | AP4: Verba unidade | AQ4: Gerado total | AR4: Unidade total | AS4: VERBA TOTAL SELL IN | AT4: Saving | AU4: CUSTO UNI. NF | AV4: NOVO CUSTO | AY4: 50% Volume preço Promo | AZ4: 50% Volume preço Televendas | BA4: Preço Médio | BB4: Margem entregue | BD4: Cidade | BE4: Razão social | BF4: CNPJ | BG4: Inscrição estadual | BH4: Endereço | BI4: Número | BJ4: Bairro | BK4: Cidade | BL4: Estado | BM4: Cep
A5: 0.03228 | B5: =VLOOKUP(F5,Planilha3!D:F,3,0) -> 1663.6933 | C5: =B5/A5 -> 51539.444 | D5: Mainstream | E5: Amstel | F5: 904113 | G5: 1052772 | H5: CERVEJA AMSTEL 269ML | I5: 12 | J5: 336 | K5: =J5*24 -> 8064 | L5: =K5*85 -> 685440 | M5: =L5/J5 -> 2040 | N5: =L5/K5 -> 85 | O5: 33.16 | P5: =O5/I5 -> 2.7633333 | Q5: =R5*I5 -> 0.6 | R5: 0.05 | S5: =T5*I5 -> 3.6 | T5: 0.3 | U5: =SUM(R5,T5) -> 0.35 | V5: 0.35 | W5: =VLOOKUP(F5,'[1]Proposta HNK para Tenda'!$F:$T,15,0) -> 3.29 | X5: =VLOOKUP(F5,'[1]Proposta HNK para Tenda'!$F:$U,16,0) -> 3.09 | Y5: 2.79 | Z5: =L5*(Q5+S5) -> 2878848 | AA5: =L5*O5 -> 22729190 | AB5: =L5*12*0.269/100 -> 22126.003 | AD5: =SUM(AJ5,AM5,AP5) -> 0.3681265 | AE5: =SUM(R5,T5) -> 0.35 | AF5: =AD5-AE5 -> 0.0181265 | AH5: 19.98 | AI5: =AH5*AB5 -> 442077.54 | AJ5: =AI5/L5/I5 -> 0.0537462 | AK5: 23.87 | AL5: =AK5*AB5 -> 528147.7 | AM5: =AL5/L5/I5 -> 0.0642103 | AN5: 93 | AO5: =AN5*AB5 -> 2057718.3 | AP5: =AO5/L5/I5 -> 0.25017 | AQ5: =SUM(AI5,AL5,AO5) -> 3027943.5 | AR5: =SUM(AJ5,AM5,AP5) -> 0.3681265 | AS5: =Z5 -> 2878848 | AT5: =AQ5-AS5 -> 149095.54 | AU5: =O5/I5 -> 2.7633333 | AV5: =AU5-R5-T5 -> 2.4133333 | AW5: =(X5-AV5)/X5 -> 0.21898598 | AY5: =X5*50% -> 1.545 | AZ5: =Y5*50% -> 1.395 | BA5: =AY5+AZ5 -> 2.94 | BB5: =(X5-Y5)/X5 -> 0.097087379 | BD5: Itu | BE5: HNK BR INDUSTRIA DE BEBIDAS LTDA. | BF5: 50.221.019/0001-36 | BG5: 387000650117 | BH5: Av Primo Schincariol | BI5: 2222 | BJ5: Chácara Flórida | BK5: 13312250 | BL5: Itu | BM5: SP
A6: 0.042 | B6: =VLOOKUP(F6,Planilha3!D:F,3,0) -> 1031.9338 | C6: =B6/A6 -> 24569.852 | D6: Mainstream | E6: Amstel | F6: 904952 | G6: 1193288 | H6: CERVEJA AMSTEL 350ML SLEEK | I6: 12 | J6: 280 | K6: =J6*24 -> 6720 | L6: 302400 | M6: =L6/J6 -> 1080 | N6: =L6/K6 -> 45 | O6: 39.21 | P6: =O6/I6 -> 3.2675 | Q6: =R6*I6 -> 1.2 | R6: 0.1 | S6: =T6*I6 -> 3.24 | T6: 0.27 | U6: =SUM(R6,T6) -> 0.37 | V6: 0.37 | W6: =VLOOKUP(F6,'[1]Proposta HNK para Tenda'!$F:$T,15,0) -> 3.89 | X6: =VLOOKUP(F6,'[1]Proposta HNK para Tenda'!$F:$U,16,0) -> 3.69 | Y6: 3.29 | Z6: =L6*(Q6+S6) -> 1342656 | AA6: =L6*O6 -> 11857104 | AB6: =L6*12*0.35/100 -> 12700.8 | AD6: =SUM(AJ6,AM6,AP6) -> 0.378 | AE6: =SUM(R6,T6) -> 0.37 | AF6: =AD6-AE6 -> 0.008 | AH6: 21.4 | AI6: =AH6*AB6 -> 271797.12 | AJ6: =AI6/L6/I6 -> 0.0749 | AK6: 21.6 | AL6: =AK6*AB6 -> 274337.28 | AM6: =AL6/L6/I6 -> 0.0756 | AN6: 65 | AO6: =AN6*AB6 -> 825552 | AP6: =AO6/L6/I6 -> 0.2275 | AQ6: =SUM(AI6,AL6,AO6) -> 1371686.4 | AR6: =SUM(AJ6,AM6,AP6) -> 0.378 | AS6: =Z6 -> 1342656 | AT6: =AQ6-AS6 -> 29030.4 | AU6: =O6/I6 -> 3.2675 | AV6: =AU6-R6-T6 -> 2.8975 | AW6: =(X6-AV6)/X6 -> 0.21476965 | AY6: =X6*50% -> 1.845 | AZ6: =Y6*50% -> 1.645 | BA6: =AY6+AZ6 -> 3.49 | BB6: =(X6-Y6)/X6 -> 0.10840108 | BD6: Jacarei | BE6: HNK BR INDUSTRIA DE BEBIDAS LTDA. | BF6: 50.221.019/0104-41 | BG6: 392558326113 | BH6: Av Presidente Humberto de Alencar Castelo Branco | BI6: 2911 | BJ6: Conjunto Habitacional Marinho | BK6: 12321150 | BL6: Jacareí | BM6: SP
A7: 0.072 | B7: =VLOOKUP(F7,Planilha3!D:F,3,0) -> 40.23064 | C7: =B7/A7 -> 558.75888 | D7: Mainstream | E7: Amstel | F7: 905052 | G7: 1207152 | H7: CERVEJA AMSTEL LN 355ML | I7: 12 | J7: 175 | K7: =J7*24 -> 4200 | L7: 8400 | M7: =L7/J7 -> 48 | N7: =L7/K7 -> 2 | O7: 47.28 | P7: =O7/I7 -> 3.94 | Q7: =R7*I7 -> 0.6 | R7: 0.05 | S7: =T7*I7 -> 9 | T7: 0.75 | U7: =SUM(R7,T7) -> 0.8 | V7: 0.8 | W7: =VLOOKUP(F7,'[1]Proposta HNK para Tenda'!$F:$T,15,0) -> 4.69 | X7: =VLOOKUP(F7,'[1]Proposta HNK para Tenda'!$F:$U,16,0) -> 4.49 | Z7: =L7*(Q7+S7) -> 80640 | AA7: =L7*O7 -> 397152 | AB7: =L7*12*0.355/100 -> 357.84 | AD7: =SUM(AJ7,AM7,AP7) -> 0.1662465 | AE7: =SUM(R7,T7) -> 0.8 | AF7: =AD7-AE7 -> -0.6337535 | AH7: 21.03 | AI7: =AH7*AB7 -> 7525.3752 | AJ7: =AI7/L7/I7 -> 0.0746565 | AK7: 25.8 | AL7: =AK7*AB7 -> 9232.272 | AM7: =AL7/L7/I7 -> 0.09159 | AN7: 0 | AO7: =AN7*AB7 -> 0 | AP7: =AO7/L7/I7 -> 0 | AQ7: =SUM(AI7,AL7,AO7) -> 16757.647 | AR7: =SUM(AJ7,AM7,AP7) -> 0.1662465 | AS7: =Z7 -> 80640 | AT7: =AQ7-AS7 -> -63882.353 | AU7: =O7/I7 -> 3.94 | AV7: =AU7-R7-T7 -> 3.14 | AW7: =(X7-AV7)/X7 -> 0.30066815 | AY7: =X7*100% -> 4.49 | AZ7: =Y7*50% -> 0 | BA7: =AY7+AZ7 -> 4.49 | BD7: Itu | BE7: HNK BR INDUSTRIA DE BEBIDAS LTDA. | BF7: 50.221.019/0001-36 | BG7: 387000650117 | BH7: Av Primo Schincariol | BI7: 2222 | BJ7: Chácara Flórida | BK7: 13312250 | BL7: Itu | BM7: SP
A8: =0.275*12/100 -> 0.033 | B8: =VLOOKUP(F8,Planilha3!D:F,3,0) -> #N/A | C8: =B8/A8 -> #N/A | D8: Mainstream | E8: Amstel | F8: 904632 | G8: 1155684 | H8: CERVEJA AMSTEL ULTRA 269 ML | I8: 12 | J8: 364 | K8: =J8*24 -> 8736 | L8: =J8*68 -> 24752 | M8: =L8/J8 -> 68 | N8: =L8/K8 -> 2.8333333 | O8: 39.26 | P8: =O8/I8 -> 3.2716667 | Q8: =R8*I8 -> 1.2 | R8: 0.1 | S8: =T8*I8 -> 1.56 | T8: 0.13 | U8: =SUM(R8,T8) -> 0.23 | V8: 0.23 | W8: 3.99 | X8: 3.49 | Z8: =L8*(Q8+S8) -> 68315.52 | AA8: =L8*O8 -> 971763.52 | AB8: =L8*12*0.275/100 -> 816.816 | AD8: =SUM(AJ8,AM8,AP8) -> 0.2377375 | AE8: =SUM(R8,T8) -> 0.23 | AF8: =AD8-AE8 -> 0.0077375 | AH8: 86.45 | AI8: =AH8*AB8 -> 70613.743 | AJ8: =AI8/L8/I8 -> 0.2377375 | AK8: 0 | AL8: =AK8*AB8 -> 0 | AM8: =AL8/L8/I8 -> 0 | AN8: 0 | AO8: =AN8*AB8 -> 0 | AP8: =AO8/L8/I8 -> 0 | AQ8: =SUM(AI8,AL8,AO8) -> 70613.743 | AR8: =SUM(AJ8,AM8,AP8) -> 0.2377375 | AS8: =Z8 -> 68315.52 | AT8: =AQ8-AS8 -> 2298.2232 | AU8: =O8/I8 -> 3.2716667 | AV8: =AU8-R8-T8 -> 3.0416667 | AW8: =(X8-AV8)/X8 -> 0.12846227 | AY8: =X8*100% -> 3.49 | AZ8: =Y8*50% -> 0 | BA8: =AY8+AZ8 -> 3.49 | BD8: Itu | BE8: HNK BR INDUSTRIA DE BEBIDAS LTDA. | BF8: 50.221.019/0001-36 | BG8: 387000650117 | BH8: Av Primo Schincariol | BI8: 2222 | BJ8: Chácara Flórida | BK8: 13312250 | BL8: Itu | BM8: SP
A9: =0.275*12/100 -> 0.033 | B9: =VLOOKUP(F9,Planilha3!D:F,3,0) -> 7.6058015 | C9: =B9/A9 -> 230.47883 | D9: Mainstream | E9: Amstel | F9: 904631 | G9: 1160860 | H9: CERVEJA AMSTEL ULTRA LN 275 ML | I9: 12 | J9: 196 | K9: =J9*24 -> 4704 | L9: 0 | M9: =L9/J9 -> 0 | N9: =L9/K9 -> 0 | O9: 47.13 | P9: =O9/I9 -> 3.9275 | Q9: =R9*I9 -> 0 | R9: 0 | S9: =T9*I9 -> 0 | T9: 0 | U9: =SUM(R9,T9) -> 0 | V9: 0 | W9: =VLOOKUP(F9,'[1]Proposta HNK para Tenda'!$F:$T,15,0) -> 4.79 | X9: =VLOOKUP(F9,'[1]Proposta HNK para Tenda'!$F:$U,16,0) -> 4.79 | Z9: =L9*(Q9+S9) -> 0 | AA9: =L9*O9 -> 0 | AB9: =L9*12*0.275/100 -> 0 | AD9: =SUM(AJ9,AM9,AP9) -> #DIV/0! | AE9: =SUM(R9,T9) -> 0 | AF9: =AD9-AE9 -> #DIV/0! | AH9: 0 | AI9: =AH9*AB9 -> 0 | AJ9: =AI9/L9/I9 -> #DIV/0! | AL9: =AK9*AB9 -> 0 | AM9: =AL9/L9/I9 -> #DIV/0! | AN9: 0 | AO9: =AN9*AB9 -> 0 | AP9: =AO9/L9/I9 -> #DIV/0! | AQ9: =SUM(AI9,AL9,AO9) -> 0 | AR9: =SUM(AJ9,AM9,AP9) -> #DIV/0! | AS9: =Z9 -> 0 | AT9: =AQ9-AS9 -> 0 | AU9: =O9/I9 -> 3.9275 | AV9: =AU9-R9-T9 -> 3.9275 | AW9: =(X9-AV9)/X9 -> 0.18006263 | AY9: =X9*100% -> 4.79 | AZ9: =Y9*50% -> 0 | BA9: =AY9+AZ9 -> 4.79 | BD9: Itu | BE9: HNK BR INDUSTRIA DE BEBIDAS LTDA. | BF9: 50.221.019/0001-36 | BG9: 387000650117 | BH9: Av Primo Schincariol | BI9: 2222 | BJ9: Chácara Flórida | BK9: 13312250 | BL9: Itu | BM9: SP
A10: 0.03228 | B10: =VLOOKUP(F10,Planilha3!D:F,3,0) -> 113.71405 | C10: =B10/A10 -> 3522.7399 | D10: Premium | E10: Eisenbahn | F10: 904194 | G10: 1153719 | H10: CERVEJA EISENBAHN PILSEN 269ML | I10: 12 | J10: 364 | K10: =J10*24 -> 8736 | L10: =K10*2 -> 17472 | M10: =L10/J10 -> 48 | N10: =L10/K10 -> 2 | O10: 31.52 | P10: =O10/I10 -> 2.6266667 | Q10: =R10*I10 -> 0 | R10: 0 | S10: =T10*I10 -> 0 | T10: 0 | U10: =SUM(R10,T10) -> 0 | V10: 0 | W10: 3.09 | X10: 3.09 | Z10: =L10*(Q10+S10) -> 0 | AA10: =L10*O10 -> 550717.44 | AB10: =L10*12*0.269/100 -> 563.99616 | AD10: =SUM(AJ10,AM10,AP10) -> 0 | AE10: =SUM(R10,T10) -> 0 | AF10: =AD10-AE10 -> 0 | AH10: 0 | AI10: =AH10*AB10 -> 0 | AJ10: =AI10/L10/I10 -> 0 | AL10: =AK10*AB10 -> 0 | AM10: =AL10/L10/I10 -> 0 | AN10: 0 | AO10: =AN10*AB10 -> 0 | AP10: =AO10/L10/I10 -> 0 | AQ10: =SUM(AI10,AL10,AO10) -> 0 | AR10: =SUM(AJ10,AM10,AP10) -> 0 | AS10: =Z10 -> 0 | AT10: =AQ10-AS10 -> 0 | AU10: =O10/I10 -> 2.6266667 | AV10: =AU10-R10-T10 -> 2.6266667 | AW10: =(X10-AV10)/X10 -> 0.14994606 | AY10: =X10*100% -> 3.09 | AZ10: =Y10*50% -> 0 | BA10: =AY10+AZ10 -> 3.09 | BD10: Itu | BE10: HNK BR INDUSTRIA DE BEBIDAS LTDA. | BF10: 50.221.019/0001-36 | BG10: 387000650117 | BH10: Av Primo Schincariol | BI10: 2222 | BJ10: Chácara Flórida | BK10: 13312250 | BL10: Itu | BM10: SP
A11: 0.042 | B11: =VLOOKUP(F11,Planilha3!D:F,3,0) -> 719.15382 | C11: =B11/A11 -> 17122.71 | D11: Premium | E11: Eisenbahn | F11: 903750 | G11: 1055249 | H11: CERVEJA EISENBAHN PILSEN 350ML | I11: 12 | J11: 280 | K11: =J11*24 -> 6720 | L11: =K11*6 -> 40320 | M11: =L11/J11 -> 144 | N11: =L11/K11 -> 6 | O11: 40.7 | P11: =O11/I11 -> 3.3916667 | Q11: =R11*I11 -> 0 | R11: 0 | S11: =T11*I11 -> 0 | T11: 0 | U11: =SUM(R11,T11) -> 0 | V11: 0 | W11: 3.99 | X11: 3.99 | Z11: =L11*(Q11+S11) -> 0 | AA11: =L11*O11 -> 1641024 | AB11: =L11*12*0.35/100 -> 1693.44 | AD11: =SUM(AJ11,AM11,AP11) -> 0 | AE11: =SUM(R11,T11) -> 0 | AF11: =AD11-AE11 -> 0 | AH11: 0 | AI11: =AH11*AB11 -> 0 | AJ11: =AI11/L11/I11 -> 0 | AL11: =AK11*AB11 -> 0 | AM11: =AL11/L11/I11 -> 0 | AN11: 0 | AO11: =AN11*AB11 -> 0 | AP11: =AO11/L11/I11 -> 0 | AQ11: =SUM(AI11,AL11,AO11) -> 0 | AR11: =SUM(AJ11,AM11,AP11) -> 0 | AS11: =Z11 -> 0 | AT11: =AQ11-AS11 -> 0 | AU11: =O11/I11 -> 3.3916667 | AV11: =AU11-R11-T11 -> 3.3916667 | AW11: =(X11-AV11)/X11 -> 0.14995823 | AY11: =X11*100% -> 3.99 | AZ11: =Y11*50% -> 0 | BA11: =AY11+AZ11 -> 3.99 | BD11: Itu | BE11: HNK BR INDUSTRIA DE BEBIDAS LTDA. | BF11: 50.221.019/0001-36 | BG11: 387000650117 | BH11: Av Primo Schincariol | BI11: 2222 | BJ11: Chácara Flórida | BK11: 13312250 | BL11: Itu | BM11: SP
A12: 0.0426 | B12: =VLOOKUP(F12,Planilha3!D:F,3,0) -> 44.325777 | C12: =B12/A12 -> 1040.5112 | D12: Premium | E12: Eisenbahn | F12: 901781 | G12: 1016972 | H12: CERVEJA EISENBAHN PILSEN LN 355ML | I12: 12 | J12: 175 | K12: =J12*24 -> 4200 | L12: =K12*1 -> 4200 | M12: =L12/J12 -> 24 | N12: =L12/K12 -> 1 | O12: 51.92 | P12: =O12/I12 -> 4.3266667 | Q12: =R12*I12 -> 3 | R12: 0.25 | S12: =T12*I12 -> 0.36 | T12: 0.03 | U12: =SUM(R12,T12) -> 0.28 | V12: 0.28 | W12: 5.09 | X12: 4.19 | Z12: =L12*(Q12+S12) -> 14112 | AA12: =L12*O12 -> 218064 | AB12: =L12*12*0.355/100 -> 178.92 | AD12: =SUM(AJ12,AM12,AP12) -> 0.28826 | AE12: =SUM(R12,T12) -> 0.28 | AF12: =AD12-AE12 -> 0.00826 | AH12: 81.2 | AI12: =AH12*AB12 -> 14528.304 | AJ12: =AI12/L12/I12 -> 0.28826 | AL12: =AK12*AB12 -> 0 | AM12: =AL12/L12/I12 -> 0 | AN12: 0 | AO12: =AN12*AB12 -> 0 | AP12: =AO12/L12/I12 -> 0 | AQ12: =SUM(AI12,AL12,AO12) -> 14528.304 | AR12: =SUM(AJ12,AM12,AP12) -> 0.28826 | AS12: =Z12 -> 14112 | AT12: =AQ12-AS12 -> 416.304 | AU12: =O12/I12 -> 4.3266667 | AV12: =AU12-R12-T12 -> 4.0466667 | AW12: =(X12-AV12)/X12 -> 0.034208433 | AY12: =X12*100% -> 4.19 | AZ12: =Y12*50% -> 0 | BA12: =AY12+AZ12 -> 4.19 | BD12: Itu | BE12: HNK BR INDUSTRIA DE BEBIDAS LTDA. | BF12: 50.221.019/0001-36 | BG12: 387000650117 | BH12: Av Primo Schincariol | BI12: 2222 | BJ12: Chácara Flórida | BK12: 13312250 | BL12: Itu | BM12: SP
A13: 0.042 | B13: =VLOOKUP(F13,Planilha3!D:F,3,0) -> 32.20274 | C13: =B13/A13 -> 766.73189 | D13: Premium | E13: Eisenbahn | F13: 904772 | G13: 1170146 | H13: CERVEJA EISENBAHN UNFILTERED LA 350ML | I13: 12 | J13: 280 | K13: =J13*24 -> 6720 | L13: 6720 | M13: =L13/J13 -> 24 | N13: =L13/K13 -> 1 | O13: 40.7 | P13: =O13/I13 -> 3.3916667 | Q13: =R13*I13 -> 0 | R13: 0 | S13: =T13*I13 -> 0 | T13: 0 | U13: =SUM(R13,T13) -> 0 | V13: 0 | W13: 3.99 | X13: 3.99 | Z13: =L13*(Q13+S13) -> 0 | AA13: =L13*O13 -> 273504 | AB13: =L13*12*0.35/100 -> 282.24 | AD13: =SUM(AJ13,AM13,AP13) -> 0 | AE13: =SUM(R13,T13) -> 0 | AF13: =AD13-AE13 -> 0 | AH13: 0 | AI13: =AH13*AB13 -> 0 | AJ13: =AI13/L13/I13 -> 0 | AL13: =AK13*AB13 -> 0 | AM13: =AL13/L13/I13 -> 0 | AN13: 0 | AO13: =AN13*AB13 -> 0 | AP13: =AO13/L13/I13 -> 0 | AQ13: =SUM(AI13,AL13,AO13) -> 0 | AR13: =SUM(AJ13,AM13,AP13) -> 0 | AS13: =Z13 -> 0 | AT13: =AQ13-AS13 -> 0 | AU13: =O13/I13 -> 3.3916667 | AV13: =AU13-R13-T13 -> 3.3916667 | AW13: =(X13-AV13)/X13 -> 0.14995823 | AY13: =X13*100% -> 3.99 | AZ13: =Y13*50% -> 0 | BA13: =AY13+AZ13 -> 3.99 | BD13: Itu | BE13: HNK BR INDUSTRIA DE BEBIDAS LTDA. | BF13: 50.221.019/0001-36 | BG13: 387000650117 | BH13: Av Primo Schincariol | BI13: 2222 | BJ13: Chácara Flórida | BK13: 13312250 | BL13: Itu | BM13: SP
A14: 0.0426 | B14: =VLOOKUP(F14,Planilha3!D:F,3,0) -> 1.8908876 | C14: =B14/A14 -> 44.387033 | D14: Premium | E14: Eisenbahn | F14: 904771 | G14: 1170180 | H14: CERVEJA EISENBAHN UNFILTERED LN 355ML | I14: 12 | J14: 175 | K14: =J14*24 -> 4200 | L14: 0 | M14: =L14/J14 -> 0 | N14: =L14/K14 -> 0 | O14: 51.92 | P14: =O14/I14 -> 4.3266667 | Q14: =R14*I14 -> 3 | R14: 0.25 | S14: =T14*I14 -> 0.36 | T14: 0.03 | U14: =SUM(R14,T14) -> 0.28 | V14: 0.28 | W14: 5.09 | X14: 4.19 | Z14: =L14*(Q14+S14) -> 0 | AA14: =L14*O14 -> 0 | AB14: =L14*12*0.355/100 -> 0 | AD14: =SUM(AJ14,AM14,AP14) -> #DIV/0! | AE14: =SUM(R14,T14) -> 0.28 | AF14: =AD14-AE14 -> #DIV/0! | AH14: 81.2 | AI14: =AH14*AB14 -> 0 | AJ14: =AI14/L14/I14 -> #DIV/0! | AL14: =AK14*AB14 -> 0 | AM14: =AL14/L14/I14 -> #DIV/0! | AN14: 0 | AO14: =AN14*AB14 -> 0 | AP14: =AO14/L14/I14 -> #DIV/0! | AQ14: =SUM(AI14,AL14,AO14) -> 0 | AR14: =SUM(AJ14,AM14,AP14) -> #DIV/0! | AS14: =Z14 -> 0 | AT14: =AQ14-AS14 -> 0 | AU14: =O14/I14 -> 4.3266667 | AV14: =AU14-R14-T14 -> 4.0466667 | AW14: =(X14-AV14)/X14 -> 0.034208433 | AY14: =X14*100% -> 4.19 | AZ14: =Y14*50% -> 0 | BA14: =AY14+AZ14 -> 4.19 | BD14: Itu | BE14: HNK BR INDUSTRIA DE BEBIDAS LTDA. | BF14: 50.221.019/0001-36 | BG14: 387000650117 | BH14: Av Primo Schincariol | BI14: 2222 | BJ14: Chácara Flórida | BK14: 13312250 | BL14: Itu | BM14: SP
A15: =0.269*8/100 -> 0.02152 | B15: =VLOOKUP(F15,Planilha3!D:F,3,0) -> 105.66937 | C15: =B15/A15 -> 4910.2865 | D15: Premium | E15: Heineken | F15: 904895 | G15: 1208101 | H15: CERVEJA HEINEKEN 0% ALCOOL LA 269ML | I15: 8 | J15: 520 | K15: =J15*26 -> 13520 | L15: 27040 | M15: =L15/J15 -> 52 | N15: =L15/K15 -> 2 | O15: 31.21 | P15: =O15/I15 -> 3.90125 | Q15: =R15*I15 -> 0.8 | R15: 0.1 | S15: =T15*I15 -> 0.64 | T15: 0.08 | U15: =SUM(R15,T15) -> 0.18 | V15: 0.18 | W15: =VLOOKUP(F15,'[1]Proposta HNK para Tenda'!$F:$T,15,0) -> 4.59 | X15: =VLOOKUP(F15,'[1]Proposta HNK para Tenda'!$F:$U,16,0) -> 3.99 | Z15: =L15*(Q15+S15) -> 38937.6 | AA15: =L15*O15 -> 843918.4 | AB15: =L15*8*0.269/100 -> 581.9008 | AD15: =SUM(AJ15,AM15,AP15) -> 0.1905596 | AE15: =SUM(R15,T15) -> 0.18 | AF15: =AD15-AE15 -> 0.0105596 | AH15: 70.84 | AI15: =AH15*AB15 -> 41221.853 | AJ15: =AI15/L15/I15 -> 0.1905596 | AL15: =AK15*AB15 -> 0 | AM15: =AL15/L15/I15 -> 0 | AN15: 0 | AO15: =AN15*AB15 -> 0 | AP15: =AO15/L15/I15 -> 0 | AQ15: =SUM(AI15,AL15,AO15) -> 41221.853 | AR15: =SUM(AJ15,AM15,AP15) -> 0.1905596 | AS15: =Z15 -> 38937.6 | AT15: =AQ15-AS15 -> 2284.2527 | AU15: =O15/I15 -> 3.90125 | AV15: =AU15-R15-T15 -> 3.72125 | AW15: =(X15-AV15)/X15 -> 0.06735589 | AY15: =X15*100% -> 3.99 | AZ15: =Y15*50% -> 0 | BA15: =AY15+AZ15 -> 3.99 | BD15: Ponta Grossa | BE15: HNK BR INDUSTRIA DE BEBIDAS LTDA. | BF15: 50.221.019/0097-88 | BG15: 911.300.50.81 | BH15: Av Tocantins | BI15: 199 | BJ15: Cara-Cara | BK15: 84043610 | BL15: Ponta Grossa | BM15: PR
A16: 0.042 | B16: =VLOOKUP(F16,Planilha3!D:F,3,0) -> 151.60164 | C16: =B16/A16 -> 3609.5629 | D16: Premium | E16: Heineken | F16: 904961 | G16: 1193325 | H16: CERVEJA HEINEKEN 0% ALCOOL LA 350ML SLEEK | I16: 12 | J16: 280 | K16: =J16*26 -> 7280 | L16: 109200 | M16: =L16/J16 -> 390 | N16: =L16/K16 -> 15 | O16: 58.04 | P16: =O16/I16 -> 4.8366667 | Q16: =R16*I16 -> 1.2 | R16: 0.1 | S16: =T16*I16 -> 4.2 | T16: 0.35 | U16: =SUM(R16,T16) -> 0.45 | V16: 0.45 | W16: =VLOOKUP(F16,'[1]Proposta HNK para Tenda'!$F:$T,15,0) -> 5.69 | X16: =VLOOKUP(F16,'[1]Proposta HNK para Tenda'!$F:$U,16,0) -> 5.29 | Z16: =L16*(Q16+S16) -> 589680 | AA16: =L16*O16 -> 6337968 | AB16: =L16*12*0.35/100 -> 4586.4 | AD16: =SUM(AJ16,AM16,AP16) -> 0.47901 | AE16: =SUM(R16,T16) -> 0.45 | AF16: =AD16-AE16 -> 0.02901 | AH16: 33.86 | AI16: =AH16*AB16 -> 155295.5 | AJ16: =AI16/L16/I16 -> 0.11851 | AL16: =AK16*AB16 -> 0 | AM16: =AL16/L16/I16 -> 0 | AN16: 103 | AO16: =AN16*AB16 -> 472399.2 | AP16: =AO16/L16/I16 -> 0.3605 | AQ16: =SUM(AI16,AL16,AO16) -> 627694.7 | AR16: =SUM(AJ16,AM16,AP16) -> 0.47901 | AS16: =Z16 -> 589680 | AT16: =AQ16-AS16 -> 38014.704 | AU16: =O16/I16 -> 4.8366667 | AV16: =AU16-R16-T16 -> 4.3866667 | AW16: =(X16-AV16)/X16 -> 0.17076244 | AY16: =X16*100% -> 5.29 | AZ16: =Y16*50% -> 0 | BA16: =AY16+AZ16 -> 5.29 | BD16: Ponta Grossa | BE16: HNK BR INDUSTRIA DE BEBIDAS LTDA. | BF16: 50.221.019/0097-88 | BG16: 911.300.50.81 | BH16: Av Tocantins | BI16: 199 | BJ16: Cara-Cara | BK16: 84043610 | BL16: Ponta Grossa | BM16: PR
A17: 0.0792 | B17: =VLOOKUP(F17,Planilha3!D:F,3,0) -> 143.24875 | C17: =B17/A17 -> 1808.6964 | D17: Premium | E17: Heineken | F17: 903996 | G17: 1140139 | H17: CERVEJA HEINEKEN 0% ALCOOL LN 330ML | I17: 24 | J17: 91 | K17: =J17*26 -> 2366 | L17: 7098 | M17: =L17/J17 -> 78 | N17: =L17/K17 -> 3 | O17: 142.6 | P17: =O17/I17 -> 5.9416667 | Q17: =R17*I17 -> 1.2 | R17: 0.05 | S17: =T17*I17 -> 0.24 | T17: 0.01 | U17: =SUM(R17,T17) -> 0.06 | V17: 0.06 | W17: =VLOOKUP(F17,'[1]Proposta HNK para Tenda'!$F:$T,15,0) -> 6.99 | X17: =VLOOKUP(F17,'[1]Proposta HNK para Tenda'!$F:$U,16,0) -> 6.59 | Z17: =L17*(Q17+S17) -> 10221.12 | AA17: =L17*O17 -> 1012174.8 | AB17: =L17*24*0.33/100 -> 562.1616 | AD17: =SUM(AJ17,AM17,AP17) -> 0.068508 | AE17: =SUM(R17,T17) -> 0.06 | AF17: =AD17-AE17 -> 0.008508 | AH17: 20.76 | AI17: =AH17*AB17 -> 11670.475 | AJ17: =AI17/L17/I17 -> 0.068508 | AL17: =AK17*AB17 -> 0 | AM17: =AL17/L17/I17 -> 0 | AN17: 0 | AO17: =AN17*AB17 -> 0 | AP17: =AO17/L17/I17 -> 0 | AQ17: =SUM(AI17,AL17,AO17) -> 11670.475 | AR17: =SUM(AJ17,AM17,AP17) -> 0.068508 | AS17: =Z17 -> 10221.12 | AT17: =AQ17-AS17 -> 1449.3548 | AU17: =O17/I17 -> 5.9416667 | AV17: =AU17-R17-T17 -> 5.8816667 | AW17: =(X17-AV17)/X17 -> 0.10748609 | AY17: =X17*100% -> 6.59 | AZ17: =Y17*50% -> 0 | BA17: =AY17+AZ17 -> 6.59 | BD17: Ponta Grossa | BE17: HNK BR INDUSTRIA DE BEBIDAS LTDA. | BF17: 50.221.019/0097-88 | BG17: 911.300.50.81 | BH17: Av Tocantins | BI17: 199 | BJ17: Cara-Cara | BK17: 84043610 | BL17: Ponta Grossa | BM17: PR
A18: =0.269*8/100 -> 0.02152 | B18: =VLOOKUP(F18,Planilha3!D:F,3,0) -> 1756.2216 | C18: =B18/A18 -> 81608.811 | D18: Premium | E18: Heineken | F18: 904721 | G18: 1169727 | H18: CERVEJA HEINEKEN 269ML | I18: 8 | J18: 520 | K18: =J18*26 -> 13520 | L18: =K18*45 -> 608400 | M18: =L18/J18 -> 1170 | N18: =L18/K18 -> 45 | O18: 31.21 | P18: =O18/I18 -> 3.90125 | Q18: =R18*I18 -> 0.8 | R18: 0.1 | S18: =T18*I18 -> 1.6 | T18: 0.2 | U18: =SUM(R18,T18) -> 0.3 | V18: 0.4 | W18: =VLOOKUP(F18,'[1]Proposta HNK para Tenda'!$F:$T,15,0) -> 4.59 | X18: =VLOOKUP(F18,'[1]Proposta HNK para Tenda'!$F:$U,16,0) -> 3.99 | Z18: =L18*(Q18+S18) -> 1460160 | AA18: =L18*O18 -> 18988164 | AB18: =L18*8*0.269/100 -> 13092.768 | AD18: =SUM(AJ18,AM18,AP18) -> 0.1905596 | AE18: =SUM(R18,T18) -> 0.3 | AF18: =AD18-AE18 -> -0.1094404 | AH18: 70.84 | AI18: =AH18*AB18 -> 927491.69 | AJ18: =AI18/L18/I18 -> 0.1905596 | AL18: =AK18*AB18 -> 0 | AM18: =AL18/L18/I18 -> 0 | AN18: 0 | AO18: =AN18*AB18 -> 0 | AP18: =AO18/L18/I18 -> 0 | AQ18: =SUM(AI18,AL18,AO18) -> 927491.69 | AR18: =SUM(AJ18,AM18,AP18) -> 0.1905596 | AS18: =Z18 -> 1460160 | AT18: =AQ18-AS18 -> -532668.31 | AU18: =O18/I18 -> 3.90125 | AV18: =AU18-R18-T18 -> 3.60125 | AW18: =(X18-AV18)/X18 -> 0.097431078 | AY18: =X18*100% -> 3.99 | AZ18: =Y18*50% -> 0 | BA18: =AY18+AZ18 -> 3.99 | BD18: Ponta Grossa | BE18: HNK BR INDUSTRIA DE BEBIDAS LTDA. | BF18: 50.221.019/0097-88 | BG18: 911.300.50.81 | BH18: Av Tocantins | BI18: 199 | BJ18: Cara-Cara | BK18: 84043610 | BL18: Ponta Grossa | BM18: PR
A19: 0.042 | B19: =VLOOKUP(F19,Planilha3!D:F,3,0) -> 2524.72 | C19: =B19/A19 -> 60112.38 | D19: Premium | E19: Heineken | F19: 904932 | G19: 1193319 | H19: CERVEJA HEINEKEN 350ML SLEEK | I19: 12 | J19: 280 | K19: =J19*26 -> 7280 | L19: 509600 | M19: =L19/J19 -> 1820 | N19: =L19/K19 -> 70 | O19: 58.04 | P19: =O19/I19 -> 4.8366667 | Q19: =R19*I19 -> 1.2 | R19: 0.1 | S19: =T19*I19 -> 4.2 | T19: 0.35 | U19: =SUM(R19,T19) -> 0.45 | V19: 0.45 | W19: =VLOOKUP(F19,'[1]Proposta HNK para Tenda'!$F:$T,15,0) -> 5.69 | X19: =VLOOKUP(F19,'[1]Proposta HNK para Tenda'!$F:$U,16,0) -> 5.29 | Y19: 4.99 | Z19: =L19*(Q19+S19) -> 2751840 | AA19: =L19*O19 -> 29577184 | AB19: =L19*12*0.35/100 -> 21403.2 | AD19: =SUM(AJ19,AM19,AP19) -> 0.47901 | AE19: =SUM(R19,T19) -> 0.45 | AF19: =AD19-AE19 -> 0.02901 | AH19: 33.86 | AI19: =AH19*AB19 -> 724712.35 | AJ19: =AI19/L19/I19 -> 0.11851 | AL19: =AK19*AB19 -> 0 | AM19: =AL19/L19/I19 -> 0 | AN19: 103 | AO19: =AN19*AB19 -> 2204529.6 | AP19: =AO19/L19/I19 -> 0.3605 | AQ19: =SUM(AI19,AL19,AO19) -> 2929242 | AR19: =SUM(AJ19,AM19,AP19) -> 0.47901 | AS19: =Z19 -> 2751840 | AT19: =AQ19-AS19 -> 177401.95 | AU19: =O19/I19 -> 4.8366667 | AV19: =AU19-R19-T19 -> 4.3866667 | AW19: =(X19-AV19)/X19 -> 0.17076244 | AY19: =X19*50% -> 2.645 | AZ19: =Y19*50% -> 2.495 | BA19: =AY19+AZ19 -> 5.14 | BB19: =(X19-Y19)/X19 -> 0.056710775 | BD19: Jacarei | BE19: HNK BR INDUSTRIA DE BEBIDAS LTDA. | BF19: 50.221.019/0104-41 | BG19: 392558326113 | BH19: Av Presidente Humberto de Alencar Castelo Branco | BI19: 2911 | BJ19: Conjunto Habitacional Marinho | BK19: 12321150 | BL19: Jacareí | BM19: SP
A20: =0.25*24/100 -> 0.06 | B20: =VLOOKUP(F20,Planilha3!D:F,3,0) -> 501.62261 | C20: =B20/A20 -> 8360.3768 | D20: Premium | E20: Heineken | F20: 905291 | G20: 1016561 | H20: CERVEJA HEINEKEN LN 250ML | I20: 24 | J20: 104 | K20: =J20*26 -> 2704 | L20: 24336 | M20: =L20/J20 -> 234 | N20: =L20/K20 -> 9 | O20: 107.92 | P20: =O20/I20 -> 4.4966667 | Q20: =R20*I20 -> 1.2 | R20: 0.05 | S20: =T20*I20 -> 0.72 | T20: 0.03 | U20: =SUM(R20,T20) -> 0.08 | V20: 0.08 | W20: 5.29 | X20: 4.99 | Z20: =L20*(Q20+S20) -> 46725.12 | AA20: =L20*O20 -> 2626341.1 | AB20: =L20*24*0.25/100 -> 1460.16 | AD20: =SUM(AJ20,AM20,AP20) -> 0.237075 | AE20: =SUM(R20,T20) -> 0.08 | AF20: =AD20-AE20 -> 0.157075 | AH20: 35.8 | AI20: =AH20*AB20 -> 52273.728 | AJ20: =AI20/L20/I20 -> 0.0895 | AL20: =AK20*AB20 -> 0 | AM20: =AL20/L20/I20 -> 0 | AN20: 59.03 | AO20: =AN20*AB20 -> 86193.245 | AP20: =AO20/L20/I20 -> 0.147575 | AQ20: =SUM(AI20,AL20,AO20) -> 138466.97 | AR20: =SUM(AJ20,AM20,AP20) -> 0.237075 | AS20: =Z20 -> 46725.12 | AT20: =AQ20-AS20 -> 91741.853 | AU20: =O20/I20 -> 4.4966667 | AV20: =AU20-R20-T20 -> 4.4166667 | AW20: =(X20-AV20)/X20 -> 0.11489646 | AY20: =X20*100% -> 4.99 | AZ20: =Y20*50% -> 0 | BA20: =AY20+AZ20 -> 4.99 | BD20: Jacarei | BE20: HNK BR INDUSTRIA DE BEBIDAS LTDA. | BF20: 50.221.019/0104-41 | BG20: 392558326113 | BH20: Av Presidente Humberto de Alencar Castelo Branco | BI20: 2911 | BJ20: Conjunto Habitacional Marinho | BK20: 12321150 | BL20: Jacareí | BM20: SP
A21: 0.0792 | B21: =VLOOKUP(F21,Planilha3!D:F,3,0) -> 1279.3007 | C21: =B21/A21 -> 16152.787 | D21: Premium | E21: Heineken | F21: 903478 | G21: 1045807 | H21: CERVEJA HEINEKEN LN 330 ML | I21: 24 | J21: 91 | K21: =J21*26 -> 2366 | L21: 70980 | M21: =L21/J21 -> 780 | N21: =L21/K21 -> 30 | O21: 142.6 | P21: =O21/I21 -> 5.9416667 | Q21: =R21*I21 -> 1.2 | R21: 0.05 | S21: =T21*I21 -> 0.24 | T21: 0.01 | U21: =SUM(R21,T21) -> 0.06 | V21: 0.06 | W21: =VLOOKUP(F21,'[1]Proposta HNK para Tenda'!$F:$T,15,0) -> 6.99 | X21: =VLOOKUP(F21,'[1]Proposta HNK para Tenda'!$F:$U,16,0) -> 6.59 | Z21: =L21*(Q21+S21) -> 102211.2 | AA21: =L21*O21 -> 10121748 | AB21: =L21*24*0.33/100 -> 5621.616 | AD21: =SUM(AJ21,AM21,AP21) -> 0.068508 | AE21: =SUM(R21,T21) -> 0.06 | AF21: =AD21-AE21 -> 0.008508 | AH21: 20.76 | AI21: =AH21*AB21 -> 116704.75 | AJ21: =AI21/L21/I21 -> 0.068508 | AL21: =AK21*AB21 -> 0 | AM21: =AL21/L21/I21 -> 0 | AN21: 0 | AO21: =AN21*AB21 -> 0 | AP21: =AO21/L21/I21 -> 0 | AQ21: =SUM(AI21,AL21,AO21) -> 116704.75 | AR21: =SUM(AJ21,AM21,AP21) -> 0.068508 | AS21: =Z21 -> 102211.2 | AT21: =AQ21-AS21 -> 14493.548 | AU21: =O21/I21 -> 5.9416667 | AV21: =AU21-R21-T21 -> 5.8816667 | AW21: =(X21-AV21)/X21 -> 0.10748609 | AY21: =X21*100% -> 6.59 | AZ21: =Y21*50% -> 0 | BA21: =AY21+AZ21 -> 6.59 | BD21: Araraquara | BE21: HNK BR INDUSTRIA DE BEBIDAS LTDA. | BF21: 50.221.019/0105-22 | BG21: 181661963118 | BH21: Av Marginal 01 | BI21: 701 | BJ21: Chácara Catani | BK21: 14808080 | BL21: Araraquara | BM21: SP
A22: 0.072 | B22: =VLOOKUP(F22,Planilha3!D:F,3,0) -> 156.38563 | C22: =B22/A22 -> 2172.0226 | D22: Premium | E22: Heineken | F22: 903480 | G22: 99187 | H22: CERVEJA HEINEKEN ONE WAY 600ML | I22: 12 | J22: 96 | K22: =J22*26 -> 2496 | L22: 2496 | M22: =L22/J22 -> 26 | N22: =L22/K22 -> 1 | O22: 137.6 | P22: =O22/I22 -> 11.466667 | Q22: =R22*I22 -> 0 | R22: 0 | S22: =T22*I22 -> 0 | T22: 0 | U22: =SUM(R22,T22) -> 0 | V22: 0 | W22: =VLOOKUP(F22,'[1]Proposta HNK para Tenda'!$F:$T,15,0) -> 13.49 | X22: =VLOOKUP(F22,'[1]Proposta HNK para Tenda'!$F:$U,16,0) -> 13.49 | Z22: =L22*(Q22+S22) -> 0 | AA22: =L22*O22 -> 343449.6 | AB22: =L22*12*0.6/100 -> 179.712 | AD22: =SUM(AJ22,AM22,AP22) -> 0 | AE22: =SUM(R22,T22) -> 0 | AF22: =AD22-AE22 -> 0 | AH22: 0 | AI22: =AH22*AB22 -> 0 | AJ22: =AI22/L22/I22 -> 0 | AL22: =AK22*AB22 -> 0 | AM22: =AL22/L22/I22 -> 0 | AN22: 0 | AO22: =AN22*AB22 -> 0 | AP22: =AO22/L22/I22 -> 0 | AQ22: =SUM(AI22,AL22,AO22) -> 0 | AR22: =SUM(AJ22,AM22,AP22) -> 0 | AS22: =Z22 -> 0 | AT22: =AQ22-AS22 -> 0 | AU22: =O22/I22 -> 11.466667 | AV22: =AU22-R22-T22 -> 11.466667 | AW22: =(X22-AV22)/X22 -> 0.14998765 | AY22: =X22*100% -> 13.49 | AZ22: =Y22*50% -> 0 | BA22: =AY22+AZ22 -> 13.49 | BD22: Jacarei | BE22: HNK BR INDUSTRIA DE BEBIDAS LTDA. | BF22: 50.221.019/0104-41 | BG22: 392558326113 | BH22: Av Presidente Humberto de Alencar Castelo Branco | BI22: 2911 | BJ22: Conjunto Habitacional Marinho | BK22: 12321150 | BL22: Jacareí | BM22: SP
A23: 0.0792 | B23: 26 | C23: =B23/A23 -> 328.28283 | D23: Premium | E23: Sol | F23: 904701 | G23: 1022426 | H23: CERVEJA SOL PREMIUM LN 330ML | I23: 24 | J23: 91 | K23: =J23*24 -> 2184 | L23: =K23*2 -> 4368 | M23: =L23/J23 -> 48 | N23: =L23/K23 -> 2 | O23: 122.2 | P23: =O23/I23 -> 5.0916667 | Q23: =R23*I23 -> 1.44 | R23: 0.06 | S23: =T23*I23 -> 1.2 | T23: 0.05 | U23: =SUM(R23,T23) -> 0.11 | V23: 0.11 | W23: 5.49 | X23: 5.09 | Z23: =L23*(Q23+S23) -> 11531.52 | AA23: =L23*O23 -> 533769.6 | AB23: =L23*24*0.33/100 -> 345.9456 | AD23: =SUM(AJ23,AM23,AP23) -> 0.119493 | AE23: =SUM(R23,T23) -> 0.11 | AF23: =AD23-AE23 -> 0.009493 | AH23: 36.21 | AI23: =AH23*AB23 -> 12526.69 | AJ23: =AI23/L23/I23 -> 0.119493 | AL23: =AK23*AB23 -> 0 | AM23: =AL23/L23/I23 -> 0 | AN23: 0 | AO23: =AN23*AB23 -> 0 | AP23: =AO23/L23/I23 -> 0 | AQ23: =SUM(AI23,AL23,AO23) -> 12526.69 | AR23: =SUM(AJ23,AM23,AP23) -> 0.119493 | AS23: =Z23 -> 11531.52 | AT23: =AQ23-AS23 -> 995.17018 | AU23: =O23/I23 -> 5.0916667 | AV23: =AU23-R23-T23 -> 4.9816667 | AW23: =(X23-AV23)/X23 -> 0.021283563 | AY23: =X23*100% -> 5.09 | AZ23: =Y23*50% -> 0 | BA23: =AY23+AZ23 -> 5.09 | BD23: Jacarei | BE23: HNK BR INDUSTRIA DE BEBIDAS LTDA. | BF23: 50.221.019/0104-41 | BG23: 392558326113 | BH23: Av Presidente Humberto de Alencar Castelo Branco | BI23: 2911 | BJ23: Conjunto Habitacional Marinho | BK23: 12321150 | BL23: Jacareí | BM23: SP
A24: 0.0792 | B24: 26 | C24: =B24/A24 -> 328.28283 | D24: Premium | E24: Sol | F24: 905271 | G24: 1228753 | H24: CERVEJA SOL 0% PREMIUM LN 330ML | I24: 24 | J24: 91 | K24: =J24*24 -> 2184 | L24: =K24*1 -> 2184 | M24: =L24/J24 -> 24 | N24: =L24/K24 -> 1 | O24: 122.2 | P24: =O24/I24 -> 5.0916667 | Q24: =R24*I24 -> 1.44 | R24: 0.06 | S24: =T24*I24 -> 1.2 | T24: 0.05 | U24: =SUM(R24,T24) -> 0.11 | V24: 0.11 | W24: 5.99 | X24: 5.79 | Z24: =L24*(Q24+S24) -> 5765.76 | AA24: =L24*O24 -> 266884.8 | AB24: =L24*24*0.33/100 -> 172.9728 | AD24: =SUM(AJ24,AM24,AP24) -> 0.119493 | AE24: =SUM(R24,T24) -> 0.11 | AF24: =AD24-AE24 -> 0.009493 | AH24: 36.21 | AI24: =AH24*AB24 -> 6263.3451 | AJ24: =AI24/L24/I24 -> 0.119493 | AL24: =AK24*AB24 -> 0 | AM24: =AL24/L24/I24 -> 0 | AN24: 0 | AO24: =AN24*AB24 -> 0 | AP24: =AO24/L24/I24 -> 0 | AQ24: =SUM(AI24,AL24,AO24) -> 6263.3451 | AR24: =SUM(AJ24,AM24,AP24) -> 0.119493 | AS24: =Z24 -> 5765.76 | AT24: =AQ24-AS24 -> 497.58509 | AU24: =O24/I24 -> 5.0916667 | AV24: =AU24-R24-T24 -> 4.9816667 | AW24: =(X24-AV24)/X24 -> 0.13960852 | AY24: =X24*100% -> 5.79 | AZ24: =Y24*50% -> 0 | BA24: =AY24+AZ24 -> 5.79 | BD24: Jacarei | BE24: HNK BR INDUSTRIA DE BEBIDAS LTDA. | BF24: 50.221.019/0104-41 | BG24: 392558326113 | BH24: Av Presidente Humberto de Alencar Castelo Branco | BI24: 2911 | BJ24: Conjunto Habitacional Marinho | BK24: 12321150 | BL24: Jacareí | BM24: SP
A25: =5*2/100 -> 0.1 | B25: =VLOOKUP(F25,Planilha3!D:F,3,0) -> 282.36335 | C25: =B25/A25 -> 2823.6335 | D25: Premium | E25: Heineken | F25: 903483 | G25: 75013 | H25: CHOPP HEINEKEN 5LT | I25: 2 | J25: 90 | K25: =J25*26 -> 2340 | L25: 9360 | M25: =L25/J25 -> 104 | N25: =L25/K25 -> 4 | O25: 177.63 | P25: =O25/I25 -> 88.815 | Q25: =R25*I25 -> 0 | R25: 0 | S25: =T25*I25 -> 0 | T25: 0 | U25: =SUM(R25,T25) -> 0 | V25: 0 | W25: =VLOOKUP(F25,'[1]Proposta HNK para Tenda'!$F:$T,15,0) -> 113.99 | X25: =VLOOKUP(F25,'[1]Proposta HNK para Tenda'!$F:$U,16,0) -> 113.99 | Z25: =L25*(Q25+S25) -> 0 | AA25: =L25*O25 -> 1662616.8 | AB25: =L25*2*5/100 -> 936 | AD25: =SUM(AJ25,AM25,AP25) -> 0 | AE25: =SUM(R25,T25) -> 0 | AF25: =AD25-AE25 -> 0 | AH25: 0 | AI25: =AH25*AB25 -> 0 | AJ25: =AI25/L25/I25 -> 0 | AL25: =AK25*AB25 -> 0 | AM25: =AL25/L25/I25 -> 0 | AN25: 0 | AO25: =AN25*AB25 -> 0 | AP25: =AO25/L25/I25 -> 0 | AQ25: =SUM(AI25,AL25,AO25) -> 0 | AR25: =SUM(AJ25,AM25,AP25) -> 0 | AS25: =Z25 -> 0 | AT25: =AQ25-AS25 -> 0 | AU25: =O25/I25 -> 88.815 | AV25: =AU25-R25-T25 -> 88.815 | AW25: =(X25-AV25)/X25 -> 0.22085271 | AY25: =X25*100% -> 113.99 | AZ25: =Y25*50% -> 0 | BA25: =AY25+AZ25 -> 113.99 | BD25: Ponta Grossa | BE25: HNK BR INDUSTRIA DE BEBIDAS LTDA. | BF25: 50.221.019/0097-88 | BG25: 911.300.50.81 | BH25: Av Tocantins | BI25: 199 | BJ25: Cara-Cara | BK25: 84043610 | BL25: Ponta Grossa | BM25: PR
A26: =0.355*6/100 -> 0.0213 | C26: =B26/A26 -> 0 | D26: Premium | E26: Praya | F26: 631974 | G26: 1228751 | H26: CERVEJA PRAYA LAGER 355ML | I26: 6 | J26: 350 | K26: =J26*26 -> 9100 | L26: =K26*1 -> 9100 | M26: =L26/J26 -> 26 | N26: =L26/K26 -> 1 | O26: 33.07 | P26: =O26/I26 -> 5.5116667 | Q26: =R26*I26 -> 0 | R26: 0 | S26: =T26*I26 -> 0 | T26: 0 | U26: =SUM(R26,T26) -> 0 | V26: 0 | W26: 6.99 | X26: 6.49 | Z26: =L26*(Q26+S26) -> 0 | AA26: =L26*O26 -> 300937 | AB26: =L26*I26*0.35/100 -> 191.1 | AD26: =SUM(AJ26,AM26,AP26) -> 0 | AE26: =SUM(R26,T26) -> 0 | AF26: =AD26-AE26 -> 0 | AH26: 0 | AI26: =AH26*AB26 -> 0 | AJ26: =AI26/L26/I26 -> 0 | AL26: =AK26*AB26 -> 0 | AM26: =AL26/L26/I26 -> 0 | AN26: 0 | AO26: =AN26*AB26 -> 0 | AP26: =AO26/L26/I26 -> 0 | AQ26: =SUM(AI26,AL26,AO26) -> 0 | AR26: =SUM(AJ26,AM26,AP26) -> 0 | AS26: =Z26 -> 0 | AT26: =AQ26-AS26 -> 0 | AU26: =O26/I26 -> 5.5116667 | AV26: =AU26-R26-T26 -> 5.5116667 | AW26: =(X26-AV26)/X26 -> 0.15074474 | AY26: =X26*100% -> 6.49 | AZ26: =Y26*50% -> 0 | BA26: =AY26+AZ26 -> 6.49 | BD26: Itu | BE26: HNK BR INDUSTRIA DE BEBIDAS LTDA. | BF26: 50.221.019/0001-36 | BG26: 387000650117 | BH26: Av Primo Schincariol | BI26: 2222 | BJ26: Chácara Flórida | BK26: 13312250 | BL26: Itu | BM26: SP
A27: =0.355*24/100 -> 0.0852 | C27: =B27/A27 -> 0 | D27: Premium | E27: Praya | F27: 634958 | G27: 1149563 | H27: CERVEJA PRAYA RECEITA CLÁSSICA LN 355ML | I27: 24 | J27: 84 | K27: =J27*26 -> 2184 | L27: =K27*2 -> 4368 | M27: =L27/J27 -> 52 | N27: =L27/K27 -> 2 | O27: 170.82 | P27: =O27/I27 -> 7.1175 | Q27: =R27*I27 -> 0 | R27: 0 | S27: =T27*I27 -> 0 | T27: 0 | U27: =SUM(R27,T27) -> 0 | V27: 0 | W27: 9.49 | X27: 8.49 | Z27: =L27*(Q27+S27) -> 0 | AA27: =L27*O27 -> 746141.76 | AB27: =L27*I27*0.35/100 -> 366.912 | AD27: =SUM(AJ27,AM27,AP27) -> 0 | AE27: =SUM(R27,T27) -> 0 | AF27: =AD27-AE27 -> 0 | AH27: 0 | AI27: =AH27*AB27 -> 0 | AJ27: =AI27/L27/I27 -> 0 | AL27: =AK27*AB27 -> 0 | AM27: =AL27/L27/I27 -> 0 | AN27: 0 | AO27: =AN27*AB27 -> 0 | AP27: =AO27/L27/I27 -> 0 | AQ27: =SUM(AI27,AL27,AO27) -> 0 | AR27: =SUM(AJ27,AM27,AP27) -> 0 | AS27: =Z27 -> 0 | AT27: =AQ27-AS27 -> 0 | AU27: =O27/I27 -> 7.1175 | AV27: =AU27-R27-T27 -> 7.1175 | AW27: =(X27-AV27)/X27 -> 0.16166078 | AY27: =X27*100% -> 8.49 | AZ27: =Y27*50% -> 0 | BA27: =AY27+AZ27 -> 8.49 | BD27: Itu | BE27: HNK BR INDUSTRIA DE BEBIDAS LTDA. | BF27: 50.221.019/0001-36 | BG27: 387000650117 | BH27: Av Primo Schincariol | BI27: 2222 | BJ27: Chácara Flórida | BK27: 13312250 | BL27: Itu | BM27: SP
A28: =0.6*12/100 -> 0.072 | C28: =B28/A28 -> 0 | D28: Premium | E28: Praya | F28: 634957 | G28: 1149565 | H28: CERVEJA PRAYA RECEITA CLÁSSICA 600ML | I28: 12 | J28: 60 | K28: =J28*26 -> 1560 | L28: =J28*15 -> 900 | M28: =L28/J28 -> 15 | N28: =L28/K28 -> 0.57692308 | O28: 136.71 | P28: =O28/I28 -> 11.3925 | Q28: =R28*I28 -> 0 | R28: 0 | S28: =T28*I28 -> 0 | T28: 0 | U28: =SUM(R28,T28) -> 0 | V28: 0 | W28: 15.19 | X28: 13.29 | Z28: =L28*(Q28+S28) -> 0 | AA28: =L28*O28 -> 123039 | AB28: =L28*I28*0.6/100 -> 64.8 | AD28: =SUM(AJ28,AM28,AP28) -> 0 | AE28: =SUM(R28,T28) -> 0 | AF28: =AD28-AE28 -> 0 | AH28: 0 | AI28: =AH28*AB28 -> 0 | AJ28: =AI28/L28/I28 -> 0 | AL28: =AK28*AB28 -> 0 | AM28: =AL28/L28/I28 -> 0 | AN28: 0 | AO28: =AN28*AB28 -> 0 | AP28: =AO28/L28/I28 -> 0 | AQ28: =SUM(AI28,AL28,AO28) -> 0 | AR28: =SUM(AJ28,AM28,AP28) -> 0 | AS28: =Z28 -> 0 | AT28: =AQ28-AS28 -> 0 | AU28: =O28/I28 -> 11.3925 | AV28: =AU28-R28-T28 -> 11.3925 | AW28: =(X28-AV28)/X28 -> 0.14277652 | AY28: =X28*100% -> 13.29 | AZ28: =Y28*50% -> 0 | BA28: =AY28+AZ28 -> 13.29 | BD28: Itu | BE28: HNK BR INDUSTRIA DE BEBIDAS LTDA. | BF28: 50.221.019/0001-36 | BG28: 387000650117 | BH28: Av Primo Schincariol | BI28: 2222 | BJ28: Chácara Flórida | BK28: 13312250 | BL28: Itu | BM28: SP
A29: 0.072 | B29: =VLOOKUP(F29,Planilha3!D:F,3,0) -> 7.4611665 | C29: =B29/A29 -> 103.62731 | D29: Craft | E29: Baden | F29: 902832 | G29: 1046669 | H29: CERVEJA BADEN IPA 600ML | I29: 12 | J29: 60 | K29: =J29*24 -> 1440 | L29: 120 | M29: =L29/J29 -> 2 | N29: =L29/K29 -> 0.083333333 | O29: 134.52 | P29: =O29/I29 -> 11.21 | Q29: =R29*I29 -> 0 | R29: 0 | S29: =T29*I29 -> 0 | T29: 0 | U29: =SUM(R29,T29) -> 0 | V29: 0 | W29: =VLOOKUP(F29,'[1]Proposta HNK para Tenda'!$F:$T,15,0) -> 14.19 | X29: =VLOOKUP(F29,'[1]Proposta HNK para Tenda'!$F:$U,16,0) -> 14.19 | Z29: =L29*(Q29+S29) -> 0 | AA29: =L29*O29 -> 16142.4 | AB29: =L29*12*0.6/100 -> 8.64 | AD29: =SUM(AJ29,AM29,AP29) -> 0 | AE29: =SUM(R29,T29) -> 0 | AF29: =AD29-AE29 -> 0 | AH29: 0 | AI29: =AH29*AB29 -> 0 | AJ29: =AI29/L29/I29 -> 0 | AL29: =AK29*AB29 -> 0 | AM29: =AL29/L29/I29 -> 0 | AN29: 0 | AO29: =AN29*AB29 -> 0 | AP29: =AO29/L29/I29 -> 0 | AQ29: =SUM(AI29,AL29,AO29) -> 0 | AR29: =SUM(AJ29,AM29,AP29) -> 0 | AS29: =Z29 -> 0 | AT29: =AQ29-AS29 -> 0 | AU29: =O29/I29 -> 11.21 | AV29: =AU29-R29-T29 -> 11.21 | AW29: =(X29-AV29)/X29 -> 0.21000705 | AY29: =X29*100% -> 14.19 | AZ29: =Y29*50% -> 0 | BA29: =AY29+AZ29 -> 14.19 | BD29: Itu | BE29: HNK BR INDUSTRIA DE BEBIDAS LTDA. | BF29: 50.221.019/0001-36 | BG29: 387000650117 | BH29: Av Primo Schincariol | BI29: 2222 | BJ29: Chácara Flórida | BK29: 13312250 | BL29: Itu | BM29: SP
A30: 0.072 | B30: =VLOOKUP(F30,Planilha3!D:F,3,0) -> 5.948199 | C30: =B30/A30 -> 82.613875 | D30: Craft | E30: Baden | F30: 900118 | G30: 1017028 | H30: CERVEJA BADEN GOLDEN 600ML | I30: 12 | J30: 60 | K30: =J30*24 -> 1440 | L30: 120 | M30: =L30/J30 -> 2 | N30: =L30/K30 -> 0.083333333 | O30: 134.52 | P30: =O30/I30 -> 11.21 | Q30: =R30*I30 -> 0 | R30: 0 | S30: =T30*I30 -> 0 | T30: 0 | U30: =SUM(R30,T30) -> 0 | V30: 0 | W30: =VLOOKUP(F30,'[1]Proposta HNK para Tenda'!$F:$T,15,0) -> 14.19 | X30: =VLOOKUP(F30,'[1]Proposta HNK para Tenda'!$F:$U,16,0) -> 14.19 | Z30: =L30*(Q30+S30) -> 0 | AA30: =L30*O30 -> 16142.4 | AB30: =L30*12*0.6/100 -> 8.64 | AD30: =SUM(AJ30,AM30,AP30) -> 0 | AE30: =SUM(R30,T30) -> 0 | AF30: =AD30-AE30 -> 0 | AH30: 0 | AI30: =AH30*AB30 -> 0 | AJ30: =AI30/L30/I30 -> 0 | AL30: =AK30*AB30 -> 0 | AM30: =AL30/L30/I30 -> 0 | AN30: 0 | AO30: =AN30*AB30 -> 0 | AP30: =AO30/L30/I30 -> 0 | AQ30: =SUM(AI30,AL30,AO30) -> 0 | AR30: =SUM(AJ30,AM30,AP30) -> 0 | AS30: =Z30 -> 0 | AT30: =AQ30-AS30 -> 0 | AU30: =O30/I30 -> 11.21 | AV30: =AU30-R30-T30 -> 11.21 | AW30: =(X30-AV30)/X30 -> 0.21000705 | AY30: =X30*100% -> 14.19 | AZ30: =Y30*50% -> 0 | BA30: =AY30+AZ30 -> 14.19 | BD30: Itu | BE30: HNK BR INDUSTRIA DE BEBIDAS LTDA. | BF30: 50.221.019/0001-36 | BG30: 387000650117 | BH30: Av Primo Schincariol | BI30: 2222 | BJ30: Chácara Flórida | BK30: 13312250 | BL30: Itu | BM30: SP
A31: 0.042 | B31: =VLOOKUP(F31,Planilha3!D:F,3,0) -> 27.698971 | C31: =B31/A31 -> 659.49932 | D31: Craft | E31: Baden | F31: 904451 | G31: 1147973 | H31: CERVEJA BADEN IPA LA 350ML | I31: 12 | J31: 280 | K31: =J31*24 -> 6720 | L31: 6720 | M31: =L31/J31 -> 24 | N31: =M31/26 -> 0.92307692 | O31: 57.73 | P31: =O31/I31 -> 4.8108333 | Q31: =R31*I31 -> 3 | R31: 0.25 | S31: =T31*I31 -> 0.72 | T31: 0.06 | U31: =SUM(R31,T31) -> 0.31 | V31: 0.31 | W31: =VLOOKUP(F31,'[1]Proposta HNK para Tenda'!$F:$T,15,0) -> 6.09 | X31: =VLOOKUP(F31,'[1]Proposta HNK para Tenda'!$F:$U,16,0) -> 5.39 | Z31: =L31*(Q31+S31) -> 24998.4 | AA31: =L31*O31 -> 387945.6 | AB31: =L31*12*0.35/100 -> 282.24 | AD31: =SUM(AJ31,AM31,AP31) -> 0.3143 | AE31: =SUM(R31,T31) -> 0.31 | AF31: =AD31-AE31 -> 0.0043 | AH31: 89.8 | AI31: =AH31*AB31 -> 25345.152 | AJ31: =AI31/L31/I31 -> 0.3143 | AL31: =AK31*AB31 -> 0 | AM31: =AL31/L31/I31 -> 0 | AN31: 0 | AO31: =AN31*AB31 -> 0 | AP31: =AO31/L31/I31 -> 0 | AQ31: =SUM(AI31,AL31,AO31) -> 25345.152 | AR31: =SUM(AJ31,AM31,AP31) -> 0.3143 | AS31: =Z31 -> 24998.4 | AT31: =AQ31-AS31 -> 346.752 | AU31: =O31/I31 -> 4.8108333 | AV31: =AU31-R31-T31 -> 4.5008333 | AW31: =(X31-AV31)/X31 -> 0.16496599 | AY31: =X31*100% -> 5.39 | AZ31: =Y31*50% -> 0 | BA31: =AY31+AZ31 -> 5.39 | BD31: Itu | BE31: HNK BR INDUSTRIA DE BEBIDAS LTDA. | BF31: 50.221.019/0001-36 | BG31: 387000650117 | BH31: Av Primo Schincariol | BI31: 2222 | BJ31: Chácara Flórida | BK31: 13312250 | BL31: Itu | BM31: SP
A32: 0.072 | B32: =VLOOKUP(F32,Planilha3!D:F,3,0) -> 2.958687 | C32: =B32/A32 -> 41.092875 | D32: Craft | E32: Baden | F32: 904742 | G32: 1169732 | H32: CERVEJA BADEN PEACH 600ML | I32: 12 | J32: 60 | K32: =J32*24 -> 1440 | L32: 120 | M32: =L32/J32 -> 2 | N32: =L32/K32 -> 0.083333333 | O32: 134.52 | P32: =O32/I32 -> 11.21 | Q32: =R32*I32 -> 0 | R32: 0 | S32: =T32*I32 -> 0 | T32: 0 | U32: =SUM(R32,T32) -> 0 | V32: 0 | W32: =VLOOKUP(F32,'[1]Proposta HNK para Tenda'!$F:$T,15,0) -> 14.19 | X32: =VLOOKUP(F32,'[1]Proposta HNK para Tenda'!$F:$U,16,0) -> 14.19 | Z32: =L32*(Q32+S32) -> 0 | AA32: =L32*O32 -> 16142.4 | AB32: =L32*12*0.6/100 -> 8.64 | AD32: =SUM(AJ32,AM32,AP32) -> 0 | AE32: =SUM(R32,T32) -> 0 | AF32: =AD32-AE32 -> 0 | AH32: 0 | AI32: =AH32*AB32 -> 0 | AJ32: =AI32/L32/I32 -> 0 | AL32: =AK32*AB32 -> 0 | AM32: =AL32/L32/I32 -> 0 | AN32: 0 | AO32: =AN32*AB32 -> 0 | AP32: =AO32/L32/I32 -> 0 | AQ32: =SUM(AI32,AL32,AO32) -> 0 | AR32: =SUM(AJ32,AM32,AP32) -> 0 | AS32: =Z32 -> 0 | AT32: =AQ32-AS32 -> 0 | AU32: =O32/I32 -> 11.21 | AV32: =AU32-R32-T32 -> 11.21 | AW32: =(X32-AV32)/X32 -> 0.21000705 | AY32: =X32*100% -> 14.19 | AZ32: =Y32*50% -> 0 | BA32: =AY32+AZ32 -> 14.19 | BD32: Itu | BE32: HNK BR INDUSTRIA DE BEBIDAS LTDA. | BF32: 50.221.019/0001-36 | BG32: 387000650117 | BH32: Av Primo Schincariol | BI32: 2222 | BJ32: Chácara Flórida | BK32: 13312250 | BL32: Itu | BM32: SP
A33: 0.042 | B33: =VLOOKUP(F33,Planilha3!D:F,3,0) -> 12.871838 | C33: =B33/A33 -> 306.47234 | D33: Craft | E33: Baden | F33: 904743 | G33: 1170232 | H33: CERVEJA BADEN PEACH LA 350ML | I33: 12 | J33: 280 | K33: =J33*24 -> 6720 | L33: 3920 | M33: =L33/J33 -> 14 | N33: =L33/K33 -> 0.58333333 | O33: 57.73 | P33: =O33/I33 -> 4.8108333 | Q33: =R33*I33 -> 3 | R33: 0.25 | S33: =T33*I33 -> 0.72 | T33: 0.06 | U33: =SUM(R33,T33) -> 0.31 | V33: 0.31 | W33: =VLOOKUP(F33,'[1]Proposta HNK para Tenda'!$F:$T,15,0) -> 6.09 | X33: =VLOOKUP(F33,'[1]Proposta HNK para Tenda'!$F:$U,16,0) -> 5.39 | Z33: =L33*(Q33+S33) -> 14582.4 | AA33: =L33*O33 -> 226301.6 | AB33: =L33*12*0.35/100 -> 164.64 | AD33: =SUM(AJ33,AM33,AP33) -> 0.3143 | AE33: =SUM(R33,T33) -> 0.31 | AF33: =AD33-AE33 -> 0.0043 | AH33: 89.8 | AI33: =AH33*AB33 -> 14784.672 | AJ33: =AI33/L33/I33 -> 0.3143 | AL33: =AK33*AB33 -> 0 | AM33: =AL33/L33/I33 -> 0 | AN33: 0 | AO33: =AN33*AB33 -> 0 | AP33: =AO33/L33/I33 -> 0 | AQ33: =SUM(AI33,AL33,AO33) -> 14784.672 | AR33: =SUM(AJ33,AM33,AP33) -> 0.3143 | AS33: =Z33 -> 14582.4 | AT33: =AQ33-AS33 -> 202.272 | AU33: =O33/I33 -> 4.8108333 | AV33: =AU33-R33-T33 -> 4.5008333 | AW33: =(X33-AV33)/X33 -> 0.16496599 | AY33: =X33*100% -> 5.39 | AZ33: =Y33*50% -> 0 | BA33: =AY33+AZ33 -> 5.39 | BD33: Itu | BE33: HNK BR INDUSTRIA DE BEBIDAS LTDA. | BF33: 50.221.019/0001-36 | BG33: 387000650117 | BH33: Av Primo Schincariol | BI33: 2222 | BJ33: Chácara Flórida | BK33: 13312250 | BL33: Itu | BM33: SP
A34: 0.072 | B34: =VLOOKUP(F34,Planilha3!D:F,3,0) -> 5.1478175 | C34: =B34/A34 -> 71.497465 | D34: Craft | E34: Baden | F34: 900109 | G34: 1017027 | H34: CERVEJA BADEN CRISTAL 600ML | I34: 12 | J34: 60 | K34: =J34*24 -> 1440 | L34: 240 | M34: =L34/J34 -> 4 | N34: =L34/K34 -> 0.16666667 | O34: 134.52 | P34: =O34/I34 -> 11.21 | Q34: =R34*I34 -> 0 | R34: 0 | S34: =T34*I34 -> 0 | T34: 0 | U34: =SUM(R34,T34) -> 0 | V34: 0 | W34: =VLOOKUP(F34,'[1]Proposta HNK para Tenda'!$F:$T,15,0) -> 14.19 | X34: =VLOOKUP(F34,'[1]Proposta HNK para Tenda'!$F:$U,16,0) -> 14.19 | Z34: =L34*(Q34+S34) -> 0 | AA34: =L34*O34 -> 32284.8 | AB34: =L34*12*0.6/100 -> 17.28 | AD34: =SUM(AJ34,AM34,AP34) -> 0 | AE34: =SUM(R34,T34) -> 0 | AF34: =AD34-AE34 -> 0 | AH34: 0 | AI34: =AH34*AB34 -> 0 | AJ34: =AI34/L34/I34 -> 0 | AL34: =AK34*AB34 -> 0 | AM34: =AL34/L34/I34 -> 0 | AN34: 0 | AO34: =AN34*AB34 -> 0 | AP34: =AO34/L34/I34 -> 0 | AQ34: =SUM(AI34,AL34,AO34) -> 0 | AR34: =SUM(AJ34,AM34,AP34) -> 0 | AS34: =Z34 -> 0 | AT34: =AQ34-AS34 -> 0 | AU34: =O34/I34 -> 11.21 | AV34: =AU34-R34-T34 -> 11.21 | AW34: =(X34-AV34)/X34 -> 0.21000705 | AY34: =X34*100% -> 14.19 | AZ34: =Y34*50% -> 0 | BA34: =AY34+AZ34 -> 14.19 | BD34: Itu | BE34: HNK BR INDUSTRIA DE BEBIDAS LTDA. | BF34: 50.221.019/0001-36 | BG34: 387000650117 | BH34: Av Primo Schincariol | BI34: 2222 | BJ34: Chácara Flórida | BK34: 13312250 | BL34: Itu | BM34: SP
A35: 0.042 | B35: =VLOOKUP(F35,Planilha3!D:F,3,0) -> 8.3101108 | C35: =B35/A35 -> 197.85978 | D35: Craft | E35: Baden | F35: 904441 | G35: 1147975 | H35: CERVEJA BADEN CRISTAL LA 350ML | I35: 12 | J35: 280 | K35: =J35*24 -> 6720 | L35: 6720 | M35: =L35/J35 -> 24 | N35: =L35/K35 -> 1 | O35: 57.73 | P35: =O35/I35 -> 4.8108333 | Q35: =R35*I35 -> 3 | R35: 0.25 | S35: =T35*I35 -> 0.72 | T35: 0.06 | U35: =SUM(R35,T35) -> 0.31 | V35: 0.31 | W35: =VLOOKUP(F35,'[1]Proposta HNK para Tenda'!$F:$T,15,0) -> 6.09 | X35: =VLOOKUP(F35,'[1]Proposta HNK para Tenda'!$F:$U,16,0) -> 5.39 | Z35: =L35*(Q35+S35) -> 24998.4 | AA35: =L35*O35 -> 387945.6 | AB35: =L35*12*0.35/100 -> 282.24 | AD35: =SUM(AJ35,AM35,AP35) -> 0.3143 | AE35: =SUM(R35,T35) -> 0.31 | AF35: =AD35-AE35 -> 0.0043 | AH35: 89.8 | AI35: =AH35*AB35 -> 25345.152 | AJ35: =AI35/L35/I35 -> 0.3143 | AL35: =AK35*AB35 -> 0 | AM35: =AL35/L35/I35 -> 0 | AN35: 0 | AO35: =AN35*AB35 -> 0 | AP35: =AO35/L35/I35 -> 0 | AQ35: =SUM(AI35,AL35,AO35) -> 25345.152 | AR35: =SUM(AJ35,AM35,AP35) -> 0.3143 | AS35: =Z35 -> 24998.4 | AT35: =AQ35-AS35 -> 346.752 | AU35: =O35/I35 -> 4.8108333 | AV35: =AU35-R35-T35 -> 4.5008333 | AW35: =(X35-AV35)/X35 -> 0.16496599 | AY35: =X35*100% -> 5.39 | AZ35: =Y35*50% -> 0 | BA35: =AY35+AZ35 -> 5.39 | BD35: Itu | BE35: HNK BR INDUSTRIA DE BEBIDAS LTDA. | BF35: 50.221.019/0001-36 | BG35: 387000650117 | BH35: Av Primo Schincariol | BI35: 2222 | BJ35: Chácara Flórida | BK35: 13312250 | BL35: Itu | BM35: SP
A36: 0.072 | B36: =VLOOKUP(F36,Planilha3!D:F,3,0) -> 6.1719833 | C36: =B36/A36 -> 85.72199 | D36: Craft | E36: Baden | F36: 901162 | G36: 1046689 | H36: CERVEJA BADEN WITIBIER 600ML | I36: 12 | J36: 60 | K36: =J36*24 -> 1440 | L36: 120 | M36: =L36/J36 -> 2 | N36: =L36/K36 -> 0.083333333 | O36: 134.52 | P36: =O36/I36 -> 11.21 | Q36: =R36*I36 -> 0 | R36: 0 | S36: =T36*I36 -> 0 | T36: 0 | U36: =SUM(R36,T36) -> 0 | V36: 0 | W36: =VLOOKUP(F36,'[1]Proposta HNK para Tenda'!$F:$T,15,0) -> 14.19 | X36: =VLOOKUP(F36,'[1]Proposta HNK para Tenda'!$F:$U,16,0) -> 14.19 | Z36: =L36*(Q36+S36) -> 0 | AA36: =L36*O36 -> 16142.4 | AB36: =L36*12*0.6/100 -> 8.64 | AD36: =SUM(AJ36,AM36,AP36) -> 0 | AE36: =SUM(R36,T36) -> 0 | AF36: =AD36-AE36 -> 0 | AH36: 0 | AI36: =AH36*AB36 -> 0 | AJ36: =AI36/L36/I36 -> 0 | AL36: =AK36*AB36 -> 0 | AM36: =AL36/L36/I36 -> 0 | AN36: 0 | AO36: =AN36*AB36 -> 0 | AP36: =AO36/L36/I36 -> 0 | AQ36: =SUM(AI36,AL36,AO36) -> 0 | AR36: =SUM(AJ36,AM36,AP36) -> 0 | AS36: =Z36 -> 0 | AT36: =AQ36-AS36 -> 0 | AU36: =O36/I36 -> 11.21 | AV36: =AU36-R36-T36 -> 11.21 | AW36: =(X36-AV36)/X36 -> 0.21000705 | AY36: =X36*100% -> 14.19 | AZ36: =Y36*50% -> 0 | BA36: =AY36+AZ36 -> 14.19 | BD36: Itu | BE36: HNK BR INDUSTRIA DE BEBIDAS LTDA. | BF36: 50.221.019/0001-36 | BG36: 387000650117 | BH36: Av Primo Schincariol | BI36: 2222 | BJ36: Chácara Flórida | BK36: 13312250 | BL36: Itu | BM36: SP
A37: 0.042 | B37: =VLOOKUP(F37,Planilha3!D:F,3,0) -> 21.928826 | C37: =B37/A37 -> 522.11489 | D37: Craft | E37: Baden | F37: 904193 | G37: 1150647 | H37: CERVEJA BADEN WITBIER LA 350ML | I37: 12 | J37: 280 | K37: =J37*24 -> 6720 | L37: 6720 | M37: =L37/J37 -> 24 | N37: =L37/K37 -> 1 | O37: 57.73 | P37: =O37/I37 -> 4.8108333 | Q37: =R37*I37 -> 3 | R37: 0.25 | S37: =T37*I37 -> 0.72 | T37: 0.06 | U37: =SUM(R37,T37) -> 0.31 | V37: 0.31 | W37: =VLOOKUP(F37,'[1]Proposta HNK para Tenda'!$F:$T,15,0) -> 6.09 | X37: =VLOOKUP(F37,'[1]Proposta HNK para Tenda'!$F:$U,16,0) -> 5.39 | Z37: =L37*(Q37+S37) -> 24998.4 | AA37: =L37*O37 -> 387945.6 | AB37: =L37*12*0.35/100 -> 282.24 | AD37: =SUM(AJ37,AM37,AP37) -> 0.3143 | AE37: =SUM(R37,T37) -> 0.31 | AF37: =AD37-AE37 -> 0.0043 | AH37: 89.8 | AI37: =AH37*AB37 -> 25345.152 | AJ37: =AI37/L37/I37 -> 0.3143 | AL37: =AK37*AB37 -> 0 | AM37: =AL37/L37/I37 -> 0 | AN37: 0 | AO37: =AN37*AB37 -> 0 | AP37: =AO37/L37/I37 -> 0 | AQ37: =SUM(AI37,AL37,AO37) -> 25345.152 | AR37: =SUM(AJ37,AM37,AP37) -> 0.3143 | AS37: =Z37 -> 24998.4 | AT37: =AQ37-AS37 -> 346.752 | AU37: =O37/I37 -> 4.8108333 | AV37: =AU37-R37-T37 -> 4.5008333 | AW37: =(X37-AV37)/X37 -> 0.16496599 | AY37: =X37*100% -> 5.39 | AZ37: =Y37*50% -> 0 | BA37: =AY37+AZ37 -> 5.39 | BD37: Itu | BE37: HNK BR INDUSTRIA DE BEBIDAS LTDA. | BF37: 50.221.019/0001-36 | BG37: 387000650117 | BH37: Av Primo Schincariol | BI37: 2222 | BJ37: Chácara Flórida | BK37: 13312250 | BL37: Itu | BM37: SP
A38: 0.042 | B38: =VLOOKUP(F38,Planilha3!D:F,3,0) -> 12.387493 | C38: =B38/A38 -> 294.94032 | D38: Craft | E38: Blue Moon | F38: 904612 | G38: 1155188 | H38: CERVEJA BLUE MOON LA 350ML | I38: 12 | J38: 280 | K38: =J38*24 -> 6720 | L38: 560 | M38: =L38/J38 -> 2 | N38: =L38/K38 -> 0.083333333 | O38: 85.23 | P38: =O38/I38 -> 7.1025 | Q38: =R38*I38 -> 10.8 | R38: 0.9 | S38: =T38*I38 -> 0.24 | T38: 0.02 | U38: =SUM(R38,T38) -> 0.92 | V38: 0.92 | W38: =VLOOKUP(F38,'[1]Proposta HNK para Tenda'!$F:$T,15,0) -> 8.99 | X38: =VLOOKUP(F38,'[1]Proposta HNK para Tenda'!$F:$U,16,0) -> 6.99 | Z38: =L38*(Q38+S38) -> 6182.4 | AA38: =L38*O38 -> 47728.8 | AB38: =L38*12*0.35/100 -> 23.52 | AD38: =SUM(AJ38,AM38,AP38) -> 0.93051 | AE38: =SUM(R38,T38) -> 0.92 | AF38: =AD38-AE38 -> 0.01051 | AH38: 265.86 | AI38: =AH38*AB38 -> 6253.0272 | AJ38: =AI38/L38/I38 -> 0.93051 | AL38: =AK38*AB38 -> 0 | AM38: =AL38/L38/I38 -> 0 | AN38: 0 | AO38: =AN38*AB38 -> 0 | AP38: =AO38/L38/I38 -> 0 | AQ38: =SUM(AI38,AL38,AO38) -> 6253.0272 | AR38: =SUM(AJ38,AM38,AP38) -> 0.93051 | AS38: =Z38 -> 6182.4 | AT38: =AQ38-AS38 -> 70.6272 | AU38: =O38/I38 -> 7.1025 | AV38: =AU38-R38-T38 -> 6.1825 | AW38: =(X38-AV38)/X38 -> 0.11552217 | AY38: =X38*100% -> 6.99 | AZ38: =Y38*50% -> 0 | BA38: =AY38+AZ38 -> 6.99 | BD38: Itu | BE38: HNK BR INDUSTRIA DE BEBIDAS LTDA. | BF38: 50.221.019/0001-36 | BG38: 387000650117 | BH38: Av Primo Schincariol | BI38: 2222 | BJ38: Chácara Flórida | BK38: 13312250 | BL38: Itu | BM38: SP
A39: 0.0852 | B39: =VLOOKUP(F39,Planilha3!D:F,3,0) -> 5.009831 | C39: =B39/A39 -> 58.800833 | D39: Craft | E39: Blue Moon | F39: 904602 | G39: 1160869 | H39: CERVEJA BLUE MOON LN 355ML | I39: 24 | J39: 56 | K39: =J39*24 -> 1344 | L39: 168 | M39: =L39/J39 -> 3 | N39: =L39/K39 -> 0.125 | O39: 208.37 | P39: =O39/I39 -> 8.6820833 | Q39: =R39*I39 -> 0 | R39: 0 | S39: =T39*I39 -> 0 | T39: 0 | U39: =SUM(R39,T39) -> 0 | V39: 0 | W39: =VLOOKUP(F39,'[1]Proposta HNK para Tenda'!$F:$T,15,0) -> 10.99 | X39: =VLOOKUP(F39,'[1]Proposta HNK para Tenda'!$F:$U,16,0) -> 10.99 | Z39: =L39*(Q39+S39) -> 0 | AA39: =L39*O39 -> 35006.16 | AB39: =L39*24*0.355/100 -> 14.3136 | AD39: =SUM(AJ39,AM39,AP39) -> 0 | AE39: =SUM(R39,T39) -> 0 | AF39: =AD39-AE39 -> 0 | AH39: 0 | AI39: =AH39*AB39 -> 0 | AJ39: =AI39/L39/I39 -> 0 | AL39: =AK39*AB39 -> 0 | AM39: =AL39/L39/I39 -> 0 | AN39: 0 | AO39: =AN39*AB39 -> 0 | AP39: =AO39/L39/I39 -> 0 | AQ39: =SUM(AI39,AL39,AO39) -> 0 | AR39: =SUM(AJ39,AM39,AP39) -> 0 | AS39: =Z39 -> 0 | AT39: =AQ39-AS39 -> 0 | AU39: =O39/I39 -> 8.6820833 | AV39: =AU39-R39-T39 -> 8.6820833 | AW39: =(X39-AV39)/X39 -> 0.21000152 | AY39: =X39*100% -> 10.99 | AZ39: =Y39*50% -> 0 | BA39: =AY39+AZ39 -> 10.99 | BD39: Itu | BE39: HNK BR INDUSTRIA DE BEBIDAS LTDA. | BF39: 50.221.019/0001-36 | BG39: 387000650117 | BH39: Av Primo Schincariol | BI39: 2222 | BJ39: Chácara Flórida | BK39: 13312250 | BL39: Itu | BM39: SP
A40: 0.042 | B40: =VLOOKUP(F40,Planilha3!D:F,3,0) -> 17.452561 | C40: =B40/A40 -> 415.53717 | D40: Craft | E40: Eisenbahn | F40: 903681 | G40: 1110090 | H40: CERVEJA EISENBAHN IPA LATA 350 ML | I40: 12 | J40: 280 | K40: =J40*24 -> 6720 | L40: 3920 | M40: =L40/J40 -> 14 | N40: =L40/K40 -> 0.58333333 | O40: 53.94 | P40: =O40/I40 -> 4.495 | Q40: =R40*I40 -> 3.24 | R40: 0.27 | S40: =T40*I40 -> 0 | T40: 0 | U40: =SUM(R40,T40) -> 0.27 | V40: 0.27 | W40: 5.69 | X40: 5.09 | Z40: =L40*(Q40+S40) -> 12700.8 | AA40: =L40*O40 -> 211444.8 | AB40: =L40*12*0.35/100 -> 164.64 | AD40: =SUM(AJ40,AM40,AP40) -> 0.26691 | AE40: =SUM(R40,T40) -> 0.27 | AF40: =AD40-AE40 -> -0.00309 | AH40: 76.26 | AI40: =AH40*AB40 -> 12555.446 | AJ40: =AI40/L40/I40 -> 0.26691 | AL40: =AK40*AB40 -> 0 | AM40: =AL40/L40/I40 -> 0 | AN40: 0 | AO40: =AN40*AB40 -> 0 | AP40: =AO40/L40/I40 -> 0 | AQ40: =SUM(AI40,AL40,AO40) -> 12555.446 | AR40: =SUM(AJ40,AM40,AP40) -> 0.26691 | AS40: =Z40 -> 12700.8 | AT40: =AQ40-AS40 -> -145.3536 | AU40: =O40/I40 -> 4.495 | AV40: =AU40-R40-T40 -> 4.225 | AW40: =(X40-AV40)/X40 -> 0.16994106 | AY40: =X40*100% -> 5.09 | AZ40: =Y40*50% -> 0 | BA40: =AY40+AZ40 -> 5.09 | BD40: Itu | BE40: HNK BR INDUSTRIA DE BEBIDAS LTDA. | BF40: 50.221.019/0001-36 | BG40: 387000650117 | BH40: Av Primo Schincariol | BI40: 2222 | BJ40: Chácara Flórida | BK40: 13312250 | BL40: Itu | BM40: SP
A41: 0.0426 | B41: =VLOOKUP(F41,Planilha3!D:F,3,0) -> 5.8949334 | C41: =B41/A41 -> 138.37872 | D41: Craft | E41: Eisenbahn | F41: 903741 | G41: 1080284 | H41: CERVEJA EISENBAHN IPA LN 355ML | I41: 12 | J41: 175 | K41: =J41*24 -> 4200 | L41: 700 | M41: =L41/J41 -> 4 | N41: =L41/K41 -> 0.16666667 | O41: 64.37 | P41: =O41/I41 -> 5.3641667 | Q41: =R41*I41 -> 0 | R41: 0 | S41: =T41*I41 -> 0 | T41: 0 | U41: =SUM(R41,T41) -> 0 | V41: 0 | W41: 6.79 | X41: 6.79 | Z41: =L41*(Q41+S41) -> 0 | AA41: =L41*O41 -> 45059 | AB41: =L41*12*0.355/100 -> 29.82 | AD41: =SUM(AJ41,AM41,AP41) -> 0 | AE41: =SUM(R41,T41) -> 0 | AF41: =AD41-AE41 -> 0 | AH41: 0 | AI41: =AH41*AB41 -> 0 | AJ41: =AI41/L41/I41 -> 0 | AL41: =AK41*AB41 -> 0 | AM41: =AL41/L41/I41 -> 0 | AN41: 0 | AO41: =AN41*AB41 -> 0 | AP41: =AO41/L41/I41 -> 0 | AQ41: =SUM(AI41,AL41,AO41) -> 0 | AR41: =SUM(AJ41,AM41,AP41) -> 0 | AS41: =Z41 -> 0 | AT41: =AQ41-AS41 -> 0 | AU41: =O41/I41 -> 5.3641667 | AV41: =AU41-R41-T41 -> 5.3641667 | AW41: =(X41-AV41)/X41 -> 0.20999018 | AY41: =X41*100% -> 6.79 | AZ41: =Y41*50% -> 0 | BA41: =AY41+AZ41 -> 6.79 | BD41: Itu | BE41: HNK BR INDUSTRIA DE BEBIDAS LTDA. | BF41: 50.221.019/0001-36 | BG41: 387000650117 | BH41: Av Primo Schincariol | BI41: 2222 | BJ41: Chácara Flórida | BK41: 13312250 | BL41: Itu | BM41: SP
A42: 0.0426 | B42: =VLOOKUP(F42,Planilha3!D:F,3,0) -> 5.6291775 | C42: =B42/A42 -> 132.14032 | D42: Craft | E42: Eisenbahn | F42: 902544 | G42: 1041649 | H42: CERVEJA EISENBAHN PALE ALE LN 355ML | I42: 12 | J42: 175 | K42: =J42*24 -> 4200 | L42: 700 | M42: =L42/J42 -> 4 | N42: =L42/K42 -> 0.16666667 | O42: 64.37 | P42: =O42/I42 -> 5.3641667 | Q42: =R42*I42 -> 0 | R42: 0 | S42: =T42*I42 -> 0 | T42: 0 | U42: =SUM(R42,T42) -> 0 | V42: 0 | W42: 6.79 | X42: 6.79 | Z42: =L42*(Q42+S42) -> 0 | AA42: =L42*O42 -> 45059 | AB42: =L42*12*0.355/100 -> 29.82 | AD42: =SUM(AJ42,AM42,AP42) -> 0 | AE42: =SUM(R42,T42) -> 0 | AF42: =AD42-AE42 -> 0 | AH42: 0 | AI42: =AH42*AB42 -> 0 | AJ42: =AI42/L42/I42 -> 0 | AL42: =AK42*AB42 -> 0 | AM42: =AL42/L42/I42 -> 0 | AN42: 0 | AO42: =AN42*AB42 -> 0 | AP42: =AO42/L42/I42 -> 0 | AQ42: =SUM(AI42,AL42,AO42) -> 0 | AR42: =SUM(AJ42,AM42,AP42) -> 0 | AS42: =Z42 -> 0 | AT42: =AQ42-AS42 -> 0 | AU42: =O42/I42 -> 5.3641667 | AV42: =AU42-R42-T42 -> 5.3641667 | AW42: =(X42-AV42)/X42 -> 0.20999018 | AY42: =X42*100% -> 6.79 | AZ42: =Y42*50% -> 0 | BA42: =AY42+AZ42 -> 6.79 | BD42: Itu | BE42: HNK BR INDUSTRIA DE BEBIDAS LTDA. | BF42: 50.221.019/0001-36 | BG42: 387000650117 | BH42: Av Primo Schincariol | BI42: 2222 | BJ42: Chácara Flórida | BK42: 13312250 | BL42: Itu | BM42: SP
A43: 0.042 | B43: =VLOOKUP(F43,Planilha3!D:F,3,0) -> 33.175375 | C43: =B43/A43 -> 789.88988 | D43: Craft | E43: Eisenbahn | F43: 903683 | G43: 1110091 | H43: CERVEJA EISENBAHN PALE ALE LT 350ML | I43: 12 | J43: 280 | K43: =J43*24 -> 6720 | L43: 840 | M43: =L43/J43 -> 3 | N43: =L43/K43 -> 0.125 | O43: 53.94 | P43: =O43/I43 -> 4.495 | Q43: =R43*I43 -> 3.24 | R43: 0.27 | S43: =T43*I43 -> 0 | T43: 0 | U43: =SUM(R43,T43) -> 0.27 | V43: 0.27 | W43: 5.69 | X43: 5.09 | Z43: =L43*(Q43+S43) -> 2721.6 | AA43: =L43*O43 -> 45309.6 | AB43: =L43*12*0.35/100 -> 35.28 | AD43: =SUM(AJ43,AM43,AP43) -> 0.26691 | AE43: =SUM(R43,T43) -> 0.27 | AF43: =AD43-AE43 -> -0.00309 | AH43: 76.26 | AI43: =AH43*AB43 -> 2690.4528 | AJ43: =AI43/L43/I43 -> 0.26691 | AL43: =AK43*AB43 -> 0 | AM43: =AL43/L43/I43 -> 0 | AN43: 0 | AO43: =AN43*AB43 -> 0 | AP43: =AO43/L43/I43 -> 0 | AQ43: =SUM(AI43,AL43,AO43) -> 2690.4528 | AR43: =SUM(AJ43,AM43,AP43) -> 0.26691 | AS43: =Z43 -> 2721.6 | AT43: =AQ43-AS43 -> -31.1472 | AU43: =O43/I43 -> 4.495 | AV43: =AU43-R43-T43 -> 4.225 | AW43: =(X43-AV43)/X43 -> 0.16994106 | AY43: =X43*100% -> 5.09 | AZ43: =Y43*50% -> 0 | BA43: =AY43+AZ43 -> 5.09 | BD43: Itu | BE43: HNK BR INDUSTRIA DE BEBIDAS LTDA. | BF43: 50.221.019/0001-36 | BG43: 387000650117 | BH43: Av Primo Schincariol | BI43: 2222 | BJ43: Chácara Flórida | BK43: 13312250 | BL43: Itu | BM43: SP
A44: 0.042 | B44: 0 | C44: =B44/A44 -> 0 | D44: Craft | E44: Eisenbahn | F44: 904773 | G44: 1170235 | H44: CERVEJA EISENBAHN SESSION IPA LA 350ML | I44: 12 | J44: 280 | K44: =J44*24 -> 6720 | L44: 1400 | M44: =L44/J44 -> 5 | N44: =L44/K44 -> 0.20833333 | O44: 53.94 | P44: =O44/I44 -> 4.495 | Q44: =R44*I44 -> 3.24 | R44: 0.27 | S44: =T44*I44 -> 0 | T44: 0 | U44: =SUM(R44,T44) -> 0.27 | V44: 0.27 | W44: 5.69 | X44: 5.09 | Z44: =L44*(Q44+S44) -> 4536 | AA44: =L44*O44 -> 75516 | AB44: =L44*12*0.35/100 -> 58.8 | AD44: =SUM(AJ44,AM44,AP44) -> 0.26691 | AE44: =SUM(R44,T44) -> 0.27 | AF44: =AD44-AE44 -> -0.00309 | AH44: 76.26 | AI44: =AH44*AB44 -> 4484.088 | AJ44: =AI44/L44/I44 -> 0.26691 | AL44: =AK44*AB44 -> 0 | AM44: =AL44/L44/I44 -> 0 | AN44: 0 | AO44: =AN44*AB44 -> 0 | AP44: =AO44/L44/I44 -> 0 | AQ44: =SUM(AI44,AL44,AO44) -> 4484.088 | AR44: =SUM(AJ44,AM44,AP44) -> 0.26691 | AS44: =Z44 -> 4536 | AT44: =AQ44-AS44 -> -51.912 | AU44: =O44/I44 -> 4.495 | AV44: =AU44-R44-T44 -> 4.225 | AW44: =(X44-AV44)/X44 -> 0.16994106 | AY44: =X44*100% -> 5.09 | AZ44: =Y44*50% -> 0 | BA44: =AY44+AZ44 -> 5.09 | BD44: Itu | BE44: HNK BR INDUSTRIA DE BEBIDAS LTDA. | BF44: 50.221.019/0001-36 | BG44: 387000650117 | BH44: Av Primo Schincariol | BI44: 2222 | BJ44: Chácara Flórida | BK44: 13312250 | BL44: Itu | BM44: SP
